Workbook

Sheet Dashboard
A1: Benefit growth test - 100 projects, 60-yr horizon (2026-2085): raw, growth, and growth with no cash penalty
A2: Raw = LIN40 benefits as-is. Growth = calendar-year real growth U(1%,3%) (project 1 +3%, project 28 -2%). Envelope 210 $M p.a. = max(pro-rata s2000 124.6, largest single-project annual spend 206.9) rounded up to $10M, so every project fits without pre-banking. All values link to the model sheets.
A4: Headline | B4: Raw | C4: Growth | D4: Growth, no cash penalty | F4: Schedule shift by growth band (growth vs raw)
A5: Total PV benefits ($M) | B5: ='Raw profile'!J17 -> 7410.1203 | C5: ='Growth profile'!J17 -> 13627.303 | D5: ='Growth (no penalty)'!J17 -> 13893.822 | F5: Growth band | G5: Projects | H5: Avg shift (yrs) | I5: Deferred | J5: Pinned to 2085 | K5: Accelerated
A6: Project 1 start year (BCR 7, +3%) | B6: ='Raw profile'!I24 -> 2026 | C6: ='Growth profile'!I24 -> 2039 | D6: ='Growth (no penalty)'!I24 -> 2040 | F6: shrinking | G6: =COUNTIF(Comparison!$N$5:$N$104,F6) -> 1 | H6: =IFERROR(AVERAGEIF(Comparison!$N$5:$N$104,F6,Comparison!$I$5:$I$104),0) -> 0 | I6: =COUNTIFS(Comparison!$N$5:$N$104,F6,Comparison!$I$5:$I$104,">0") -> 0 | J6: =COUNTIFS(Comparison!$N$5:$N$104,F6,Comparison!$L$5:$L$104,2085,Comparison!$I$5:$I$104,">0") -> 0 | K6: =COUNTIFS(Comparison!$N$5:$N$104,F6,Comparison!$I$5:$I$104,"<0") -> 0
A7: project 28 start year (-2%) | B7: =INDEX('Raw profile'!I24:I123,MATCH("project 28",'Raw profile'!A24:A123,0)) -> 2026 | C7: =INDEX('Growth profile'!I24:I123,MATCH("project 28",'Growth profile'!A24:A123,0)) -> 2026 | D7: =INDEX('Growth (no penalty)'!I24:I123,MATCH("project 28",'Growth (no penalty)'!A24:A123,0)) -> 2026 | F7: under 1.5% | G7: =COUNTIF(Comparison!$N$5:$N$104,F7) -> 28 | H7: =IFERROR(AVERAGEIF(Comparison!$N$5:$N$104,F7,Comparison!$I$5:$I$104),0) -> -7.8214286 | I7: =COUNTIFS(Comparison!$N$5:$N$104,F7,Comparison!$I$5:$I$104,">0") -> 1 | J7: =COUNTIFS(Comparison!$N$5:$N$104,F7,Comparison!$L$5:$L$104,2085,Comparison!$I$5:$I$104,">0") -> 0 | K7: =COUNTIFS(Comparison!$N$5:$N$104,F7,Comparison!$I$5:$I$104,"<0") -> 21
A8: Last construction year | B8: ='Raw profile'!B14 -> 2044 | C8: ='Growth profile'!B14 -> 2044 | D8: ='Growth (no penalty)'!B14 -> 2045 | F8: 1.5% to 1.8% | G8: =COUNTIF(Comparison!$N$5:$N$104,F8) -> 13 | H8: =IFERROR(AVERAGEIF(Comparison!$N$5:$N$104,F8,Comparison!$I$5:$I$104),0) -> -6.5384615 | I8: =COUNTIFS(Comparison!$N$5:$N$104,F8,Comparison!$I$5:$I$104,">0") -> 0 | J8: =COUNTIFS(Comparison!$N$5:$N$104,F8,Comparison!$L$5:$L$104,2085,Comparison!$I$5:$I$104,">0") -> 0 | K8: =COUNTIFS(Comparison!$N$5:$N$104,F8,Comparison!$I$5:$I$104,"<0") -> 9
A9: Max annual spend / envelope | B9: ='Raw profile'!J8 -> 1.2079536 | C9: ='Growth profile'!J8 -> 1.1859557 | D9: ='Growth (no penalty)'!J8 -> 4.0557503 | F9: 1.8% and over | G9: =COUNTIF(Comparison!$N$5:$N$104,F9) -> 58 | H9: =IFERROR(AVERAGEIF(Comparison!$N$5:$N$104,F9,Comparison!$I$5:$I$104),0) -> 2.8103448 | I9: =COUNTIFS(Comparison!$N$5:$N$104,F9,Comparison!$I$5:$I$104,">0") -> 31 | J9: =COUNTIFS(Comparison!$N$5:$N$104,F9,Comparison!$L$5:$L$104,2085,Comparison!$I$5:$I$104,">0") -> 0 | K9: =COUNTIFS(Comparison!$N$5:$N$104,F9,Comparison!$I$5:$I$104,"<0") -> 25
A10: Years with spend above envelope | B10: ='Raw profile'!J9 -> 12 | C10: ='Growth profile'!J9 -> 8 | D10: ='Growth (no penalty)'!J9 -> 6 | F10: All | G10: =SUM(G6:G9) -> 100 | H10: =IFERROR(AVERAGE(Comparison!$I$5:$I$104),0) -> -1.41 | I10: =SUM(I6:I9) -> 32 | J10: =SUM(J6:J9) -> 0 | K10: =SUM(K6:K9) -> 55
A11: Peak balance carried while building ($M) | B11: ='Raw profile'!J5 -> 47.2655 | C11: ='Growth profile'!J5 -> 44.683444 | D11: ='Growth (no penalty)'!J5 -> 1691.0532
A12: Average balance carried while building ($M) | B12: ='Raw profile'!J6 -> 5.2065596 | C12: ='Growth profile'!J6 -> 24.428736 | D12: ='Growth (no penalty)'!J6 -> 630.20539 | F12: Full per-project table: 'Comparison'. Gantt: 'Gantt'. Odd cases: 'Fringe cases'.
A13: Years holding cash above penalty-free cap | B13: ='Raw profile'!J7 -> 1 | C13: ='Growth profile'!J7 -> 5 | D13: ='Growth (no penalty)'!J7 -> 13
A14: Funded years with zero spend | B14: ='Raw profile'!J10 -> 0 | C14: ='Growth profile'!J10 -> 0 | D14: ='Growth (no penalty)'!J10 -> 0
A15: Benefit-years truncated at 2085 | B15: =SUM('Raw profile'!N24:N123) -> 0 | C15: =SUM('Growth profile'!N24:N123) -> 0 | D15: =SUM('Growth (no penalty)'!N24:N123) -> 0
A16: MindOpt status / gap | B16: OPTIMAL / 0.000% | C16: OPTIMAL / 0.000% | D16: OPTIMAL / 0.000%
A18: Annual spend vs funding envelope, closing balance and the penalty-free cash cap (2026-2050)
A79: BCR - Spend-weighted project average: raw vs growth vs growth with no cash penalty | E79: Each year: sum(project spend x project BCR) / total spend, BCR = PV benefits / PV cost as scheduled (MBCM 2% / 1.5%), as in the optimiser dashboard.
A101: BCR of projects starting each year (cost-weighted): raw vs growth vs no cash penalty | E101: Each start year: sum(project cost x project BCR) / sum(project cost) over projects starting that year. Blank = no starts. Shows the ranking directly, without spend-smearing.
A123: Portfolio PV BCR (cumulative), 2026-2085: raw vs growth vs no cash penalty | E123: Each year: PV of all benefits realised to date / PV of all spend to date (MBCM rates), as in the optimiser dashboard. Starts near zero while building; the 2085 value is the portfolio BCR.
A145: BCR of projects starting in each 3-year NLTP period (cost-weighted): raw vs growth vs no cash penalty | M145: First period starts (edit to align with NLTP boundaries): | U145: 2026
M146: NLTP period | N146: From | O146: To | P146: Raw BCR | Q146: Growth BCR | R146: No-penalty BCR | S146: Raw starts | T146: Growth starts | U146: No-penalty starts
M147: =N147&"-"&RIGHT(O147,2) -> 2026-28 | N147: =$U$145+0 -> 2026 | O147: =N147+2 -> 2028 | P147: =IFERROR(SUMPRODUCT(('Raw profile'!$I$24:$I$123>=$N147)*('Raw profile'!$I$24:$I$123<=$O147)*'Raw profile'!$E$24:$E$123*'Raw profile'!$S$24:$S$123)/SUMPRODUCT(('Raw profile'!$I$24:$I$123>=$N147)*('Raw profile'!$I$24:$I$123<=$O147)*'Raw profile'!$E$24:$E$123),NA()) -> 2.8559604 | Q147: =IFERROR(SUMPRODUCT(('Growth profile'!$I$24:$I$123>=$N147)*('Growth profile'!$I$24:$I$123<=$O147)*'Growth profile'!$E$24:$E$123*'Growth profile'!$S$24:$S$123)/SUMPRODUCT(('Growth profile'!$I$24:$I$123>=$N147)*('Growth profile'!$I$24:$I$123<=$O147)*'Growth profile'!$E$24:$E$123),NA()) -> 3.495899 | R147: =IFERROR(SUMPRODUCT(('Growth (no penalty)'!$I$24:$I$123>=$N147)*('Growth (no penalty)'!$I$24:$I$123<=$O147)*'Growth (no penalty)'!$E$24:$E$123*'Growth (no penalty)'!$S$24:$S$123)/SUMPRODUCT(('Growth (no penalty)'!$I$24:$I$123>=$N147)*('Growth (no penalty)'!$I$24:$I$123<=$O147)*'Growth (no penalty)'!$E$24:$E$123),NA()) -> 3.2877013 | S147: =SUMPRODUCT(('Raw profile'!$I$24:$I$123>=$N147)*('Raw profile'!$I$24:$I$123<=$O147)) -> 31 | T147: =SUMPRODUCT(('Growth profile'!$I$24:$I$123>=$N147)*('Growth profile'!$I$24:$I$123<=$O147)) -> 32 | U147: =SUMPRODUCT(('Growth (no penalty)'!$I$24:$I$123>=$N147)*('Growth (no penalty)'!$I$24:$I$123<=$O147)) -> 35
M148: =N148&"-"&RIGHT(O148,2) -> 2029-31 | N148: =$U$145+3 -> 2029 | O148: =N148+2 -> 2031 | P148: =IFERROR(SUMPRODUCT(('Raw profile'!$I$24:$I$123>=$N148)*('Raw profile'!$I$24:$I$123<=$O148)*'Raw profile'!$E$24:$E$123*'Raw profile'!$S$24:$S$123)/SUMPRODUCT(('Raw profile'!$I$24:$I$123>=$N148)*('Raw profile'!$I$24:$I$123<=$O148)*'Raw profile'!$E$24:$E$123),NA()) -> 2.2316235 | Q148: =IFERROR(SUMPRODUCT(('Growth profile'!$I$24:$I$123>=$N148)*('Growth profile'!$I$24:$I$123<=$O148)*'Growth profile'!$E$24:$E$123*'Growth profile'!$S$24:$S$123)/SUMPRODUCT(('Growth profile'!$I$24:$I$123>=$N148)*('Growth profile'!$I$24:$I$123<=$O148)*'Growth profile'!$E$24:$E$123),NA()) -> 3.5248422 | R148: =IFERROR(SUMPRODUCT(('Growth (no penalty)'!$I$24:$I$123>=$N148)*('Growth (no penalty)'!$I$24:$I$123<=$O148)*'Growth (no penalty)'!$E$24:$E$123*'Growth (no penalty)'!$S$24:$S$123)/SUMPRODUCT(('Growth (no penalty)'!$I$24:$I$123>=$N148)*('Growth (no penalty)'!$I$24:$I$123<=$O148)*'Growth (no penalty)'!$E$24:$E$123),NA()) -> 4.6945876 | S148: =SUMPRODUCT(('Raw profile'!$I$24:$I$123>=$N148)*('Raw profile'!$I$24:$I$123<=$O148)) -> 11 | T148: =SUMPRODUCT(('Growth profile'!$I$24:$I$123>=$N148)*('Growth profile'!$I$24:$I$123<=$O148)) -> 10 | U148: =SUMPRODUCT(('Growth (no penalty)'!$I$24:$I$123>=$N148)*('Growth (no penalty)'!$I$24:$I$123<=$O148)) -> 5
M149: =N149&"-"&RIGHT(O149,2) -> 2032-34 | N149: =$U$145+6 -> 2032 | O149: =N149+2 -> 2034 | P149: =IFERROR(SUMPRODUCT(('Raw profile'!$I$24:$I$123>=$N149)*('Raw profile'!$I$24:$I$123<=$O149)*'Raw profile'!$E$24:$E$123*'Raw profile'!$S$24:$S$123)/SUMPRODUCT(('Raw profile'!$I$24:$I$123>=$N149)*('Raw profile'!$I$24:$I$123<=$O149)*'Raw profile'!$E$24:$E$123),NA()) -> 1.9658065 | Q149: =IFERROR(SUMPRODUCT(('Growth profile'!$I$24:$I$123>=$N149)*('Growth profile'!$I$24:$I$123<=$O149)*'Growth profile'!$E$24:$E$123*'Growth profile'!$S$24:$S$123)/SUMPRODUCT(('Growth profile'!$I$24:$I$123>=$N149)*('Growth profile'!$I$24:$I$123<=$O149)*'Growth profile'!$E$24:$E$123),NA()) -> 3.9081502 | R149: =IFERROR(SUMPRODUCT(('Growth (no penalty)'!$I$24:$I$123>=$N149)*('Growth (no penalty)'!$I$24:$I$123<=$O149)*'Growth (no penalty)'!$E$24:$E$123*'Growth (no penalty)'!$S$24:$S$123)/SUMPRODUCT(('Growth (no penalty)'!$I$24:$I$123>=$N149)*('Growth (no penalty)'!$I$24:$I$123<=$O149)*'Growth (no penalty)'!$E$24:$E$123),NA()) -> 1.332184 | S149: =SUMPRODUCT(('Raw profile'!$I$24:$I$123>=$N149)*('Raw profile'!$I$24:$I$123<=$O149)) -> 6 | T149: =SUMPRODUCT(('Growth profile'!$I$24:$I$123>=$N149)*('Growth profile'!$I$24:$I$123<=$O149)) -> 23 | U149: =SUMPRODUCT(('Growth (no penalty)'!$I$24:$I$123>=$N149)*('Growth (no penalty)'!$I$24:$I$123<=$O149)) -> 1
M150: =N150&"-"&RIGHT(O150,2) -> 2035-37 | N150: =$U$145+9 -> 2035 | O150: =N150+2 -> 2037 | P150: =IFERROR(SUMPRODUCT(('Raw profile'!$I$24:$I$123>=$N150)*('Raw profile'!$I$24:$I$123<=$O150)*'Raw profile'!$E$24:$E$123*'Raw profile'!$S$24:$S$123)/SUMPRODUCT(('Raw profile'!$I$24:$I$123>=$N150)*('Raw profile'!$I$24:$I$123<=$O150)*'Raw profile'!$E$24:$E$123),NA()) -> 1.7312536 | Q150: =IFERROR(SUMPRODUCT(('Growth profile'!$I$24:$I$123>=$N150)*('Growth profile'!$I$24:$I$123<=$O150)*'Growth profile'!$E$24:$E$123*'Growth profile'!$S$24:$S$123)/SUMPRODUCT(('Growth profile'!$I$24:$I$123>=$N150)*('Growth profile'!$I$24:$I$123<=$O150)*'Growth profile'!$E$24:$E$123),NA()) -> 4.4315604 | R150: =IFERROR(SUMPRODUCT(('Growth (no penalty)'!$I$24:$I$123>=$N150)*('Growth (no penalty)'!$I$24:$I$123<=$O150)*'Growth (no penalty)'!$E$24:$E$123*'Growth (no penalty)'!$S$24:$S$123)/SUMPRODUCT(('Growth (no penalty)'!$I$24:$I$123>=$N150)*('Growth (no penalty)'!$I$24:$I$123<=$O150)*'Growth (no penalty)'!$E$24:$E$123),NA()) -> 5.6777835 | S150: =SUMPRODUCT(('Raw profile'!$I$24:$I$123>=$N150)*('Raw profile'!$I$24:$I$123<=$O150)) -> 19 | T150: =SUMPRODUCT(('Growth profile'!$I$24:$I$123>=$N150)*('Growth profile'!$I$24:$I$123<=$O150)) -> 16 | U150: =SUMPRODUCT(('Growth (no penalty)'!$I$24:$I$123>=$N150)*('Growth (no penalty)'!$I$24:$I$123<=$O150)) -> 1
M151: =N151&"-"&RIGHT(O151,2) -> 2038-40 | N151: =$U$145+12 -> 2038 | O151: =N151+2 -> 2040 | P151: =IFERROR(SUMPRODUCT(('Raw profile'!$I$24:$I$123>=$N151)*('Raw profile'!$I$24:$I$123<=$O151)*'Raw profile'!$E$24:$E$123*'Raw profile'!$S$24:$S$123)/SUMPRODUCT(('Raw profile'!$I$24:$I$123>=$N151)*('Raw profile'!$I$24:$I$123<=$O151)*'Raw profile'!$E$24:$E$123),NA()) -> 1.1166783 | Q151: =IFERROR(SUMPRODUCT(('Growth profile'!$I$24:$I$123>=$N151)*('Growth profile'!$I$24:$I$123<=$O151)*'Growth profile'!$E$24:$E$123*'Growth profile'!$S$24:$S$123)/SUMPRODUCT(('Growth profile'!$I$24:$I$123>=$N151)*('Growth profile'!$I$24:$I$123<=$O151)*'Growth profile'!$E$24:$E$123),NA()) -> 9.3049067 | R151: =IFERROR(SUMPRODUCT(('Growth (no penalty)'!$I$24:$I$123>=$N151)*('Growth (no penalty)'!$I$24:$I$123<=$O151)*'Growth (no penalty)'!$E$24:$E$123*'Growth (no penalty)'!$S$24:$S$123)/SUMPRODUCT(('Growth (no penalty)'!$I$24:$I$123>=$N151)*('Growth (no penalty)'!$I$24:$I$123<=$O151)*'Growth (no penalty)'!$E$24:$E$123),NA()) -> 5.5486849 | S151: =SUMPRODUCT(('Raw profile'!$I$24:$I$123>=$N151)*('Raw profile'!$I$24:$I$123<=$O151)) -> 13 | T151: =SUMPRODUCT(('Growth profile'!$I$24:$I$123>=$N151)*('Growth profile'!$I$24:$I$123<=$O151)) -> 9 | U151: =SUMPRODUCT(('Growth (no penalty)'!$I$24:$I$123>=$N151)*('Growth (no penalty)'!$I$24:$I$123<=$O151)) -> 6
M152: =N152&"-"&RIGHT(O152,2) -> 2041-43 | N152: =$U$145+15 -> 2041 | O152: =N152+2 -> 2043 | P152: =IFERROR(SUMPRODUCT(('Raw profile'!$I$24:$I$123>=$N152)*('Raw profile'!$I$24:$I$123<=$O152)*'Raw profile'!$E$24:$E$123*'Raw profile'!$S$24:$S$123)/SUMPRODUCT(('Raw profile'!$I$24:$I$123>=$N152)*('Raw profile'!$I$24:$I$123<=$O152)*'Raw profile'!$E$24:$E$123),NA()) -> 1.0613251 | Q152: =IFERROR(SUMPRODUCT(('Growth profile'!$I$24:$I$123>=$N152)*('Growth profile'!$I$24:$I$123<=$O152)*'Growth profile'!$E$24:$E$123*'Growth profile'!$S$24:$S$123)/SUMPRODUCT(('Growth profile'!$I$24:$I$123>=$N152)*('Growth profile'!$I$24:$I$123<=$O152)*'Growth profile'!$E$24:$E$123),NA()) -> 7.4623629 | R152: =IFERROR(SUMPRODUCT(('Growth (no penalty)'!$I$24:$I$123>=$N152)*('Growth (no penalty)'!$I$24:$I$123<=$O152)*'Growth (no penalty)'!$E$24:$E$123*'Growth (no penalty)'!$S$24:$S$123)/SUMPRODUCT(('Growth (no penalty)'!$I$24:$I$123>=$N152)*('Growth (no penalty)'!$I$24:$I$123<=$O152)*'Growth (no penalty)'!$E$24:$E$123),NA()) -> 5.4402891 | S152: =SUMPRODUCT(('Raw profile'!$I$24:$I$123>=$N152)*('Raw profile'!$I$24:$I$123<=$O152)) -> 20 | T152: =SUMPRODUCT(('Growth profile'!$I$24:$I$123>=$N152)*('Growth profile'!$I$24:$I$123<=$O152)) -> 10 | U152: =SUMPRODUCT(('Growth (no penalty)'!$I$24:$I$123>=$N152)*('Growth (no penalty)'!$I$24:$I$123<=$O152)) -> 20
M153: =N153&"-"&RIGHT(O153,2) -> 2044-46 | N153: =$U$145+18 -> 2044 | O153: =N153+2 -> 2046 | P153: =IFERROR(SUMPRODUCT(('Raw profile'!$I$24:$I$123>=$N153)*('Raw profile'!$I$24:$I$123<=$O153)*'Raw profile'!$E$24:$E$123*'Raw profile'!$S$24:$S$123)/SUMPRODUCT(('Raw profile'!$I$24:$I$123>=$N153)*('Raw profile'!$I$24:$I$123<=$O153)*'Raw profile'!$E$24:$E$123),NA()) -> #N/A | Q153: =IFERROR(SUMPRODUCT(('Growth profile'!$I$24:$I$123>=$N153)*('Growth profile'!$I$24:$I$123<=$O153)*'Growth profile'!$E$24:$E$123*'Growth profile'!$S$24:$S$123)/SUMPRODUCT(('Growth profile'!$I$24:$I$123>=$N153)*('Growth profile'!$I$24:$I$123<=$O153)*'Growth profile'!$E$24:$E$123),NA()) -> #N/A | R153: =IFERROR(SUMPRODUCT(('Growth (no penalty)'!$I$24:$I$123>=$N153)*('Growth (no penalty)'!$I$24:$I$123<=$O153)*'Growth (no penalty)'!$E$24:$E$123*'Growth (no penalty)'!$S$24:$S$123)/SUMPRODUCT(('Growth (no penalty)'!$I$24:$I$123>=$N153)*('Growth (no penalty)'!$I$24:$I$123<=$O153)*'Growth (no penalty)'!$E$24:$E$123),NA()) -> 6.5805519 | S153: =SUMPRODUCT(('Raw profile'!$I$24:$I$123>=$N153)*('Raw profile'!$I$24:$I$123<=$O153)) -> 0 | T153: =SUMPRODUCT(('Growth profile'!$I$24:$I$123>=$N153)*('Growth profile'!$I$24:$I$123<=$O153)) -> 0 | U153: =SUMPRODUCT(('Growth (no penalty)'!$I$24:$I$123>=$N153)*('Growth (no penalty)'!$I$24:$I$123<=$O153)) -> 32
M154: =N154&"-"&RIGHT(O154,2) -> 2047-49 | N154: =$U$145+21 -> 2047 | O154: =N154+2 -> 2049 | P154: =IFERROR(SUMPRODUCT(('Raw profile'!$I$24:$I$123>=$N154)*('Raw profile'!$I$24:$I$123<=$O154)*'Raw profile'!$E$24:$E$123*'Raw profile'!$S$24:$S$123)/SUMPRODUCT(('Raw profile'!$I$24:$I$123>=$N154)*('Raw profile'!$I$24:$I$123<=$O154)*'Raw profile'!$E$24:$E$123),NA()) -> #N/A | Q154: =IFERROR(SUMPRODUCT(('Growth profile'!$I$24:$I$123>=$N154)*('Growth profile'!$I$24:$I$123<=$O154)*'Growth profile'!$E$24:$E$123*'Growth profile'!$S$24:$S$123)/SUMPRODUCT(('Growth profile'!$I$24:$I$123>=$N154)*('Growth profile'!$I$24:$I$123<=$O154)*'Growth profile'!$E$24:$E$123),NA()) -> #N/A | R154: =IFERROR(SUMPRODUCT(('Growth (no penalty)'!$I$24:$I$123>=$N154)*('Growth (no penalty)'!$I$24:$I$123<=$O154)*'Growth (no penalty)'!$E$24:$E$123*'Growth (no penalty)'!$S$24:$S$123)/SUMPRODUCT(('Growth (no penalty)'!$I$24:$I$123>=$N154)*('Growth (no penalty)'!$I$24:$I$123<=$O154)*'Growth (no penalty)'!$E$24:$E$123),NA()) -> #N/A | S154: =SUMPRODUCT(('Raw profile'!$I$24:$I$123>=$N154)*('Raw profile'!$I$24:$I$123<=$O154)) -> 0 | T154: =SUMPRODUCT(('Growth profile'!$I$24:$I$123>=$N154)*('Growth profile'!$I$24:$I$123<=$O154)) -> 0 | U154: =SUMPRODUCT(('Growth (no penalty)'!$I$24:$I$123>=$N154)*('Growth (no penalty)'!$I$24:$I$123<=$O154)) -> 0
M155: =N155&"-"&RIGHT(O155,2) -> 2050-52 | N155: =$U$145+24 -> 2050 | O155: =N155+2 -> 2052 | P155: =IFERROR(SUMPRODUCT(('Raw profile'!$I$24:$I$123>=$N155)*('Raw profile'!$I$24:$I$123<=$O155)*'Raw profile'!$E$24:$E$123*'Raw profile'!$S$24:$S$123)/SUMPRODUCT(('Raw profile'!$I$24:$I$123>=$N155)*('Raw profile'!$I$24:$I$123<=$O155)*'Raw profile'!$E$24:$E$123),NA()) -> #N/A | Q155: =IFERROR(SUMPRODUCT(('Growth profile'!$I$24:$I$123>=$N155)*('Growth profile'!$I$24:$I$123<=$O155)*'Growth profile'!$E$24:$E$123*'Growth profile'!$S$24:$S$123)/SUMPRODUCT(('Growth profile'!$I$24:$I$123>=$N155)*('Growth profile'!$I$24:$I$123<=$O155)*'Growth profile'!$E$24:$E$123),NA()) -> #N/A | R155: =IFERROR(SUMPRODUCT(('Growth (no penalty)'!$I$24:$I$123>=$N155)*('Growth (no penalty)'!$I$24:$I$123<=$O155)*'Growth (no penalty)'!$E$24:$E$123*'Growth (no penalty)'!$S$24:$S$123)/SUMPRODUCT(('Growth (no penalty)'!$I$24:$I$123>=$N155)*('Growth (no penalty)'!$I$24:$I$123<=$O155)*'Growth (no penalty)'!$E$24:$E$123),NA()) -> #N/A | S155: =SUMPRODUCT(('Raw profile'!$I$24:$I$123>=$N155)*('Raw profile'!$I$24:$I$123<=$O155)) -> 0 | T155: =SUMPRODUCT(('Growth profile'!$I$24:$I$123>=$N155)*('Growth profile'!$I$24:$I$123<=$O155)) -> 0 | U155: =SUMPRODUCT(('Growth (no penalty)'!$I$24:$I$123>=$N155)*('Growth (no penalty)'!$I$24:$I$123<=$O155)) -> 0

Sheet Gantt
A1: Gantt: build (orange) and benefit years - raw vs growth vs growth with no cash penalty, 2026-2085
A2: Sorted by raw start year. Driven by the start years on the profile sheets. Red line = horizon end (2085).
E3: Build | M3: Benefit (raw) | U3: Benefit (growth) | AC3: Benefit (no cash penalty)
A5: Project | B5: Profile | C5: Start | D5: 2026 | E5: 2027 | F5: 2028 | G5: 2029 | H5: 2030 | I5: 2031 | J5: 2032 | K5: 2033 | L5: 2034 | M5: 2035 | N5: 2036 | O5: 2037 | P5: 2038 | Q5: 2039 | R5: 2040 | S5: 2041 | T5: 2042 | U5: 2043 | V5: 2044 | W5: 2045 | X5: 2046 | Y5: 2047 | Z5: 2048 | AA5: 2049 | AB5: 2050 | AC5: 2051 | AD5: 2052 | AE5: 2053 | AF5: 2054 | AG5: 2055 | AH5: 2056 | AI5: 2057 | AJ5: 2058 | AK5: 2059 | AL5: 2060 | AM5: 2061 | AN5: 2062 | AO5: 2063 | AP5: 2064 | AQ5: 2065 | AR5: 2066 | AS5: 2067 | AT5: 2068 | AU5: 2069 | AV5: 2070 | AW5: 2071 | AX5: 2072 | AY5: 2073 | AZ5: 2074 | BA5: 2075 | BB5: 2076 | BC5: 2077 | BD5: 2078 | BE5: 2079 | BF5: 2080 | BG5: 2081 | BH5: 2082 | BI5: 2083 | BJ5: 2084 | BK5: 2085
A6: ='Growth profile'!A25 -> project 4 | B6: Raw | C6: ='Raw profile'!I25 -> 2026 | D6: =IF('Raw profile'!C133>0,1,IF('Raw profile'!C236>0,2,0)) -> 1 | E6: =IF('Raw profile'!D133>0,1,IF('Raw profile'!D236>0,2,0)) -> 1 | F6: =IF('Raw profile'!E133>0,1,IF('Raw profile'!E236>0,2,0)) -> 2 | G6: =IF('Raw profile'!F133>0,1,IF('Raw profile'!F236>0,2,0)) -> 2 | H6: =IF('Raw profile'!G133>0,1,IF('Raw profile'!G236>0,2,0)) -> 2 | I6: =IF('Raw profile'!H133>0,1,IF('Raw profile'!H236>0,2,0)) -> 2 | J6: =IF('Raw profile'!I133>0,1,IF('Raw profile'!I236>0,2,0)) -> 2 | K6: =IF('Raw profile'!J133>0,1,IF('Raw profile'!J236>0,2,0)) -> 2 | ... BK6: =IF('Raw profile'!BJ133>0,1,IF('Raw profile'!BJ236>0,2,0)) -> 0
B7: Growth | C7: ='Growth profile'!I25 -> 2026 | D7: =IF('Growth profile'!C133>0,1,IF('Growth profile'!C236>0,3,0)) -> 1 | E7: =IF('Growth profile'!D133>0,1,IF('Growth profile'!D236>0,3,0)) -> 1 | F7: =IF('Growth profile'!E133>0,1,IF('Growth profile'!E236>0,3,0)) -> 3 | G7: =IF('Growth profile'!F133>0,1,IF('Growth profile'!F236>0,3,0)) -> 3 | H7: =IF('Growth profile'!G133>0,1,IF('Growth profile'!G236>0,3,0)) -> 3 | I7: =IF('Growth profile'!H133>0,1,IF('Growth profile'!H236>0,3,0)) -> 3 | J7: =IF('Growth profile'!I133>0,1,IF('Growth profile'!I236>0,3,0)) -> 3 | K7: =IF('Growth profile'!J133>0,1,IF('Growth profile'!J236>0,3,0)) -> 3 | ... BK7: =IF('Growth profile'!BJ133>0,1,IF('Growth profile'!BJ236>0,3,0)) -> 0
B8: No penalty | C8: ='Growth (no penalty)'!I25 -> 2026 | D8: =IF('Growth (no penalty)'!C133>0,1,IF('Growth (no penalty)'!C236>0,4,0)) -> 1 | E8: =IF('Growth (no penalty)'!D133>0,1,IF('Growth (no penalty)'!D236>0,4,0)) -> 1 | F8: =IF('Growth (no penalty)'!E133>0,1,IF('Growth (no penalty)'!E236>0,4,0)) -> 4 | G8: =IF('Growth (no penalty)'!F133>0,1,IF('Growth (no penalty)'!F236>0,4,0)) -> 4 | H8: =IF('Growth (no penalty)'!G133>0,1,IF('Growth (no penalty)'!G236>0,4,0)) -> 4 | I8: =IF('Growth (no penalty)'!H133>0,1,IF('Growth (no penalty)'!H236>0,4,0)) -> 4 | J8: =IF('Growth (no penalty)'!I133>0,1,IF('Growth (no penalty)'!I236>0,4,0)) -> 4 | K8: =IF('Growth (no penalty)'!J133>0,1,IF('Growth (no penalty)'!J236>0,4,0)) -> 4 | ... BK8: =IF('Growth (no penalty)'!BJ133>0,1,IF('Growth (no penalty)'!BJ236>0,4,0)) -> 0
A9: ='Growth profile'!A33 -> project 22 | B9: Raw | C9: ='Raw profile'!I33 -> 2026 | D9: =IF('Raw profile'!C141>0,1,IF('Raw profile'!C244>0,2,0)) -> 1 | E9: =IF('Raw profile'!D141>0,1,IF('Raw profile'!D244>0,2,0)) -> 1 | F9: =IF('Raw profile'!E141>0,1,IF('Raw profile'!E244>0,2,0)) -> 2 | G9: =IF('Raw profile'!F141>0,1,IF('Raw profile'!F244>0,2,0)) -> 2 | H9: =IF('Raw profile'!G141>0,1,IF('Raw profile'!G244>0,2,0)) -> 2 | I9: =IF('Raw profile'!H141>0,1,IF('Raw profile'!H244>0,2,0)) -> 2 | J9: =IF('Raw profile'!I141>0,1,IF('Raw profile'!I244>0,2,0)) -> 2 | K9: =IF('Raw profile'!J141>0,1,IF('Raw profile'!J244>0,2,0)) -> 2 | ... BK9: =IF('Raw profile'!BJ141>0,1,IF('Raw profile'!BJ244>0,2,0)) -> 0
B10: Growth | C10: ='Growth profile'!I33 -> 2026 | D10: =IF('Growth profile'!C141>0,1,IF('Growth profile'!C244>0,3,0)) -> 1 | E10: =IF('Growth profile'!D141>0,1,IF('Growth profile'!D244>0,3,0)) -> 1 | F10: =IF('Growth profile'!E141>0,1,IF('Growth profile'!E244>0,3,0)) -> 3 | G10: =IF('Growth profile'!F141>0,1,IF('Growth profile'!F244>0,3,0)) -> 3 | H10: =IF('Growth profile'!G141>0,1,IF('Growth profile'!G244>0,3,0)) -> 3 | I10: =IF('Growth profile'!H141>0,1,IF('Growth profile'!H244>0,3,0)) -> 3 | J10: =IF('Growth profile'!I141>0,1,IF('Growth profile'!I244>0,3,0)) -> 3 | K10: =IF('Growth profile'!J141>0,1,IF('Growth profile'!J244>0,3,0)) -> 3 | ... BK10: =IF('Growth profile'!BJ141>0,1,IF('Growth profile'!BJ244>0,3,0)) -> 0
B11: No penalty | C11: ='Growth (no penalty)'!I33 -> 2026 | D11: =IF('Growth (no penalty)'!C141>0,1,IF('Growth (no penalty)'!C244>0,4,0)) -> 1 | E11: =IF('Growth (no penalty)'!D141>0,1,IF('Growth (no penalty)'!D244>0,4,0)) -> 1 | F11: =IF('Growth (no penalty)'!E141>0,1,IF('Growth (no penalty)'!E244>0,4,0)) -> 4 | G11: =IF('Growth (no penalty)'!F141>0,1,IF('Growth (no penalty)'!F244>0,4,0)) -> 4 | H11: =IF('Growth (no penalty)'!G141>0,1,IF('Growth (no penalty)'!G244>0,4,0)) -> 4 | I11: =IF('Growth (no penalty)'!H141>0,1,IF('Growth (no penalty)'!H244>0,4,0)) -> 4 | J11: =IF('Growth (no penalty)'!I141>0,1,IF('Growth (no penalty)'!I244>0,4,0)) -> 4 | K11: =IF('Growth (no penalty)'!J141>0,1,IF('Growth (no penalty)'!J244>0,4,0)) -> 4 | ... BK11: =IF('Growth (no penalty)'!BJ141>0,1,IF('Growth (no penalty)'!BJ244>0,4,0)) -> 0
A12: ='Growth profile'!A36 -> project 26 | B12: Raw | C12: ='Raw profile'!I36 -> 2026 | D12: =IF('Raw profile'!C144>0,1,IF('Raw profile'!C247>0,2,0)) -> 1 | E12: =IF('Raw profile'!D144>0,1,IF('Raw profile'!D247>0,2,0)) -> 2 | F12: =IF('Raw profile'!E144>0,1,IF('Raw profile'!E247>0,2,0)) -> 2 | G12: =IF('Raw profile'!F144>0,1,IF('Raw profile'!F247>0,2,0)) -> 2 | H12: =IF('Raw profile'!G144>0,1,IF('Raw profile'!G247>0,2,0)) -> 2 | I12: =IF('Raw profile'!H144>0,1,IF('Raw profile'!H247>0,2,0)) -> 2 | J12: =IF('Raw profile'!I144>0,1,IF('Raw profile'!I247>0,2,0)) -> 2 | K12: =IF('Raw profile'!J144>0,1,IF('Raw profile'!J247>0,2,0)) -> 2 | ... BK12: =IF('Raw profile'!BJ144>0,1,IF('Raw profile'!BJ247>0,2,0)) -> 0
B13: Growth | C13: ='Growth profile'!I36 -> 2026 | D13: =IF('Growth profile'!C144>0,1,IF('Growth profile'!C247>0,3,0)) -> 1 | E13: =IF('Growth profile'!D144>0,1,IF('Growth profile'!D247>0,3,0)) -> 3 | F13: =IF('Growth profile'!E144>0,1,IF('Growth profile'!E247>0,3,0)) -> 3 | G13: =IF('Growth profile'!F144>0,1,IF('Growth profile'!F247>0,3,0)) -> 3 | H13: =IF('Growth profile'!G144>0,1,IF('Growth profile'!G247>0,3,0)) -> 3 | I13: =IF('Growth profile'!H144>0,1,IF('Growth profile'!H247>0,3,0)) -> 3 | J13: =IF('Growth profile'!I144>0,1,IF('Growth profile'!I247>0,3,0)) -> 3 | K13: =IF('Growth profile'!J144>0,1,IF('Growth profile'!J247>0,3,0)) -> 3 | ... BK13: =IF('Growth profile'!BJ144>0,1,IF('Growth profile'!BJ247>0,3,0)) -> 0
B14: No penalty | C14: ='Growth (no penalty)'!I36 -> 2026 | D14: =IF('Growth (no penalty)'!C144>0,1,IF('Growth (no penalty)'!C247>0,4,0)) -> 1 | E14: =IF('Growth (no penalty)'!D144>0,1,IF('Growth (no penalty)'!D247>0,4,0)) -> 4 | F14: =IF('Growth (no penalty)'!E144>0,1,IF('Growth (no penalty)'!E247>0,4,0)) -> 4 | G14: =IF('Growth (no penalty)'!F144>0,1,IF('Growth (no penalty)'!F247>0,4,0)) -> 4 | H14: =IF('Growth (no penalty)'!G144>0,1,IF('Growth (no penalty)'!G247>0,4,0)) -> 4 | I14: =IF('Growth (no penalty)'!H144>0,1,IF('Growth (no penalty)'!H247>0,4,0)) -> 4 | J14: =IF('Growth (no penalty)'!I144>0,1,IF('Growth (no penalty)'!I247>0,4,0)) -> 4 | K14: =IF('Growth (no penalty)'!J144>0,1,IF('Growth (no penalty)'!J247>0,4,0)) -> 4 | ... BK14: =IF('Growth (no penalty)'!BJ144>0,1,IF('Growth (no penalty)'!BJ247>0,4,0)) -> 0
A15: ='Growth profile'!A38 -> project 28 | B15: Raw | C15: ='Raw profile'!I38 -> 2026 | D15: =IF('Raw profile'!C146>0,1,IF('Raw profile'!C249>0,2,0)) -> 1 | E15: =IF('Raw profile'!D146>0,1,IF('Raw profile'!D249>0,2,0)) -> 1 | F15: =IF('Raw profile'!E146>0,1,IF('Raw profile'!E249>0,2,0)) -> 2 | G15: =IF('Raw profile'!F146>0,1,IF('Raw profile'!F249>0,2,0)) -> 2 | H15: =IF('Raw profile'!G146>0,1,IF('Raw profile'!G249>0,2,0)) -> 2 | I15: =IF('Raw profile'!H146>0,1,IF('Raw profile'!H249>0,2,0)) -> 2 | J15: =IF('Raw profile'!I146>0,1,IF('Raw profile'!I249>0,2,0)) -> 2 | K15: =IF('Raw profile'!J146>0,1,IF('Raw profile'!J249>0,2,0)) -> 2 | ... BK15: =IF('Raw profile'!BJ146>0,1,IF('Raw profile'!BJ249>0,2,0)) -> 0
B16: Growth | C16: ='Growth profile'!I38 -> 2026 | D16: =IF('Growth profile'!C146>0,1,IF('Growth profile'!C249>0,3,0)) -> 1 | E16: =IF('Growth profile'!D146>0,1,IF('Growth profile'!D249>0,3,0)) -> 1 | F16: =IF('Growth profile'!E146>0,1,IF('Growth profile'!E249>0,3,0)) -> 3 | G16: =IF('Growth profile'!F146>0,1,IF('Growth profile'!F249>0,3,0)) -> 3 | H16: =IF('Growth profile'!G146>0,1,IF('Growth profile'!G249>0,3,0)) -> 3 | I16: =IF('Growth profile'!H146>0,1,IF('Growth profile'!H249>0,3,0)) -> 3 | J16: =IF('Growth profile'!I146>0,1,IF('Growth profile'!I249>0,3,0)) -> 3 | K16: =IF('Growth profile'!J146>0,1,IF('Growth profile'!J249>0,3,0)) -> 3 | ... BK16: =IF('Growth profile'!BJ146>0,1,IF('Growth profile'!BJ249>0,3,0)) -> 0
B17: No penalty | C17: ='Growth (no penalty)'!I38 -> 2026 | D17: =IF('Growth (no penalty)'!C146>0,1,IF('Growth (no penalty)'!C249>0,4,0)) -> 1 | E17: =IF('Growth (no penalty)'!D146>0,1,IF('Growth (no penalty)'!D249>0,4,0)) -> 1 | F17: =IF('Growth (no penalty)'!E146>0,1,IF('Growth (no penalty)'!E249>0,4,0)) -> 4 | G17: =IF('Growth (no penalty)'!F146>0,1,IF('Growth (no penalty)'!F249>0,4,0)) -> 4 | H17: =IF('Growth (no penalty)'!G146>0,1,IF('Growth (no penalty)'!G249>0,4,0)) -> 4 | I17: =IF('Growth (no penalty)'!H146>0,1,IF('Growth (no penalty)'!H249>0,4,0)) -> 4 | J17: =IF('Growth (no penalty)'!I146>0,1,IF('Growth (no penalty)'!I249>0,4,0)) -> 4 | K17: =IF('Growth (no penalty)'!J146>0,1,IF('Growth (no penalty)'!J249>0,4,0)) -> 4 | ... BK17: =IF('Growth (no penalty)'!BJ146>0,1,IF('Growth (no penalty)'!BJ249>0,4,0)) -> 0
A18: ='Growth profile'!A40 -> project 32 | B18: Raw | C18: ='Raw profile'!I40 -> 2026 | D18: =IF('Raw profile'!C148>0,1,IF('Raw profile'!C251>0,2,0)) -> 1 | E18: =IF('Raw profile'!D148>0,1,IF('Raw profile'!D251>0,2,0)) -> 1 | F18: =IF('Raw profile'!E148>0,1,IF('Raw profile'!E251>0,2,0)) -> 1 | G18: =IF('Raw profile'!F148>0,1,IF('Raw profile'!F251>0,2,0)) -> 2 | H18: =IF('Raw profile'!G148>0,1,IF('Raw profile'!G251>0,2,0)) -> 2 | I18: =IF('Raw profile'!H148>0,1,IF('Raw profile'!H251>0,2,0)) -> 2 | J18: =IF('Raw profile'!I148>0,1,IF('Raw profile'!I251>0,2,0)) -> 2 | K18: =IF('Raw profile'!J148>0,1,IF('Raw profile'!J251>0,2,0)) -> 2 | ... BK18: =IF('Raw profile'!BJ148>0,1,IF('Raw profile'!BJ251>0,2,0)) -> 0
B19: Growth | C19: ='Growth profile'!I40 -> 2026 | D19: =IF('Growth profile'!C148>0,1,IF('Growth profile'!C251>0,3,0)) -> 1 | E19: =IF('Growth profile'!D148>0,1,IF('Growth profile'!D251>0,3,0)) -> 1 | F19: =IF('Growth profile'!E148>0,1,IF('Growth profile'!E251>0,3,0)) -> 1 | G19: =IF('Growth profile'!F148>0,1,IF('Growth profile'!F251>0,3,0)) -> 3 | H19: =IF('Growth profile'!G148>0,1,IF('Growth profile'!G251>0,3,0)) -> 3 | I19: =IF('Growth profile'!H148>0,1,IF('Growth profile'!H251>0,3,0)) -> 3 | J19: =IF('Growth profile'!I148>0,1,IF('Growth profile'!I251>0,3,0)) -> 3 | K19: =IF('Growth profile'!J148>0,1,IF('Growth profile'!J251>0,3,0)) -> 3 | ... BK19: =IF('Growth profile'!BJ148>0,1,IF('Growth profile'!BJ251>0,3,0)) -> 0
B20: No penalty | C20: ='Growth (no penalty)'!I40 -> 2026 | D20: =IF('Growth (no penalty)'!C148>0,1,IF('Growth (no penalty)'!C251>0,4,0)) -> 1 | E20: =IF('Growth (no penalty)'!D148>0,1,IF('Growth (no penalty)'!D251>0,4,0)) -> 1 | F20: =IF('Growth (no penalty)'!E148>0,1,IF('Growth (no penalty)'!E251>0,4,0)) -> 1 | G20: =IF('Growth (no penalty)'!F148>0,1,IF('Growth (no penalty)'!F251>0,4,0)) -> 4 | H20: =IF('Growth (no penalty)'!G148>0,1,IF('Growth (no penalty)'!G251>0,4,0)) -> 4 | I20: =IF('Growth (no penalty)'!H148>0,1,IF('Growth (no penalty)'!H251>0,4,0)) -> 4 | J20: =IF('Growth (no penalty)'!I148>0,1,IF('Growth (no penalty)'!I251>0,4,0)) -> 4 | K20: =IF('Growth (no penalty)'!J148>0,1,IF('Growth (no penalty)'!J251>0,4,0)) -> 4 | ... BK20: =IF('Growth (no penalty)'!BJ148>0,1,IF('Growth (no penalty)'!BJ251>0,4,0)) -> 0
A21: ='Growth profile'!A59 -> project 64 | B21: Raw | C21: ='Raw profile'!I59 -> 2026 | D21: =IF('Raw profile'!C167>0,1,IF('Raw profile'!C270>0,2,0)) -> 1 | E21: =IF('Raw profile'!D167>0,1,IF('Raw profile'!D270>0,2,0)) -> 1 | F21: =IF('Raw profile'!E167>0,1,IF('Raw profile'!E270>0,2,0)) -> 2 | G21: =IF('Raw profile'!F167>0,1,IF('Raw profile'!F270>0,2,0)) -> 2 | H21: =IF('Raw profile'!G167>0,1,IF('Raw profile'!G270>0,2,0)) -> 2 | I21: =IF('Raw profile'!H167>0,1,IF('Raw profile'!H270>0,2,0)) -> 2 | J21: =IF('Raw profile'!I167>0,1,IF('Raw profile'!I270>0,2,0)) -> 2 | K21: =IF('Raw profile'!J167>0,1,IF('Raw profile'!J270>0,2,0)) -> 2 | ... BK21: =IF('Raw profile'!BJ167>0,1,IF('Raw profile'!BJ270>0,2,0)) -> 0
B22: Growth | C22: ='Growth profile'!I59 -> 2026 | D22: =IF('Growth profile'!C167>0,1,IF('Growth profile'!C270>0,3,0)) -> 1 | E22: =IF('Growth profile'!D167>0,1,IF('Growth profile'!D270>0,3,0)) -> 1 | F22: =IF('Growth profile'!E167>0,1,IF('Growth profile'!E270>0,3,0)) -> 3 | G22: =IF('Growth profile'!F167>0,1,IF('Growth profile'!F270>0,3,0)) -> 3 | H22: =IF('Growth profile'!G167>0,1,IF('Growth profile'!G270>0,3,0)) -> 3 | I22: =IF('Growth profile'!H167>0,1,IF('Growth profile'!H270>0,3,0)) -> 3 | J22: =IF('Growth profile'!I167>0,1,IF('Growth profile'!I270>0,3,0)) -> 3 | K22: =IF('Growth profile'!J167>0,1,IF('Growth profile'!J270>0,3,0)) -> 3 | ... BK22: =IF('Growth profile'!BJ167>0,1,IF('Growth profile'!BJ270>0,3,0)) -> 0
B23: No penalty | C23: ='Growth (no penalty)'!I59 -> 2026 | D23: =IF('Growth (no penalty)'!C167>0,1,IF('Growth (no penalty)'!C270>0,4,0)) -> 1 | E23: =IF('Growth (no penalty)'!D167>0,1,IF('Growth (no penalty)'!D270>0,4,0)) -> 1 | F23: =IF('Growth (no penalty)'!E167>0,1,IF('Growth (no penalty)'!E270>0,4,0)) -> 4 | G23: =IF('Growth (no penalty)'!F167>0,1,IF('Growth (no penalty)'!F270>0,4,0)) -> 4 | H23: =IF('Growth (no penalty)'!G167>0,1,IF('Growth (no penalty)'!G270>0,4,0)) -> 4 | I23: =IF('Growth (no penalty)'!H167>0,1,IF('Growth (no penalty)'!H270>0,4,0)) -> 4 | J23: =IF('Growth (no penalty)'!I167>0,1,IF('Growth (no penalty)'!I270>0,4,0)) -> 4 | K23: =IF('Growth (no penalty)'!J167>0,1,IF('Growth (no penalty)'!J270>0,4,0)) -> 4 | ... BK23: =IF('Growth (no penalty)'!BJ167>0,1,IF('Growth (no penalty)'!BJ270>0,4,0)) -> 0
A24: ='Growth profile'!A74 -> project 106 | B24: Raw | C24: ='Raw profile'!I74 -> 2026 | D24: =IF('Raw profile'!C182>0,1,IF('Raw profile'!C285>0,2,0)) -> 1 | E24: =IF('Raw profile'!D182>0,1,IF('Raw profile'!D285>0,2,0)) -> 1 | F24: =IF('Raw profile'!E182>0,1,IF('Raw profile'!E285>0,2,0)) -> 1 | G24: =IF('Raw profile'!F182>0,1,IF('Raw profile'!F285>0,2,0)) -> 1 | H24: =IF('Raw profile'!G182>0,1,IF('Raw profile'!G285>0,2,0)) -> 1 | I24: =IF('Raw profile'!H182>0,1,IF('Raw profile'!H285>0,2,0)) -> 1 | J24: =IF('Raw profile'!I182>0,1,IF('Raw profile'!I285>0,2,0)) -> 1 | K24: =IF('Raw profile'!J182>0,1,IF('Raw profile'!J285>0,2,0)) -> 1 | ... BK24: =IF('Raw profile'!BJ182>0,1,IF('Raw profile'!BJ285>0,2,0)) -> 0
B25: Growth | C25: ='Growth profile'!I74 -> 2026 | D25: =IF('Growth profile'!C182>0,1,IF('Growth profile'!C285>0,3,0)) -> 1 | E25: =IF('Growth profile'!D182>0,1,IF('Growth profile'!D285>0,3,0)) -> 1 | F25: =IF('Growth profile'!E182>0,1,IF('Growth profile'!E285>0,3,0)) -> 1 | G25: =IF('Growth profile'!F182>0,1,IF('Growth profile'!F285>0,3,0)) -> 1 | H25: =IF('Growth profile'!G182>0,1,IF('Growth profile'!G285>0,3,0)) -> 1 | I25: =IF('Growth profile'!H182>0,1,IF('Growth profile'!H285>0,3,0)) -> 1 | J25: =IF('Growth profile'!I182>0,1,IF('Growth profile'!I285>0,3,0)) -> 1 | K25: =IF('Growth profile'!J182>0,1,IF('Growth profile'!J285>0,3,0)) -> 1 | ... BK25: =IF('Growth profile'!BJ182>0,1,IF('Growth profile'!BJ285>0,3,0)) -> 0
B26: No penalty | C26: ='Growth (no penalty)'!I74 -> 2026 | D26: =IF('Growth (no penalty)'!C182>0,1,IF('Growth (no penalty)'!C285>0,4,0)) -> 1 | E26: =IF('Growth (no penalty)'!D182>0,1,IF('Growth (no penalty)'!D285>0,4,0)) -> 1 | F26: =IF('Growth (no penalty)'!E182>0,1,IF('Growth (no penalty)'!E285>0,4,0)) -> 1 | G26: =IF('Growth (no penalty)'!F182>0,1,IF('Growth (no penalty)'!F285>0,4,0)) -> 1 | H26: =IF('Growth (no penalty)'!G182>0,1,IF('Growth (no penalty)'!G285>0,4,0)) -> 1 | I26: =IF('Growth (no penalty)'!H182>0,1,IF('Growth (no penalty)'!H285>0,4,0)) -> 1 | J26: =IF('Growth (no penalty)'!I182>0,1,IF('Growth (no penalty)'!I285>0,4,0)) -> 1 | K26: =IF('Growth (no penalty)'!J182>0,1,IF('Growth (no penalty)'!J285>0,4,0)) -> 1 | ... BK26: =IF('Growth (no penalty)'!BJ182>0,1,IF('Growth (no penalty)'!BJ285>0,4,0)) -> 0
A27: ='Growth profile'!A79 -> project 116 | B27: Raw | C27: ='Raw profile'!I79 -> 2026 | D27: =IF('Raw profile'!C187>0,1,IF('Raw profile'!C290>0,2,0)) -> 1 | E27: =IF('Raw profile'!D187>0,1,IF('Raw profile'!D290>0,2,0)) -> 1 | F27: =IF('Raw profile'!E187>0,1,IF('Raw profile'!E290>0,2,0)) -> 1 | G27: =IF('Raw profile'!F187>0,1,IF('Raw profile'!F290>0,2,0)) -> 1 | H27: =IF('Raw profile'!G187>0,1,IF('Raw profile'!G290>0,2,0)) -> 1 | I27: =IF('Raw profile'!H187>0,1,IF('Raw profile'!H290>0,2,0)) -> 2 | J27: =IF('Raw profile'!I187>0,1,IF('Raw profile'!I290>0,2,0)) -> 2 | K27: =IF('Raw profile'!J187>0,1,IF('Raw profile'!J290>0,2,0)) -> 2 | ... BK27: =IF('Raw profile'!BJ187>0,1,IF('Raw profile'!BJ290>0,2,0)) -> 0
B28: Growth | C28: ='Growth profile'!I79 -> 2026 | D28: =IF('Growth profile'!C187>0,1,IF('Growth profile'!C290>0,3,0)) -> 1 | E28: =IF('Growth profile'!D187>0,1,IF('Growth profile'!D290>0,3,0)) -> 1 | F28: =IF('Growth profile'!E187>0,1,IF('Growth profile'!E290>0,3,0)) -> 1 | G28: =IF('Growth profile'!F187>0,1,IF('Growth profile'!F290>0,3,0)) -> 1 | H28: =IF('Growth profile'!G187>0,1,IF('Growth profile'!G290>0,3,0)) -> 1 | I28: =IF('Growth profile'!H187>0,1,IF('Growth profile'!H290>0,3,0)) -> 3 | J28: =IF('Growth profile'!I187>0,1,IF('Growth profile'!I290>0,3,0)) -> 3 | K28: =IF('Growth profile'!J187>0,1,IF('Growth profile'!J290>0,3,0)) -> 3 | ... BK28: =IF('Growth profile'!BJ187>0,1,IF('Growth profile'!BJ290>0,3,0)) -> 0
B29: No penalty | C29: ='Growth (no penalty)'!I79 -> 2026 | D29: =IF('Growth (no penalty)'!C187>0,1,IF('Growth (no penalty)'!C290>0,4,0)) -> 1 | E29: =IF('Growth (no penalty)'!D187>0,1,IF('Growth (no penalty)'!D290>0,4,0)) -> 1 | F29: =IF('Growth (no penalty)'!E187>0,1,IF('Growth (no penalty)'!E290>0,4,0)) -> 1 | G29: =IF('Growth (no penalty)'!F187>0,1,IF('Growth (no penalty)'!F290>0,4,0)) -> 1 | H29: =IF('Growth (no penalty)'!G187>0,1,IF('Growth (no penalty)'!G290>0,4,0)) -> 1 | I29: =IF('Growth (no penalty)'!H187>0,1,IF('Growth (no penalty)'!H290>0,4,0)) -> 4 | J29: =IF('Growth (no penalty)'!I187>0,1,IF('Growth (no penalty)'!I290>0,4,0)) -> 4 | K29: =IF('Growth (no penalty)'!J187>0,1,IF('Growth (no penalty)'!J290>0,4,0)) -> 4 | ... BK29: =IF('Growth (no penalty)'!BJ187>0,1,IF('Growth (no penalty)'!BJ290>0,4,0)) -> 0
A30: ='Growth profile'!A81 -> project 120 | B30: Raw | C30: ='Raw profile'!I81 -> 2026 | D30: =IF('Raw profile'!C189>0,1,IF('Raw profile'!C292>0,2,0)) -> 1 | E30: =IF('Raw profile'!D189>0,1,IF('Raw profile'!D292>0,2,0)) -> 1 | F30: =IF('Raw profile'!E189>0,1,IF('Raw profile'!E292>0,2,0)) -> 1 | G30: =IF('Raw profile'!F189>0,1,IF('Raw profile'!F292>0,2,0)) -> 1 | H30: =IF('Raw profile'!G189>0,1,IF('Raw profile'!G292>0,2,0)) -> 1 | I30: =IF('Raw profile'!H189>0,1,IF('Raw profile'!H292>0,2,0)) -> 1 | J30: =IF('Raw profile'!I189>0,1,IF('Raw profile'!I292>0,2,0)) -> 2 | K30: =IF('Raw profile'!J189>0,1,IF('Raw profile'!J292>0,2,0)) -> 2 | ... BK30: =IF('Raw profile'!BJ189>0,1,IF('Raw profile'!BJ292>0,2,0)) -> 0
B31: Growth | C31: ='Growth profile'!I81 -> 2026 | D31: =IF('Growth profile'!C189>0,1,IF('Growth profile'!C292>0,3,0)) -> 1 | E31: =IF('Growth profile'!D189>0,1,IF('Growth profile'!D292>0,3,0)) -> 1 | F31: =IF('Growth profile'!E189>0,1,IF('Growth profile'!E292>0,3,0)) -> 1 | G31: =IF('Growth profile'!F189>0,1,IF('Growth profile'!F292>0,3,0)) -> 1 | H31: =IF('Growth profile'!G189>0,1,IF('Growth profile'!G292>0,3,0)) -> 1 | I31: =IF('Growth profile'!H189>0,1,IF('Growth profile'!H292>0,3,0)) -> 1 | J31: =IF('Growth profile'!I189>0,1,IF('Growth profile'!I292>0,3,0)) -> 3 | K31: =IF('Growth profile'!J189>0,1,IF('Growth profile'!J292>0,3,0)) -> 3 | ... BK31: =IF('Growth profile'!BJ189>0,1,IF('Growth profile'!BJ292>0,3,0)) -> 0
B32: No penalty | C32: ='Growth (no penalty)'!I81 -> 2026 | D32: =IF('Growth (no penalty)'!C189>0,1,IF('Growth (no penalty)'!C292>0,4,0)) -> 1 | E32: =IF('Growth (no penalty)'!D189>0,1,IF('Growth (no penalty)'!D292>0,4,0)) -> 1 | F32: =IF('Growth (no penalty)'!E189>0,1,IF('Growth (no penalty)'!E292>0,4,0)) -> 1 | G32: =IF('Growth (no penalty)'!F189>0,1,IF('Growth (no penalty)'!F292>0,4,0)) -> 1 | H32: =IF('Growth (no penalty)'!G189>0,1,IF('Growth (no penalty)'!G292>0,4,0)) -> 1 | I32: =IF('Growth (no penalty)'!H189>0,1,IF('Growth (no penalty)'!H292>0,4,0)) -> 1 | J32: =IF('Growth (no penalty)'!I189>0,1,IF('Growth (no penalty)'!I292>0,4,0)) -> 4 | K32: =IF('Growth (no penalty)'!J189>0,1,IF('Growth (no penalty)'!J292>0,4,0)) -> 4 | ... BK32: =IF('Growth (no penalty)'!BJ189>0,1,IF('Growth (no penalty)'!BJ292>0,4,0)) -> 0
A33: ='Growth profile'!A97 -> project 153 | B33: Raw | C33: ='Raw profile'!I97 -> 2026 | D33: =IF('Raw profile'!C205>0,1,IF('Raw profile'!C308>0,2,0)) -> 1 | E33: =IF('Raw profile'!D205>0,1,IF('Raw profile'!D308>0,2,0)) -> 1 | F33: =IF('Raw profile'!E205>0,1,IF('Raw profile'!E308>0,2,0)) -> 2 | G33: =IF('Raw profile'!F205>0,1,IF('Raw profile'!F308>0,2,0)) -> 2 | H33: =IF('Raw profile'!G205>0,1,IF('Raw profile'!G308>0,2,0)) -> 2 | I33: =IF('Raw profile'!H205>0,1,IF('Raw profile'!H308>0,2,0)) -> 2 | J33: =IF('Raw profile'!I205>0,1,IF('Raw profile'!I308>0,2,0)) -> 2 | K33: =IF('Raw profile'!J205>0,1,IF('Raw profile'!J308>0,2,0)) -> 2 | ... BK33: =IF('Raw profile'!BJ205>0,1,IF('Raw profile'!BJ308>0,2,0)) -> 0
B34: Growth | C34: ='Growth profile'!I97 -> 2026 | D34: =IF('Growth profile'!C205>0,1,IF('Growth profile'!C308>0,3,0)) -> 1 | E34: =IF('Growth profile'!D205>0,1,IF('Growth profile'!D308>0,3,0)) -> 1 | F34: =IF('Growth profile'!E205>0,1,IF('Growth profile'!E308>0,3,0)) -> 3 | G34: =IF('Growth profile'!F205>0,1,IF('Growth profile'!F308>0,3,0)) -> 3 | H34: =IF('Growth profile'!G205>0,1,IF('Growth profile'!G308>0,3,0)) -> 3 | I34: =IF('Growth profile'!H205>0,1,IF('Growth profile'!H308>0,3,0)) -> 3 | J34: =IF('Growth profile'!I205>0,1,IF('Growth profile'!I308>0,3,0)) -> 3 | K34: =IF('Growth profile'!J205>0,1,IF('Growth profile'!J308>0,3,0)) -> 3 | ... BK34: =IF('Growth profile'!BJ205>0,1,IF('Growth profile'!BJ308>0,3,0)) -> 0
B35: No penalty | C35: ='Growth (no penalty)'!I97 -> 2026 | D35: =IF('Growth (no penalty)'!C205>0,1,IF('Growth (no penalty)'!C308>0,4,0)) -> 1 | E35: =IF('Growth (no penalty)'!D205>0,1,IF('Growth (no penalty)'!D308>0,4,0)) -> 1 | F35: =IF('Growth (no penalty)'!E205>0,1,IF('Growth (no penalty)'!E308>0,4,0)) -> 4 | G35: =IF('Growth (no penalty)'!F205>0,1,IF('Growth (no penalty)'!F308>0,4,0)) -> 4 | H35: =IF('Growth (no penalty)'!G205>0,1,IF('Growth (no penalty)'!G308>0,4,0)) -> 4 | I35: =IF('Growth (no penalty)'!H205>0,1,IF('Growth (no penalty)'!H308>0,4,0)) -> 4 | J35: =IF('Growth (no penalty)'!I205>0,1,IF('Growth (no penalty)'!I308>0,4,0)) -> 4 | K35: =IF('Growth (no penalty)'!J205>0,1,IF('Growth (no penalty)'!J308>0,4,0)) -> 4 | ... BK35: =IF('Growth (no penalty)'!BJ205>0,1,IF('Growth (no penalty)'!BJ308>0,4,0)) -> 0
A36: ='Growth profile'!A121 -> project 211 | B36: Raw | C36: ='Raw profile'!I121 -> 2026 | D36: =IF('Raw profile'!C229>0,1,IF('Raw profile'!C332>0,2,0)) -> 1 | E36: =IF('Raw profile'!D229>0,1,IF('Raw profile'!D332>0,2,0)) -> 2 | F36: =IF('Raw profile'!E229>0,1,IF('Raw profile'!E332>0,2,0)) -> 2 | G36: =IF('Raw profile'!F229>0,1,IF('Raw profile'!F332>0,2,0)) -> 2 | H36: =IF('Raw profile'!G229>0,1,IF('Raw profile'!G332>0,2,0)) -> 2 | I36: =IF('Raw profile'!H229>0,1,IF('Raw profile'!H332>0,2,0)) -> 2 | J36: =IF('Raw profile'!I229>0,1,IF('Raw profile'!I332>0,2,0)) -> 2 | K36: =IF('Raw profile'!J229>0,1,IF('Raw profile'!J332>0,2,0)) -> 2 | ... BK36: =IF('Raw profile'!BJ229>0,1,IF('Raw profile'!BJ332>0,2,0)) -> 0
B37: Growth | C37: ='Growth profile'!I121 -> 2026 | D37: =IF('Growth profile'!C229>0,1,IF('Growth profile'!C332>0,3,0)) -> 1 | E37: =IF('Growth profile'!D229>0,1,IF('Growth profile'!D332>0,3,0)) -> 3 | F37: =IF('Growth profile'!E229>0,1,IF('Growth profile'!E332>0,3,0)) -> 3 | G37: =IF('Growth profile'!F229>0,1,IF('Growth profile'!F332>0,3,0)) -> 3 | H37: =IF('Growth profile'!G229>0,1,IF('Growth profile'!G332>0,3,0)) -> 3 | I37: =IF('Growth profile'!H229>0,1,IF('Growth profile'!H332>0,3,0)) -> 3 | J37: =IF('Growth profile'!I229>0,1,IF('Growth profile'!I332>0,3,0)) -> 3 | K37: =IF('Growth profile'!J229>0,1,IF('Growth profile'!J332>0,3,0)) -> 3 | ... BK37: =IF('Growth profile'!BJ229>0,1,IF('Growth profile'!BJ332>0,3,0)) -> 0
B38: No penalty | C38: ='Growth (no penalty)'!I121 -> 2026 | D38: =IF('Growth (no penalty)'!C229>0,1,IF('Growth (no penalty)'!C332>0,4,0)) -> 1 | E38: =IF('Growth (no penalty)'!D229>0,1,IF('Growth (no penalty)'!D332>0,4,0)) -> 4 | F38: =IF('Growth (no penalty)'!E229>0,1,IF('Growth (no penalty)'!E332>0,4,0)) -> 4 | G38: =IF('Growth (no penalty)'!F229>0,1,IF('Growth (no penalty)'!F332>0,4,0)) -> 4 | H38: =IF('Growth (no penalty)'!G229>0,1,IF('Growth (no penalty)'!G332>0,4,0)) -> 4 | I38: =IF('Growth (no penalty)'!H229>0,1,IF('Growth (no penalty)'!H332>0,4,0)) -> 4 | J38: =IF('Growth (no penalty)'!I229>0,1,IF('Growth (no penalty)'!I332>0,4,0)) -> 4 | K38: =IF('Growth (no penalty)'!J229>0,1,IF('Growth (no penalty)'!J332>0,4,0)) -> 4 | ... BK38: =IF('Growth (no penalty)'!BJ229>0,1,IF('Growth (no penalty)'!BJ332>0,4,0)) -> 0
A39: ='Growth profile'!A49 -> project 44 | B39: Raw | C39: ='Raw profile'!I49 -> 2026 | D39: =IF('Raw profile'!C157>0,1,IF('Raw profile'!C260>0,2,0)) -> 1 | E39: =IF('Raw profile'!D157>0,1,IF('Raw profile'!D260>0,2,0)) -> 2 | F39: =IF('Raw profile'!E157>0,1,IF('Raw profile'!E260>0,2,0)) -> 2 | G39: =IF('Raw profile'!F157>0,1,IF('Raw profile'!F260>0,2,0)) -> 2 | H39: =IF('Raw profile'!G157>0,1,IF('Raw profile'!G260>0,2,0)) -> 2 | I39: =IF('Raw profile'!H157>0,1,IF('Raw profile'!H260>0,2,0)) -> 2 | J39: =IF('Raw profile'!I157>0,1,IF('Raw profile'!I260>0,2,0)) -> 2 | K39: =IF('Raw profile'!J157>0,1,IF('Raw profile'!J260>0,2,0)) -> 2 | ... BK39: =IF('Raw profile'!BJ157>0,1,IF('Raw profile'!BJ260>0,2,0)) -> 0
B40: Growth | C40: ='Growth profile'!I49 -> 2031 | D40: =IF('Growth profile'!C157>0,1,IF('Growth profile'!C260>0,3,0)) -> 0 | E40: =IF('Growth profile'!D157>0,1,IF('Growth profile'!D260>0,3,0)) -> 0 | F40: =IF('Growth profile'!E157>0,1,IF('Growth profile'!E260>0,3,0)) -> 0 | G40: =IF('Growth profile'!F157>0,1,IF('Growth profile'!F260>0,3,0)) -> 0 | H40: =IF('Growth profile'!G157>0,1,IF('Growth profile'!G260>0,3,0)) -> 0 | I40: =IF('Growth profile'!H157>0,1,IF('Growth profile'!H260>0,3,0)) -> 1 | J40: =IF('Growth profile'!I157>0,1,IF('Growth profile'!I260>0,3,0)) -> 3 | K40: =IF('Growth profile'!J157>0,1,IF('Growth profile'!J260>0,3,0)) -> 3 | ... BK40: =IF('Growth profile'!BJ157>0,1,IF('Growth profile'!BJ260>0,3,0)) -> 0
B41: No penalty | C41: ='Growth (no penalty)'!I49 -> 2032 | D41: =IF('Growth (no penalty)'!C157>0,1,IF('Growth (no penalty)'!C260>0,4,0)) -> 0 | E41: =IF('Growth (no penalty)'!D157>0,1,IF('Growth (no penalty)'!D260>0,4,0)) -> 0 | F41: =IF('Growth (no penalty)'!E157>0,1,IF('Growth (no penalty)'!E260>0,4,0)) -> 0 | G41: =IF('Growth (no penalty)'!F157>0,1,IF('Growth (no penalty)'!F260>0,4,0)) -> 0 | H41: =IF('Growth (no penalty)'!G157>0,1,IF('Growth (no penalty)'!G260>0,4,0)) -> 0 | I41: =IF('Growth (no penalty)'!H157>0,1,IF('Growth (no penalty)'!H260>0,4,0)) -> 0 | J41: =IF('Growth (no penalty)'!I157>0,1,IF('Growth (no penalty)'!I260>0,4,0)) -> 1 | K41: =IF('Growth (no penalty)'!J157>0,1,IF('Growth (no penalty)'!J260>0,4,0)) -> 4 | ... BK41: =IF('Growth (no penalty)'!BJ157>0,1,IF('Growth (no penalty)'!BJ260>0,4,0)) -> 0
A42: ='Growth profile'!A96 -> project 150 | B42: Raw | C42: ='Raw profile'!I96 -> 2026 | D42: =IF('Raw profile'!C204>0,1,IF('Raw profile'!C307>0,2,0)) -> 1 | E42: =IF('Raw profile'!D204>0,1,IF('Raw profile'!D307>0,2,0)) -> 1 | F42: =IF('Raw profile'!E204>0,1,IF('Raw profile'!E307>0,2,0)) -> 2 | G42: =IF('Raw profile'!F204>0,1,IF('Raw profile'!F307>0,2,0)) -> 2 | H42: =IF('Raw profile'!G204>0,1,IF('Raw profile'!G307>0,2,0)) -> 2 | I42: =IF('Raw profile'!H204>0,1,IF('Raw profile'!H307>0,2,0)) -> 2 | J42: =IF('Raw profile'!I204>0,1,IF('Raw profile'!I307>0,2,0)) -> 2 | K42: =IF('Raw profile'!J204>0,1,IF('Raw profile'!J307>0,2,0)) -> 2 | ... BK42: =IF('Raw profile'!BJ204>0,1,IF('Raw profile'!BJ307>0,2,0)) -> 0
B43: Growth | C43: ='Growth profile'!I96 -> 2034 | D43: =IF('Growth profile'!C204>0,1,IF('Growth profile'!C307>0,3,0)) -> 0 | E43: =IF('Growth profile'!D204>0,1,IF('Growth profile'!D307>0,3,0)) -> 0 | F43: =IF('Growth profile'!E204>0,1,IF('Growth profile'!E307>0,3,0)) -> 0 | G43: =IF('Growth profile'!F204>0,1,IF('Growth profile'!F307>0,3,0)) -> 0 | H43: =IF('Growth profile'!G204>0,1,IF('Growth profile'!G307>0,3,0)) -> 0 | I43: =IF('Growth profile'!H204>0,1,IF('Growth profile'!H307>0,3,0)) -> 0 | J43: =IF('Growth profile'!I204>0,1,IF('Growth profile'!I307>0,3,0)) -> 0 | K43: =IF('Growth profile'!J204>0,1,IF('Growth profile'!J307>0,3,0)) -> 0 | ... BK43: =IF('Growth profile'!BJ204>0,1,IF('Growth profile'!BJ307>0,3,0)) -> 0
B44: No penalty | C44: ='Growth (no penalty)'!I96 -> 2044 | D44: =IF('Growth (no penalty)'!C204>0,1,IF('Growth (no penalty)'!C307>0,4,0)) -> 0 | E44: =IF('Growth (no penalty)'!D204>0,1,IF('Growth (no penalty)'!D307>0,4,0)) -> 0 | F44: =IF('Growth (no penalty)'!E204>0,1,IF('Growth (no penalty)'!E307>0,4,0)) -> 0 | G44: =IF('Growth (no penalty)'!F204>0,1,IF('Growth (no penalty)'!F307>0,4,0)) -> 0 | H44: =IF('Growth (no penalty)'!G204>0,1,IF('Growth (no penalty)'!G307>0,4,0)) -> 0 | I44: =IF('Growth (no penalty)'!H204>0,1,IF('Growth (no penalty)'!H307>0,4,0)) -> 0 | J44: =IF('Growth (no penalty)'!I204>0,1,IF('Growth (no penalty)'!I307>0,4,0)) -> 0 | K44: =IF('Growth (no penalty)'!J204>0,1,IF('Growth (no penalty)'!J307>0,4,0)) -> 0 | ... BK44: =IF('Growth (no penalty)'!BJ204>0,1,IF('Growth (no penalty)'!BJ307>0,4,0)) -> 4
A45: ='Growth profile'!A32 -> project 20 | B45: Raw | C45: ='Raw profile'!I32 -> 2026 | D45: =IF('Raw profile'!C140>0,1,IF('Raw profile'!C243>0,2,0)) -> 1 | E45: =IF('Raw profile'!D140>0,1,IF('Raw profile'!D243>0,2,0)) -> 1 | F45: =IF('Raw profile'!E140>0,1,IF('Raw profile'!E243>0,2,0)) -> 2 | G45: =IF('Raw profile'!F140>0,1,IF('Raw profile'!F243>0,2,0)) -> 2 | H45: =IF('Raw profile'!G140>0,1,IF('Raw profile'!G243>0,2,0)) -> 2 | I45: =IF('Raw profile'!H140>0,1,IF('Raw profile'!H243>0,2,0)) -> 2 | J45: =IF('Raw profile'!I140>0,1,IF('Raw profile'!I243>0,2,0)) -> 2 | K45: =IF('Raw profile'!J140>0,1,IF('Raw profile'!J243>0,2,0)) -> 2 | ... BK45: =IF('Raw profile'!BJ140>0,1,IF('Raw profile'!BJ243>0,2,0)) -> 0
B46: Growth | C46: ='Growth profile'!I32 -> 2035 | D46: =IF('Growth profile'!C140>0,1,IF('Growth profile'!C243>0,3,0)) -> 0 | E46: =IF('Growth profile'!D140>0,1,IF('Growth profile'!D243>0,3,0)) -> 0 | F46: =IF('Growth profile'!E140>0,1,IF('Growth profile'!E243>0,3,0)) -> 0 | G46: =IF('Growth profile'!F140>0,1,IF('Growth profile'!F243>0,3,0)) -> 0 | H46: =IF('Growth profile'!G140>0,1,IF('Growth profile'!G243>0,3,0)) -> 0 | I46: =IF('Growth profile'!H140>0,1,IF('Growth profile'!H243>0,3,0)) -> 0 | J46: =IF('Growth profile'!I140>0,1,IF('Growth profile'!I243>0,3,0)) -> 0 | K46: =IF('Growth profile'!J140>0,1,IF('Growth profile'!J243>0,3,0)) -> 0 | ... BK46: =IF('Growth profile'!BJ140>0,1,IF('Growth profile'!BJ243>0,3,0)) -> 0
B47: No penalty | C47: ='Growth (no penalty)'!I32 -> 2044 | D47: =IF('Growth (no penalty)'!C140>0,1,IF('Growth (no penalty)'!C243>0,4,0)) -> 0 | E47: =IF('Growth (no penalty)'!D140>0,1,IF('Growth (no penalty)'!D243>0,4,0)) -> 0 | F47: =IF('Growth (no penalty)'!E140>0,1,IF('Growth (no penalty)'!E243>0,4,0)) -> 0 | G47: =IF('Growth (no penalty)'!F140>0,1,IF('Growth (no penalty)'!F243>0,4,0)) -> 0 | H47: =IF('Growth (no penalty)'!G140>0,1,IF('Growth (no penalty)'!G243>0,4,0)) -> 0 | I47: =IF('Growth (no penalty)'!H140>0,1,IF('Growth (no penalty)'!H243>0,4,0)) -> 0 | J47: =IF('Growth (no penalty)'!I140>0,1,IF('Growth (no penalty)'!I243>0,4,0)) -> 0 | K47: =IF('Growth (no penalty)'!J140>0,1,IF('Growth (no penalty)'!J243>0,4,0)) -> 0 | ... BK47: =IF('Growth (no penalty)'!BJ140>0,1,IF('Growth (no penalty)'!BJ243>0,4,0)) -> 4
A48: ='Growth profile'!A48 -> project 43 | B48: Raw | C48: ='Raw profile'!I48 -> 2026 | D48: =IF('Raw profile'!C156>0,1,IF('Raw profile'!C259>0,2,0)) -> 1 | E48: =IF('Raw profile'!D156>0,1,IF('Raw profile'!D259>0,2,0)) -> 2 | F48: =IF('Raw profile'!E156>0,1,IF('Raw profile'!E259>0,2,0)) -> 2 | G48: =IF('Raw profile'!F156>0,1,IF('Raw profile'!F259>0,2,0)) -> 2 | H48: =IF('Raw profile'!G156>0,1,IF('Raw profile'!G259>0,2,0)) -> 2 | I48: =IF('Raw profile'!H156>0,1,IF('Raw profile'!H259>0,2,0)) -> 2 | J48: =IF('Raw profile'!I156>0,1,IF('Raw profile'!I259>0,2,0)) -> 2 | K48: =IF('Raw profile'!J156>0,1,IF('Raw profile'!J259>0,2,0)) -> 2 | ... BK48: =IF('Raw profile'!BJ156>0,1,IF('Raw profile'!BJ259>0,2,0)) -> 0
B49: Growth | C49: ='Growth profile'!I48 -> 2035 | D49: =IF('Growth profile'!C156>0,1,IF('Growth profile'!C259>0,3,0)) -> 0 | E49: =IF('Growth profile'!D156>0,1,IF('Growth profile'!D259>0,3,0)) -> 0 | F49: =IF('Growth profile'!E156>0,1,IF('Growth profile'!E259>0,3,0)) -> 0 | G49: =IF('Growth profile'!F156>0,1,IF('Growth profile'!F259>0,3,0)) -> 0 | H49: =IF('Growth profile'!G156>0,1,IF('Growth profile'!G259>0,3,0)) -> 0 | I49: =IF('Growth profile'!H156>0,1,IF('Growth profile'!H259>0,3,0)) -> 0 | J49: =IF('Growth profile'!I156>0,1,IF('Growth profile'!I259>0,3,0)) -> 0 | K49: =IF('Growth profile'!J156>0,1,IF('Growth profile'!J259>0,3,0)) -> 0 | ... BK49: =IF('Growth profile'!BJ156>0,1,IF('Growth profile'!BJ259>0,3,0)) -> 0
B50: No penalty | C50: ='Growth (no penalty)'!I48 -> 2045 | D50: =IF('Growth (no penalty)'!C156>0,1,IF('Growth (no penalty)'!C259>0,4,0)) -> 0 | E50: =IF('Growth (no penalty)'!D156>0,1,IF('Growth (no penalty)'!D259>0,4,0)) -> 0 | F50: =IF('Growth (no penalty)'!E156>0,1,IF('Growth (no penalty)'!E259>0,4,0)) -> 0 | G50: =IF('Growth (no penalty)'!F156>0,1,IF('Growth (no penalty)'!F259>0,4,0)) -> 0 | H50: =IF('Growth (no penalty)'!G156>0,1,IF('Growth (no penalty)'!G259>0,4,0)) -> 0 | I50: =IF('Growth (no penalty)'!H156>0,1,IF('Growth (no penalty)'!H259>0,4,0)) -> 0 | J50: =IF('Growth (no penalty)'!I156>0,1,IF('Growth (no penalty)'!I259>0,4,0)) -> 0 | K50: =IF('Growth (no penalty)'!J156>0,1,IF('Growth (no penalty)'!J259>0,4,0)) -> 0 | ... BK50: =IF('Growth (no penalty)'!BJ156>0,1,IF('Growth (no penalty)'!BJ259>0,4,0)) -> 4
A51: ='Growth profile'!A29 -> project 12 | B51: Raw | C51: ='Raw profile'!I29 -> 2026 | D51: =IF('Raw profile'!C137>0,1,IF('Raw profile'!C240>0,2,0)) -> 1 | E51: =IF('Raw profile'!D137>0,1,IF('Raw profile'!D240>0,2,0)) -> 1 | F51: =IF('Raw profile'!E137>0,1,IF('Raw profile'!E240>0,2,0)) -> 2 | G51: =IF('Raw profile'!F137>0,1,IF('Raw profile'!F240>0,2,0)) -> 2 | H51: =IF('Raw profile'!G137>0,1,IF('Raw profile'!G240>0,2,0)) -> 2 | I51: =IF('Raw profile'!H137>0,1,IF('Raw profile'!H240>0,2,0)) -> 2 | J51: =IF('Raw profile'!I137>0,1,IF('Raw profile'!I240>0,2,0)) -> 2 | K51: =IF('Raw profile'!J137>0,1,IF('Raw profile'!J240>0,2,0)) -> 2 | ... BK51: =IF('Raw profile'!BJ137>0,1,IF('Raw profile'!BJ240>0,2,0)) -> 0
B52: Growth | C52: ='Growth profile'!I29 -> 2037 | D52: =IF('Growth profile'!C137>0,1,IF('Growth profile'!C240>0,3,0)) -> 0 | E52: =IF('Growth profile'!D137>0,1,IF('Growth profile'!D240>0,3,0)) -> 0 | F52: =IF('Growth profile'!E137>0,1,IF('Growth profile'!E240>0,3,0)) -> 0 | G52: =IF('Growth profile'!F137>0,1,IF('Growth profile'!F240>0,3,0)) -> 0 | H52: =IF('Growth profile'!G137>0,1,IF('Growth profile'!G240>0,3,0)) -> 0 | I52: =IF('Growth profile'!H137>0,1,IF('Growth profile'!H240>0,3,0)) -> 0 | J52: =IF('Growth profile'!I137>0,1,IF('Growth profile'!I240>0,3,0)) -> 0 | K52: =IF('Growth profile'!J137>0,1,IF('Growth profile'!J240>0,3,0)) -> 0 | ... BK52: =IF('Growth profile'!BJ137>0,1,IF('Growth profile'!BJ240>0,3,0)) -> 0
B53: No penalty | C53: ='Growth (no penalty)'!I29 -> 2044 | D53: =IF('Growth (no penalty)'!C137>0,1,IF('Growth (no penalty)'!C240>0,4,0)) -> 0 | E53: =IF('Growth (no penalty)'!D137>0,1,IF('Growth (no penalty)'!D240>0,4,0)) -> 0 | F53: =IF('Growth (no penalty)'!E137>0,1,IF('Growth (no penalty)'!E240>0,4,0)) -> 0 | G53: =IF('Growth (no penalty)'!F137>0,1,IF('Growth (no penalty)'!F240>0,4,0)) -> 0 | H53: =IF('Growth (no penalty)'!G137>0,1,IF('Growth (no penalty)'!G240>0,4,0)) -> 0 | I53: =IF('Growth (no penalty)'!H137>0,1,IF('Growth (no penalty)'!H240>0,4,0)) -> 0 | J53: =IF('Growth (no penalty)'!I137>0,1,IF('Growth (no penalty)'!I240>0,4,0)) -> 0 | K53: =IF('Growth (no penalty)'!J137>0,1,IF('Growth (no penalty)'!J240>0,4,0)) -> 0 | ... BK53: =IF('Growth (no penalty)'!BJ137>0,1,IF('Growth (no penalty)'!BJ240>0,4,0)) -> 4
A54: ='Growth profile'!A112 -> project 184 | B54: Raw | C54: ='Raw profile'!I112 -> 2026 | D54: =IF('Raw profile'!C220>0,1,IF('Raw profile'!C323>0,2,0)) -> 1 | E54: =IF('Raw profile'!D220>0,1,IF('Raw profile'!D323>0,2,0)) -> 2 | F54: =IF('Raw profile'!E220>0,1,IF('Raw profile'!E323>0,2,0)) -> 2 | G54: =IF('Raw profile'!F220>0,1,IF('Raw profile'!F323>0,2,0)) -> 2 | H54: =IF('Raw profile'!G220>0,1,IF('Raw profile'!G323>0,2,0)) -> 2 | I54: =IF('Raw profile'!H220>0,1,IF('Raw profile'!H323>0,2,0)) -> 2 | J54: =IF('Raw profile'!I220>0,1,IF('Raw profile'!I323>0,2,0)) -> 2 | K54: =IF('Raw profile'!J220>0,1,IF('Raw profile'!J323>0,2,0)) -> 2 | ... BK54: =IF('Raw profile'!BJ220>0,1,IF('Raw profile'!BJ323>0,2,0)) -> 0
B55: Growth | C55: ='Growth profile'!I112 -> 2037 | D55: =IF('Growth profile'!C220>0,1,IF('Growth profile'!C323>0,3,0)) -> 0 | E55: =IF('Growth profile'!D220>0,1,IF('Growth profile'!D323>0,3,0)) -> 0 | F55: =IF('Growth profile'!E220>0,1,IF('Growth profile'!E323>0,3,0)) -> 0 | G55: =IF('Growth profile'!F220>0,1,IF('Growth profile'!F323>0,3,0)) -> 0 | H55: =IF('Growth profile'!G220>0,1,IF('Growth profile'!G323>0,3,0)) -> 0 | I55: =IF('Growth profile'!H220>0,1,IF('Growth profile'!H323>0,3,0)) -> 0 | J55: =IF('Growth profile'!I220>0,1,IF('Growth profile'!I323>0,3,0)) -> 0 | K55: =IF('Growth profile'!J220>0,1,IF('Growth profile'!J323>0,3,0)) -> 0 | ... BK55: =IF('Growth profile'!BJ220>0,1,IF('Growth profile'!BJ323>0,3,0)) -> 0
B56: No penalty | C56: ='Growth (no penalty)'!I112 -> 2045 | D56: =IF('Growth (no penalty)'!C220>0,1,IF('Growth (no penalty)'!C323>0,4,0)) -> 0 | E56: =IF('Growth (no penalty)'!D220>0,1,IF('Growth (no penalty)'!D323>0,4,0)) -> 0 | F56: =IF('Growth (no penalty)'!E220>0,1,IF('Growth (no penalty)'!E323>0,4,0)) -> 0 | G56: =IF('Growth (no penalty)'!F220>0,1,IF('Growth (no penalty)'!F323>0,4,0)) -> 0 | H56: =IF('Growth (no penalty)'!G220>0,1,IF('Growth (no penalty)'!G323>0,4,0)) -> 0 | I56: =IF('Growth (no penalty)'!H220>0,1,IF('Growth (no penalty)'!H323>0,4,0)) -> 0 | J56: =IF('Growth (no penalty)'!I220>0,1,IF('Growth (no penalty)'!I323>0,4,0)) -> 0 | K56: =IF('Growth (no penalty)'!J220>0,1,IF('Growth (no penalty)'!J323>0,4,0)) -> 0 | ... BK56: =IF('Growth (no penalty)'!BJ220>0,1,IF('Growth (no penalty)'!BJ323>0,4,0)) -> 4
A57: ='Growth profile'!A70 -> project 100 | B57: Raw | C57: ='Raw profile'!I70 -> 2026 | D57: =IF('Raw profile'!C178>0,1,IF('Raw profile'!C281>0,2,0)) -> 1 | E57: =IF('Raw profile'!D178>0,1,IF('Raw profile'!D281>0,2,0)) -> 1 | F57: =IF('Raw profile'!E178>0,1,IF('Raw profile'!E281>0,2,0)) -> 2 | G57: =IF('Raw profile'!F178>0,1,IF('Raw profile'!F281>0,2,0)) -> 2 | H57: =IF('Raw profile'!G178>0,1,IF('Raw profile'!G281>0,2,0)) -> 2 | I57: =IF('Raw profile'!H178>0,1,IF('Raw profile'!H281>0,2,0)) -> 2 | J57: =IF('Raw profile'!I178>0,1,IF('Raw profile'!I281>0,2,0)) -> 2 | K57: =IF('Raw profile'!J178>0,1,IF('Raw profile'!J281>0,2,0)) -> 2 | ... BK57: =IF('Raw profile'!BJ178>0,1,IF('Raw profile'!BJ281>0,2,0)) -> 0
B58: Growth | C58: ='Growth profile'!I70 -> 2038 | D58: =IF('Growth profile'!C178>0,1,IF('Growth profile'!C281>0,3,0)) -> 0 | E58: =IF('Growth profile'!D178>0,1,IF('Growth profile'!D281>0,3,0)) -> 0 | F58: =IF('Growth profile'!E178>0,1,IF('Growth profile'!E281>0,3,0)) -> 0 | G58: =IF('Growth profile'!F178>0,1,IF('Growth profile'!F281>0,3,0)) -> 0 | H58: =IF('Growth profile'!G178>0,1,IF('Growth profile'!G281>0,3,0)) -> 0 | I58: =IF('Growth profile'!H178>0,1,IF('Growth profile'!H281>0,3,0)) -> 0 | J58: =IF('Growth profile'!I178>0,1,IF('Growth profile'!I281>0,3,0)) -> 0 | K58: =IF('Growth profile'!J178>0,1,IF('Growth profile'!J281>0,3,0)) -> 0 | ... BK58: =IF('Growth profile'!BJ178>0,1,IF('Growth profile'!BJ281>0,3,0)) -> 0
B59: No penalty | C59: ='Growth (no penalty)'!I70 -> 2044 | D59: =IF('Growth (no penalty)'!C178>0,1,IF('Growth (no penalty)'!C281>0,4,0)) -> 0 | E59: =IF('Growth (no penalty)'!D178>0,1,IF('Growth (no penalty)'!D281>0,4,0)) -> 0 | F59: =IF('Growth (no penalty)'!E178>0,1,IF('Growth (no penalty)'!E281>0,4,0)) -> 0 | G59: =IF('Growth (no penalty)'!F178>0,1,IF('Growth (no penalty)'!F281>0,4,0)) -> 0 | H59: =IF('Growth (no penalty)'!G178>0,1,IF('Growth (no penalty)'!G281>0,4,0)) -> 0 | I59: =IF('Growth (no penalty)'!H178>0,1,IF('Growth (no penalty)'!H281>0,4,0)) -> 0 | J59: =IF('Growth (no penalty)'!I178>0,1,IF('Growth (no penalty)'!I281>0,4,0)) -> 0 | K59: =IF('Growth (no penalty)'!J178>0,1,IF('Growth (no penalty)'!J281>0,4,0)) -> 0 | ... BK59: =IF('Growth (no penalty)'!BJ178>0,1,IF('Growth (no penalty)'!BJ281>0,4,0)) -> 4
A60: ='Growth profile'!A24 -> project 1 | B60: Raw | C60: ='Raw profile'!I24 -> 2026 | D60: =IF('Raw profile'!C132>0,1,IF('Raw profile'!C235>0,2,0)) -> 1 | E60: =IF('Raw profile'!D132>0,1,IF('Raw profile'!D235>0,2,0)) -> 1 | F60: =IF('Raw profile'!E132>0,1,IF('Raw profile'!E235>0,2,0)) -> 1 | G60: =IF('Raw profile'!F132>0,1,IF('Raw profile'!F235>0,2,0)) -> 1 | H60: =IF('Raw profile'!G132>0,1,IF('Raw profile'!G235>0,2,0)) -> 1 | I60: =IF('Raw profile'!H132>0,1,IF('Raw profile'!H235>0,2,0)) -> 1 | J60: =IF('Raw profile'!I132>0,1,IF('Raw profile'!I235>0,2,0)) -> 2 | K60: =IF('Raw profile'!J132>0,1,IF('Raw profile'!J235>0,2,0)) -> 2 | ... BK60: =IF('Raw profile'!BJ132>0,1,IF('Raw profile'!BJ235>0,2,0)) -> 0
B61: Growth | C61: ='Growth profile'!I24 -> 2039 | D61: =IF('Growth profile'!C132>0,1,IF('Growth profile'!C235>0,3,0)) -> 0 | E61: =IF('Growth profile'!D132>0,1,IF('Growth profile'!D235>0,3,0)) -> 0 | F61: =IF('Growth profile'!E132>0,1,IF('Growth profile'!E235>0,3,0)) -> 0 | G61: =IF('Growth profile'!F132>0,1,IF('Growth profile'!F235>0,3,0)) -> 0 | H61: =IF('Growth profile'!G132>0,1,IF('Growth profile'!G235>0,3,0)) -> 0 | I61: =IF('Growth profile'!H132>0,1,IF('Growth profile'!H235>0,3,0)) -> 0 | J61: =IF('Growth profile'!I132>0,1,IF('Growth profile'!I235>0,3,0)) -> 0 | K61: =IF('Growth profile'!J132>0,1,IF('Growth profile'!J235>0,3,0)) -> 0 | ... BK61: =IF('Growth profile'!BJ132>0,1,IF('Growth profile'!BJ235>0,3,0)) -> 0
B62: No penalty | C62: ='Growth (no penalty)'!I24 -> 2040 | D62: =IF('Growth (no penalty)'!C132>0,1,IF('Growth (no penalty)'!C235>0,4,0)) -> 0 | E62: =IF('Growth (no penalty)'!D132>0,1,IF('Growth (no penalty)'!D235>0,4,0)) -> 0 | F62: =IF('Growth (no penalty)'!E132>0,1,IF('Growth (no penalty)'!E235>0,4,0)) -> 0 | G62: =IF('Growth (no penalty)'!F132>0,1,IF('Growth (no penalty)'!F235>0,4,0)) -> 0 | H62: =IF('Growth (no penalty)'!G132>0,1,IF('Growth (no penalty)'!G235>0,4,0)) -> 0 | I62: =IF('Growth (no penalty)'!H132>0,1,IF('Growth (no penalty)'!H235>0,4,0)) -> 0 | J62: =IF('Growth (no penalty)'!I132>0,1,IF('Growth (no penalty)'!I235>0,4,0)) -> 0 | K62: =IF('Growth (no penalty)'!J132>0,1,IF('Growth (no penalty)'!J235>0,4,0)) -> 0 | ... BK62: =IF('Growth (no penalty)'!BJ132>0,1,IF('Growth (no penalty)'!BJ235>0,4,0)) -> 4
A63: ='Growth profile'!A119 -> project 200 | B63: Raw | C63: ='Raw profile'!I119 -> 2026 | D63: =IF('Raw profile'!C227>0,1,IF('Raw profile'!C330>0,2,0)) -> 1 | E63: =IF('Raw profile'!D227>0,1,IF('Raw profile'!D330>0,2,0)) -> 1 | F63: =IF('Raw profile'!E227>0,1,IF('Raw profile'!E330>0,2,0)) -> 2 | G63: =IF('Raw profile'!F227>0,1,IF('Raw profile'!F330>0,2,0)) -> 2 | H63: =IF('Raw profile'!G227>0,1,IF('Raw profile'!G330>0,2,0)) -> 2 | I63: =IF('Raw profile'!H227>0,1,IF('Raw profile'!H330>0,2,0)) -> 2 | J63: =IF('Raw profile'!I227>0,1,IF('Raw profile'!I330>0,2,0)) -> 2 | K63: =IF('Raw profile'!J227>0,1,IF('Raw profile'!J330>0,2,0)) -> 2 | ... BK63: =IF('Raw profile'!BJ227>0,1,IF('Raw profile'!BJ330>0,2,0)) -> 0
B64: Growth | C64: ='Growth profile'!I119 -> 2039 | D64: =IF('Growth profile'!C227>0,1,IF('Growth profile'!C330>0,3,0)) -> 0 | E64: =IF('Growth profile'!D227>0,1,IF('Growth profile'!D330>0,3,0)) -> 0 | F64: =IF('Growth profile'!E227>0,1,IF('Growth profile'!E330>0,3,0)) -> 0 | G64: =IF('Growth profile'!F227>0,1,IF('Growth profile'!F330>0,3,0)) -> 0 | H64: =IF('Growth profile'!G227>0,1,IF('Growth profile'!G330>0,3,0)) -> 0 | I64: =IF('Growth profile'!H227>0,1,IF('Growth profile'!H330>0,3,0)) -> 0 | J64: =IF('Growth profile'!I227>0,1,IF('Growth profile'!I330>0,3,0)) -> 0 | K64: =IF('Growth profile'!J227>0,1,IF('Growth profile'!J330>0,3,0)) -> 0 | ... BK64: =IF('Growth profile'!BJ227>0,1,IF('Growth profile'!BJ330>0,3,0)) -> 0
B65: No penalty | C65: ='Growth (no penalty)'!I119 -> 2044 | D65: =IF('Growth (no penalty)'!C227>0,1,IF('Growth (no penalty)'!C330>0,4,0)) -> 0 | E65: =IF('Growth (no penalty)'!D227>0,1,IF('Growth (no penalty)'!D330>0,4,0)) -> 0 | F65: =IF('Growth (no penalty)'!E227>0,1,IF('Growth (no penalty)'!E330>0,4,0)) -> 0 | G65: =IF('Growth (no penalty)'!F227>0,1,IF('Growth (no penalty)'!F330>0,4,0)) -> 0 | H65: =IF('Growth (no penalty)'!G227>0,1,IF('Growth (no penalty)'!G330>0,4,0)) -> 0 | I65: =IF('Growth (no penalty)'!H227>0,1,IF('Growth (no penalty)'!H330>0,4,0)) -> 0 | J65: =IF('Growth (no penalty)'!I227>0,1,IF('Growth (no penalty)'!I330>0,4,0)) -> 0 | K65: =IF('Growth (no penalty)'!J227>0,1,IF('Growth (no penalty)'!J330>0,4,0)) -> 0 | ... BK65: =IF('Growth (no penalty)'!BJ227>0,1,IF('Growth (no penalty)'!BJ330>0,4,0)) -> 4
A66: ='Growth profile'!A98 -> project 156 | B66: Raw | C66: ='Raw profile'!I98 -> 2026 | D66: =IF('Raw profile'!C206>0,1,IF('Raw profile'!C309>0,2,0)) -> 1 | E66: =IF('Raw profile'!D206>0,1,IF('Raw profile'!D309>0,2,0)) -> 1 | F66: =IF('Raw profile'!E206>0,1,IF('Raw profile'!E309>0,2,0)) -> 1 | G66: =IF('Raw profile'!F206>0,1,IF('Raw profile'!F309>0,2,0)) -> 1 | H66: =IF('Raw profile'!G206>0,1,IF('Raw profile'!G309>0,2,0)) -> 2 | I66: =IF('Raw profile'!H206>0,1,IF('Raw profile'!H309>0,2,0)) -> 2 | J66: =IF('Raw profile'!I206>0,1,IF('Raw profile'!I309>0,2,0)) -> 2 | K66: =IF('Raw profile'!J206>0,1,IF('Raw profile'!J309>0,2,0)) -> 2 | ... BK66: =IF('Raw profile'!BJ206>0,1,IF('Raw profile'!BJ309>0,2,0)) -> 0
B67: Growth | C67: ='Growth profile'!I98 -> 2040 | D67: =IF('Growth profile'!C206>0,1,IF('Growth profile'!C309>0,3,0)) -> 0 | E67: =IF('Growth profile'!D206>0,1,IF('Growth profile'!D309>0,3,0)) -> 0 | F67: =IF('Growth profile'!E206>0,1,IF('Growth profile'!E309>0,3,0)) -> 0 | G67: =IF('Growth profile'!F206>0,1,IF('Growth profile'!F309>0,3,0)) -> 0 | H67: =IF('Growth profile'!G206>0,1,IF('Growth profile'!G309>0,3,0)) -> 0 | I67: =IF('Growth profile'!H206>0,1,IF('Growth profile'!H309>0,3,0)) -> 0 | J67: =IF('Growth profile'!I206>0,1,IF('Growth profile'!I309>0,3,0)) -> 0 | K67: =IF('Growth profile'!J206>0,1,IF('Growth profile'!J309>0,3,0)) -> 0 | ... BK67: =IF('Growth profile'!BJ206>0,1,IF('Growth profile'!BJ309>0,3,0)) -> 0
B68: No penalty | C68: ='Growth (no penalty)'!I98 -> 2042 | D68: =IF('Growth (no penalty)'!C206>0,1,IF('Growth (no penalty)'!C309>0,4,0)) -> 0 | E68: =IF('Growth (no penalty)'!D206>0,1,IF('Growth (no penalty)'!D309>0,4,0)) -> 0 | F68: =IF('Growth (no penalty)'!E206>0,1,IF('Growth (no penalty)'!E309>0,4,0)) -> 0 | G68: =IF('Growth (no penalty)'!F206>0,1,IF('Growth (no penalty)'!F309>0,4,0)) -> 0 | H68: =IF('Growth (no penalty)'!G206>0,1,IF('Growth (no penalty)'!G309>0,4,0)) -> 0 | I68: =IF('Growth (no penalty)'!H206>0,1,IF('Growth (no penalty)'!H309>0,4,0)) -> 0 | J68: =IF('Growth (no penalty)'!I206>0,1,IF('Growth (no penalty)'!I309>0,4,0)) -> 0 | K68: =IF('Growth (no penalty)'!J206>0,1,IF('Growth (no penalty)'!J309>0,4,0)) -> 0 | ... BK68: =IF('Growth (no penalty)'!BJ206>0,1,IF('Growth (no penalty)'!BJ309>0,4,0)) -> 4
A69: ='Growth profile'!A84 -> project 126 | B69: Raw | C69: ='Raw profile'!I84 -> 2026 | D69: =IF('Raw profile'!C192>0,1,IF('Raw profile'!C295>0,2,0)) -> 1 | E69: =IF('Raw profile'!D192>0,1,IF('Raw profile'!D295>0,2,0)) -> 1 | F69: =IF('Raw profile'!E192>0,1,IF('Raw profile'!E295>0,2,0)) -> 1 | G69: =IF('Raw profile'!F192>0,1,IF('Raw profile'!F295>0,2,0)) -> 1 | H69: =IF('Raw profile'!G192>0,1,IF('Raw profile'!G295>0,2,0)) -> 2 | I69: =IF('Raw profile'!H192>0,1,IF('Raw profile'!H295>0,2,0)) -> 2 | J69: =IF('Raw profile'!I192>0,1,IF('Raw profile'!I295>0,2,0)) -> 2 | K69: =IF('Raw profile'!J192>0,1,IF('Raw profile'!J295>0,2,0)) -> 2 | ... BK69: =IF('Raw profile'!BJ192>0,1,IF('Raw profile'!BJ295>0,2,0)) -> 0
B70: Growth | C70: ='Growth profile'!I84 -> 2041 | D70: =IF('Growth profile'!C192>0,1,IF('Growth profile'!C295>0,3,0)) -> 0 | E70: =IF('Growth profile'!D192>0,1,IF('Growth profile'!D295>0,3,0)) -> 0 | F70: =IF('Growth profile'!E192>0,1,IF('Growth profile'!E295>0,3,0)) -> 0 | G70: =IF('Growth profile'!F192>0,1,IF('Growth profile'!F295>0,3,0)) -> 0 | H70: =IF('Growth profile'!G192>0,1,IF('Growth profile'!G295>0,3,0)) -> 0 | I70: =IF('Growth profile'!H192>0,1,IF('Growth profile'!H295>0,3,0)) -> 0 | J70: =IF('Growth profile'!I192>0,1,IF('Growth profile'!I295>0,3,0)) -> 0 | K70: =IF('Growth profile'!J192>0,1,IF('Growth profile'!J295>0,3,0)) -> 0 | ... BK70: =IF('Growth profile'!BJ192>0,1,IF('Growth profile'!BJ295>0,3,0)) -> 0
B71: No penalty | C71: ='Growth (no penalty)'!I84 -> 2042 | D71: =IF('Growth (no penalty)'!C192>0,1,IF('Growth (no penalty)'!C295>0,4,0)) -> 0 | E71: =IF('Growth (no penalty)'!D192>0,1,IF('Growth (no penalty)'!D295>0,4,0)) -> 0 | F71: =IF('Growth (no penalty)'!E192>0,1,IF('Growth (no penalty)'!E295>0,4,0)) -> 0 | G71: =IF('Growth (no penalty)'!F192>0,1,IF('Growth (no penalty)'!F295>0,4,0)) -> 0 | H71: =IF('Growth (no penalty)'!G192>0,1,IF('Growth (no penalty)'!G295>0,4,0)) -> 0 | I71: =IF('Growth (no penalty)'!H192>0,1,IF('Growth (no penalty)'!H295>0,4,0)) -> 0 | J71: =IF('Growth (no penalty)'!I192>0,1,IF('Growth (no penalty)'!I295>0,4,0)) -> 0 | K71: =IF('Growth (no penalty)'!J192>0,1,IF('Growth (no penalty)'!J295>0,4,0)) -> 0 | ... BK71: =IF('Growth (no penalty)'!BJ192>0,1,IF('Growth (no penalty)'!BJ295>0,4,0)) -> 4
A72: ='Growth profile'!A56 -> project 56 | B72: Raw | C72: ='Raw profile'!I56 -> 2026 | D72: =IF('Raw profile'!C164>0,1,IF('Raw profile'!C267>0,2,0)) -> 1 | E72: =IF('Raw profile'!D164>0,1,IF('Raw profile'!D267>0,2,0)) -> 2 | F72: =IF('Raw profile'!E164>0,1,IF('Raw profile'!E267>0,2,0)) -> 2 | G72: =IF('Raw profile'!F164>0,1,IF('Raw profile'!F267>0,2,0)) -> 2 | H72: =IF('Raw profile'!G164>0,1,IF('Raw profile'!G267>0,2,0)) -> 2 | I72: =IF('Raw profile'!H164>0,1,IF('Raw profile'!H267>0,2,0)) -> 2 | J72: =IF('Raw profile'!I164>0,1,IF('Raw profile'!I267>0,2,0)) -> 2 | K72: =IF('Raw profile'!J164>0,1,IF('Raw profile'!J267>0,2,0)) -> 2 | ... BK72: =IF('Raw profile'!BJ164>0,1,IF('Raw profile'!BJ267>0,2,0)) -> 0
B73: Growth | C73: ='Growth profile'!I56 -> 2042 | D73: =IF('Growth profile'!C164>0,1,IF('Growth profile'!C267>0,3,0)) -> 0 | E73: =IF('Growth profile'!D164>0,1,IF('Growth profile'!D267>0,3,0)) -> 0 | F73: =IF('Growth profile'!E164>0,1,IF('Growth profile'!E267>0,3,0)) -> 0 | G73: =IF('Growth profile'!F164>0,1,IF('Growth profile'!F267>0,3,0)) -> 0 | H73: =IF('Growth profile'!G164>0,1,IF('Growth profile'!G267>0,3,0)) -> 0 | I73: =IF('Growth profile'!H164>0,1,IF('Growth profile'!H267>0,3,0)) -> 0 | J73: =IF('Growth profile'!I164>0,1,IF('Growth profile'!I267>0,3,0)) -> 0 | K73: =IF('Growth profile'!J164>0,1,IF('Growth profile'!J267>0,3,0)) -> 0 | ... BK73: =IF('Growth profile'!BJ164>0,1,IF('Growth profile'!BJ267>0,3,0)) -> 0
B74: No penalty | C74: ='Growth (no penalty)'!I56 -> 2045 | D74: =IF('Growth (no penalty)'!C164>0,1,IF('Growth (no penalty)'!C267>0,4,0)) -> 0 | E74: =IF('Growth (no penalty)'!D164>0,1,IF('Growth (no penalty)'!D267>0,4,0)) -> 0 | F74: =IF('Growth (no penalty)'!E164>0,1,IF('Growth (no penalty)'!E267>0,4,0)) -> 0 | G74: =IF('Growth (no penalty)'!F164>0,1,IF('Growth (no penalty)'!F267>0,4,0)) -> 0 | H74: =IF('Growth (no penalty)'!G164>0,1,IF('Growth (no penalty)'!G267>0,4,0)) -> 0 | I74: =IF('Growth (no penalty)'!H164>0,1,IF('Growth (no penalty)'!H267>0,4,0)) -> 0 | J74: =IF('Growth (no penalty)'!I164>0,1,IF('Growth (no penalty)'!I267>0,4,0)) -> 0 | K74: =IF('Growth (no penalty)'!J164>0,1,IF('Growth (no penalty)'!J267>0,4,0)) -> 0 | ... BK74: =IF('Growth (no penalty)'!BJ164>0,1,IF('Growth (no penalty)'!BJ267>0,4,0)) -> 4
A75: ='Growth profile'!A64 -> project 84 | B75: Raw | C75: ='Raw profile'!I64 -> 2026 | D75: =IF('Raw profile'!C172>0,1,IF('Raw profile'!C275>0,2,0)) -> 1 | E75: =IF('Raw profile'!D172>0,1,IF('Raw profile'!D275>0,2,0)) -> 2 | F75: =IF('Raw profile'!E172>0,1,IF('Raw profile'!E275>0,2,0)) -> 2 | G75: =IF('Raw profile'!F172>0,1,IF('Raw profile'!F275>0,2,0)) -> 2 | H75: =IF('Raw profile'!G172>0,1,IF('Raw profile'!G275>0,2,0)) -> 2 | I75: =IF('Raw profile'!H172>0,1,IF('Raw profile'!H275>0,2,0)) -> 2 | J75: =IF('Raw profile'!I172>0,1,IF('Raw profile'!I275>0,2,0)) -> 2 | K75: =IF('Raw profile'!J172>0,1,IF('Raw profile'!J275>0,2,0)) -> 2 | ... BK75: =IF('Raw profile'!BJ172>0,1,IF('Raw profile'!BJ275>0,2,0)) -> 0
B76: Growth | C76: ='Growth profile'!I64 -> 2042 | D76: =IF('Growth profile'!C172>0,1,IF('Growth profile'!C275>0,3,0)) -> 0 | E76: =IF('Growth profile'!D172>0,1,IF('Growth profile'!D275>0,3,0)) -> 0 | F76: =IF('Growth profile'!E172>0,1,IF('Growth profile'!E275>0,3,0)) -> 0 | G76: =IF('Growth profile'!F172>0,1,IF('Growth profile'!F275>0,3,0)) -> 0 | H76: =IF('Growth profile'!G172>0,1,IF('Growth profile'!G275>0,3,0)) -> 0 | I76: =IF('Growth profile'!H172>0,1,IF('Growth profile'!H275>0,3,0)) -> 0 | J76: =IF('Growth profile'!I172>0,1,IF('Growth profile'!I275>0,3,0)) -> 0 | K76: =IF('Growth profile'!J172>0,1,IF('Growth profile'!J275>0,3,0)) -> 0 | ... BK76: =IF('Growth profile'!BJ172>0,1,IF('Growth profile'!BJ275>0,3,0)) -> 0
B77: No penalty | C77: ='Growth (no penalty)'!I64 -> 2045 | D77: =IF('Growth (no penalty)'!C172>0,1,IF('Growth (no penalty)'!C275>0,4,0)) -> 0 | E77: =IF('Growth (no penalty)'!D172>0,1,IF('Growth (no penalty)'!D275>0,4,0)) -> 0 | F77: =IF('Growth (no penalty)'!E172>0,1,IF('Growth (no penalty)'!E275>0,4,0)) -> 0 | G77: =IF('Growth (no penalty)'!F172>0,1,IF('Growth (no penalty)'!F275>0,4,0)) -> 0 | H77: =IF('Growth (no penalty)'!G172>0,1,IF('Growth (no penalty)'!G275>0,4,0)) -> 0 | I77: =IF('Growth (no penalty)'!H172>0,1,IF('Growth (no penalty)'!H275>0,4,0)) -> 0 | J77: =IF('Growth (no penalty)'!I172>0,1,IF('Growth (no penalty)'!I275>0,4,0)) -> 0 | K77: =IF('Growth (no penalty)'!J172>0,1,IF('Growth (no penalty)'!J275>0,4,0)) -> 0 | ... BK77: =IF('Growth (no penalty)'!BJ172>0,1,IF('Growth (no penalty)'!BJ275>0,4,0)) -> 4
A78: ='Growth profile'!A83 -> project 125 | B78: Raw | C78: ='Raw profile'!I83 -> 2026 | D78: =IF('Raw profile'!C191>0,1,IF('Raw profile'!C294>0,2,0)) -> 1 | E78: =IF('Raw profile'!D191>0,1,IF('Raw profile'!D294>0,2,0)) -> 1 | F78: =IF('Raw profile'!E191>0,1,IF('Raw profile'!E294>0,2,0)) -> 2 | G78: =IF('Raw profile'!F191>0,1,IF('Raw profile'!F294>0,2,0)) -> 2 | H78: =IF('Raw profile'!G191>0,1,IF('Raw profile'!G294>0,2,0)) -> 2 | I78: =IF('Raw profile'!H191>0,1,IF('Raw profile'!H294>0,2,0)) -> 2 | J78: =IF('Raw profile'!I191>0,1,IF('Raw profile'!I294>0,2,0)) -> 2 | K78: =IF('Raw profile'!J191>0,1,IF('Raw profile'!J294>0,2,0)) -> 2 | ... BK78: =IF('Raw profile'!BJ191>0,1,IF('Raw profile'!BJ294>0,2,0)) -> 0
B79: Growth | C79: ='Growth profile'!I83 -> 2042 | D79: =IF('Growth profile'!C191>0,1,IF('Growth profile'!C294>0,3,0)) -> 0 | E79: =IF('Growth profile'!D191>0,1,IF('Growth profile'!D294>0,3,0)) -> 0 | F79: =IF('Growth profile'!E191>0,1,IF('Growth profile'!E294>0,3,0)) -> 0 | G79: =IF('Growth profile'!F191>0,1,IF('Growth profile'!F294>0,3,0)) -> 0 | H79: =IF('Growth profile'!G191>0,1,IF('Growth profile'!G294>0,3,0)) -> 0 | I79: =IF('Growth profile'!H191>0,1,IF('Growth profile'!H294>0,3,0)) -> 0 | J79: =IF('Growth profile'!I191>0,1,IF('Growth profile'!I294>0,3,0)) -> 0 | K79: =IF('Growth profile'!J191>0,1,IF('Growth profile'!J294>0,3,0)) -> 0 | ... BK79: =IF('Growth profile'!BJ191>0,1,IF('Growth profile'!BJ294>0,3,0)) -> 0
B80: No penalty | C80: ='Growth (no penalty)'!I83 -> 2044 | D80: =IF('Growth (no penalty)'!C191>0,1,IF('Growth (no penalty)'!C294>0,4,0)) -> 0 | E80: =IF('Growth (no penalty)'!D191>0,1,IF('Growth (no penalty)'!D294>0,4,0)) -> 0 | F80: =IF('Growth (no penalty)'!E191>0,1,IF('Growth (no penalty)'!E294>0,4,0)) -> 0 | G80: =IF('Growth (no penalty)'!F191>0,1,IF('Growth (no penalty)'!F294>0,4,0)) -> 0 | H80: =IF('Growth (no penalty)'!G191>0,1,IF('Growth (no penalty)'!G294>0,4,0)) -> 0 | I80: =IF('Growth (no penalty)'!H191>0,1,IF('Growth (no penalty)'!H294>0,4,0)) -> 0 | J80: =IF('Growth (no penalty)'!I191>0,1,IF('Growth (no penalty)'!I294>0,4,0)) -> 0 | K80: =IF('Growth (no penalty)'!J191>0,1,IF('Growth (no penalty)'!J294>0,4,0)) -> 0 | ... BK80: =IF('Growth (no penalty)'!BJ191>0,1,IF('Growth (no penalty)'!BJ294>0,4,0)) -> 4
A81: ='Growth profile'!A41 -> project 33 | B81: Raw | C81: ='Raw profile'!I41 -> 2026 | D81: =IF('Raw profile'!C149>0,1,IF('Raw profile'!C252>0,2,0)) -> 1 | E81: =IF('Raw profile'!D149>0,1,IF('Raw profile'!D252>0,2,0)) -> 1 | F81: =IF('Raw profile'!E149>0,1,IF('Raw profile'!E252>0,2,0)) -> 2 | G81: =IF('Raw profile'!F149>0,1,IF('Raw profile'!F252>0,2,0)) -> 2 | H81: =IF('Raw profile'!G149>0,1,IF('Raw profile'!G252>0,2,0)) -> 2 | I81: =IF('Raw profile'!H149>0,1,IF('Raw profile'!H252>0,2,0)) -> 2 | J81: =IF('Raw profile'!I149>0,1,IF('Raw profile'!I252>0,2,0)) -> 2 | K81: =IF('Raw profile'!J149>0,1,IF('Raw profile'!J252>0,2,0)) -> 2 | ... BK81: =IF('Raw profile'!BJ149>0,1,IF('Raw profile'!BJ252>0,2,0)) -> 0
B82: Growth | C82: ='Growth profile'!I41 -> 2043 | D82: =IF('Growth profile'!C149>0,1,IF('Growth profile'!C252>0,3,0)) -> 0 | E82: =IF('Growth profile'!D149>0,1,IF('Growth profile'!D252>0,3,0)) -> 0 | F82: =IF('Growth profile'!E149>0,1,IF('Growth profile'!E252>0,3,0)) -> 0 | G82: =IF('Growth profile'!F149>0,1,IF('Growth profile'!F252>0,3,0)) -> 0 | H82: =IF('Growth profile'!G149>0,1,IF('Growth profile'!G252>0,3,0)) -> 0 | I82: =IF('Growth profile'!H149>0,1,IF('Growth profile'!H252>0,3,0)) -> 0 | J82: =IF('Growth profile'!I149>0,1,IF('Growth profile'!I252>0,3,0)) -> 0 | K82: =IF('Growth profile'!J149>0,1,IF('Growth profile'!J252>0,3,0)) -> 0 | ... BK82: =IF('Growth profile'!BJ149>0,1,IF('Growth profile'!BJ252>0,3,0)) -> 0
B83: No penalty | C83: ='Growth (no penalty)'!I41 -> 2044 | D83: =IF('Growth (no penalty)'!C149>0,1,IF('Growth (no penalty)'!C252>0,4,0)) -> 0 | E83: =IF('Growth (no penalty)'!D149>0,1,IF('Growth (no penalty)'!D252>0,4,0)) -> 0 | F83: =IF('Growth (no penalty)'!E149>0,1,IF('Growth (no penalty)'!E252>0,4,0)) -> 0 | G83: =IF('Growth (no penalty)'!F149>0,1,IF('Growth (no penalty)'!F252>0,4,0)) -> 0 | H83: =IF('Growth (no penalty)'!G149>0,1,IF('Growth (no penalty)'!G252>0,4,0)) -> 0 | I83: =IF('Growth (no penalty)'!H149>0,1,IF('Growth (no penalty)'!H252>0,4,0)) -> 0 | J83: =IF('Growth (no penalty)'!I149>0,1,IF('Growth (no penalty)'!I252>0,4,0)) -> 0 | K83: =IF('Growth (no penalty)'!J149>0,1,IF('Growth (no penalty)'!J252>0,4,0)) -> 0 | ... BK83: =IF('Growth (no penalty)'!BJ149>0,1,IF('Growth (no penalty)'!BJ252>0,4,0)) -> 4
A84: ='Growth profile'!A51 -> project 48 | B84: Raw | C84: ='Raw profile'!I51 -> 2026 | D84: =IF('Raw profile'!C159>0,1,IF('Raw profile'!C262>0,2,0)) -> 1 | E84: =IF('Raw profile'!D159>0,1,IF('Raw profile'!D262>0,2,0)) -> 1 | F84: =IF('Raw profile'!E159>0,1,IF('Raw profile'!E262>0,2,0)) -> 2 | G84: =IF('Raw profile'!F159>0,1,IF('Raw profile'!F262>0,2,0)) -> 2 | H84: =IF('Raw profile'!G159>0,1,IF('Raw profile'!G262>0,2,0)) -> 2 | I84: =IF('Raw profile'!H159>0,1,IF('Raw profile'!H262>0,2,0)) -> 2 | J84: =IF('Raw profile'!I159>0,1,IF('Raw profile'!I262>0,2,0)) -> 2 | K84: =IF('Raw profile'!J159>0,1,IF('Raw profile'!J262>0,2,0)) -> 2 | ... BK84: =IF('Raw profile'!BJ159>0,1,IF('Raw profile'!BJ262>0,2,0)) -> 0
B85: Growth | C85: ='Growth profile'!I51 -> 2043 | D85: =IF('Growth profile'!C159>0,1,IF('Growth profile'!C262>0,3,0)) -> 0 | E85: =IF('Growth profile'!D159>0,1,IF('Growth profile'!D262>0,3,0)) -> 0 | F85: =IF('Growth profile'!E159>0,1,IF('Growth profile'!E262>0,3,0)) -> 0 | G85: =IF('Growth profile'!F159>0,1,IF('Growth profile'!F262>0,3,0)) -> 0 | H85: =IF('Growth profile'!G159>0,1,IF('Growth profile'!G262>0,3,0)) -> 0 | I85: =IF('Growth profile'!H159>0,1,IF('Growth profile'!H262>0,3,0)) -> 0 | J85: =IF('Growth profile'!I159>0,1,IF('Growth profile'!I262>0,3,0)) -> 0 | K85: =IF('Growth profile'!J159>0,1,IF('Growth profile'!J262>0,3,0)) -> 0 | ... BK85: =IF('Growth profile'!BJ159>0,1,IF('Growth profile'!BJ262>0,3,0)) -> 0
B86: No penalty | C86: ='Growth (no penalty)'!I51 -> 2044 | D86: =IF('Growth (no penalty)'!C159>0,1,IF('Growth (no penalty)'!C262>0,4,0)) -> 0 | E86: =IF('Growth (no penalty)'!D159>0,1,IF('Growth (no penalty)'!D262>0,4,0)) -> 0 | F86: =IF('Growth (no penalty)'!E159>0,1,IF('Growth (no penalty)'!E262>0,4,0)) -> 0 | G86: =IF('Growth (no penalty)'!F159>0,1,IF('Growth (no penalty)'!F262>0,4,0)) -> 0 | H86: =IF('Growth (no penalty)'!G159>0,1,IF('Growth (no penalty)'!G262>0,4,0)) -> 0 | I86: =IF('Growth (no penalty)'!H159>0,1,IF('Growth (no penalty)'!H262>0,4,0)) -> 0 | J86: =IF('Growth (no penalty)'!I159>0,1,IF('Growth (no penalty)'!I262>0,4,0)) -> 0 | K86: =IF('Growth (no penalty)'!J159>0,1,IF('Growth (no penalty)'!J262>0,4,0)) -> 0 | ... BK86: =IF('Growth (no penalty)'!BJ159>0,1,IF('Growth (no penalty)'!BJ262>0,4,0)) -> 4
A87: ='Growth profile'!A91 -> project 144 | B87: Raw | C87: ='Raw profile'!I91 -> 2027 | D87: =IF('Raw profile'!C199>0,1,IF('Raw profile'!C302>0,2,0)) -> 0 | E87: =IF('Raw profile'!D199>0,1,IF('Raw profile'!D302>0,2,0)) -> 1 | F87: =IF('Raw profile'!E199>0,1,IF('Raw profile'!E302>0,2,0)) -> 0 | G87: =IF('Raw profile'!F199>0,1,IF('Raw profile'!F302>0,2,0)) -> 0 | H87: =IF('Raw profile'!G199>0,1,IF('Raw profile'!G302>0,2,0)) -> 0 | I87: =IF('Raw profile'!H199>0,1,IF('Raw profile'!H302>0,2,0)) -> 1 | J87: =IF('Raw profile'!I199>0,1,IF('Raw profile'!I302>0,2,0)) -> 2 | K87: =IF('Raw profile'!J199>0,1,IF('Raw profile'!J302>0,2,0)) -> 2 | ... BK87: =IF('Raw profile'!BJ199>0,1,IF('Raw profile'!BJ302>0,2,0)) -> 0
B88: Growth | C88: ='Growth profile'!I91 -> 2026 | D88: =IF('Growth profile'!C199>0,1,IF('Growth profile'!C302>0,3,0)) -> 1 | E88: =IF('Growth profile'!D199>0,1,IF('Growth profile'!D302>0,3,0)) -> 0 | F88: =IF('Growth profile'!E199>0,1,IF('Growth profile'!E302>0,3,0)) -> 0 | G88: =IF('Growth profile'!F199>0,1,IF('Growth profile'!F302>0,3,0)) -> 0 | H88: =IF('Growth profile'!G199>0,1,IF('Growth profile'!G302>0,3,0)) -> 1 | I88: =IF('Growth profile'!H199>0,1,IF('Growth profile'!H302>0,3,0)) -> 3 | J88: =IF('Growth profile'!I199>0,1,IF('Growth profile'!I302>0,3,0)) -> 3 | K88: =IF('Growth profile'!J199>0,1,IF('Growth profile'!J302>0,3,0)) -> 3 | ... BK88: =IF('Growth profile'!BJ199>0,1,IF('Growth profile'!BJ302>0,3,0)) -> 0
B89: No penalty | C89: ='Growth (no penalty)'!I91 -> 2026 | D89: =IF('Growth (no penalty)'!C199>0,1,IF('Growth (no penalty)'!C302>0,4,0)) -> 1 | E89: =IF('Growth (no penalty)'!D199>0,1,IF('Growth (no penalty)'!D302>0,4,0)) -> 0 | F89: =IF('Growth (no penalty)'!E199>0,1,IF('Growth (no penalty)'!E302>0,4,0)) -> 0 | G89: =IF('Growth (no penalty)'!F199>0,1,IF('Growth (no penalty)'!F302>0,4,0)) -> 0 | H89: =IF('Growth (no penalty)'!G199>0,1,IF('Growth (no penalty)'!G302>0,4,0)) -> 1 | I89: =IF('Growth (no penalty)'!H199>0,1,IF('Growth (no penalty)'!H302>0,4,0)) -> 4 | J89: =IF('Growth (no penalty)'!I199>0,1,IF('Growth (no penalty)'!I302>0,4,0)) -> 4 | K89: =IF('Growth (no penalty)'!J199>0,1,IF('Growth (no penalty)'!J302>0,4,0)) -> 4 | ... BK89: =IF('Growth (no penalty)'!BJ199>0,1,IF('Growth (no penalty)'!BJ302>0,4,0)) -> 0
A90: ='Growth profile'!A52 -> project 50 | B90: Raw | C90: ='Raw profile'!I52 -> 2027 | D90: =IF('Raw profile'!C160>0,1,IF('Raw profile'!C263>0,2,0)) -> 0 | E90: =IF('Raw profile'!D160>0,1,IF('Raw profile'!D263>0,2,0)) -> 1 | F90: =IF('Raw profile'!E160>0,1,IF('Raw profile'!E263>0,2,0)) -> 1 | G90: =IF('Raw profile'!F160>0,1,IF('Raw profile'!F263>0,2,0)) -> 1 | H90: =IF('Raw profile'!G160>0,1,IF('Raw profile'!G263>0,2,0)) -> 1 | I90: =IF('Raw profile'!H160>0,1,IF('Raw profile'!H263>0,2,0)) -> 1 | J90: =IF('Raw profile'!I160>0,1,IF('Raw profile'!I263>0,2,0)) -> 1 | K90: =IF('Raw profile'!J160>0,1,IF('Raw profile'!J263>0,2,0)) -> 1 | ... BK90: =IF('Raw profile'!BJ160>0,1,IF('Raw profile'!BJ263>0,2,0)) -> 0
B91: Growth | C91: ='Growth profile'!I52 -> 2032 | D91: =IF('Growth profile'!C160>0,1,IF('Growth profile'!C263>0,3,0)) -> 0 | E91: =IF('Growth profile'!D160>0,1,IF('Growth profile'!D263>0,3,0)) -> 0 | F91: =IF('Growth profile'!E160>0,1,IF('Growth profile'!E263>0,3,0)) -> 0 | G91: =IF('Growth profile'!F160>0,1,IF('Growth profile'!F263>0,3,0)) -> 0 | H91: =IF('Growth profile'!G160>0,1,IF('Growth profile'!G263>0,3,0)) -> 0 | I91: =IF('Growth profile'!H160>0,1,IF('Growth profile'!H263>0,3,0)) -> 0 | J91: =IF('Growth profile'!I160>0,1,IF('Growth profile'!I263>0,3,0)) -> 1 | K91: =IF('Growth profile'!J160>0,1,IF('Growth profile'!J263>0,3,0)) -> 1 | ... BK91: =IF('Growth profile'!BJ160>0,1,IF('Growth profile'!BJ263>0,3,0)) -> 0
B92: No penalty | C92: ='Growth (no penalty)'!I52 -> 2038 | D92: =IF('Growth (no penalty)'!C160>0,1,IF('Growth (no penalty)'!C263>0,4,0)) -> 0 | E92: =IF('Growth (no penalty)'!D160>0,1,IF('Growth (no penalty)'!D263>0,4,0)) -> 0 | F92: =IF('Growth (no penalty)'!E160>0,1,IF('Growth (no penalty)'!E263>0,4,0)) -> 0 | G92: =IF('Growth (no penalty)'!F160>0,1,IF('Growth (no penalty)'!F263>0,4,0)) -> 0 | H92: =IF('Growth (no penalty)'!G160>0,1,IF('Growth (no penalty)'!G263>0,4,0)) -> 0 | I92: =IF('Growth (no penalty)'!H160>0,1,IF('Growth (no penalty)'!H263>0,4,0)) -> 0 | J92: =IF('Growth (no penalty)'!I160>0,1,IF('Growth (no penalty)'!I263>0,4,0)) -> 0 | K92: =IF('Growth (no penalty)'!J160>0,1,IF('Growth (no penalty)'!J263>0,4,0)) -> 0 | ... BK92: =IF('Growth (no penalty)'!BJ160>0,1,IF('Growth (no penalty)'!BJ263>0,4,0)) -> 4
A93: ='Growth profile'!A102 -> project 162 | B93: Raw | C93: ='Raw profile'!I102 -> 2027 | D93: =IF('Raw profile'!C210>0,1,IF('Raw profile'!C313>0,2,0)) -> 0 | E93: =IF('Raw profile'!D210>0,1,IF('Raw profile'!D313>0,2,0)) -> 1 | F93: =IF('Raw profile'!E210>0,1,IF('Raw profile'!E313>0,2,0)) -> 1 | G93: =IF('Raw profile'!F210>0,1,IF('Raw profile'!F313>0,2,0)) -> 1 | H93: =IF('Raw profile'!G210>0,1,IF('Raw profile'!G313>0,2,0)) -> 2 | I93: =IF('Raw profile'!H210>0,1,IF('Raw profile'!H313>0,2,0)) -> 2 | J93: =IF('Raw profile'!I210>0,1,IF('Raw profile'!I313>0,2,0)) -> 2 | K93: =IF('Raw profile'!J210>0,1,IF('Raw profile'!J313>0,2,0)) -> 2 | ... BK93: =IF('Raw profile'!BJ210>0,1,IF('Raw profile'!BJ313>0,2,0)) -> 0
B94: Growth | C94: ='Growth profile'!I102 -> 2041 | D94: =IF('Growth profile'!C210>0,1,IF('Growth profile'!C313>0,3,0)) -> 0 | E94: =IF('Growth profile'!D210>0,1,IF('Growth profile'!D313>0,3,0)) -> 0 | F94: =IF('Growth profile'!E210>0,1,IF('Growth profile'!E313>0,3,0)) -> 0 | G94: =IF('Growth profile'!F210>0,1,IF('Growth profile'!F313>0,3,0)) -> 0 | H94: =IF('Growth profile'!G210>0,1,IF('Growth profile'!G313>0,3,0)) -> 0 | I94: =IF('Growth profile'!H210>0,1,IF('Growth profile'!H313>0,3,0)) -> 0 | J94: =IF('Growth profile'!I210>0,1,IF('Growth profile'!I313>0,3,0)) -> 0 | K94: =IF('Growth profile'!J210>0,1,IF('Growth profile'!J313>0,3,0)) -> 0 | ... BK94: =IF('Growth profile'!BJ210>0,1,IF('Growth profile'!BJ313>0,3,0)) -> 0
B95: No penalty | C95: ='Growth (no penalty)'!I102 -> 2043 | D95: =IF('Growth (no penalty)'!C210>0,1,IF('Growth (no penalty)'!C313>0,4,0)) -> 0 | E95: =IF('Growth (no penalty)'!D210>0,1,IF('Growth (no penalty)'!D313>0,4,0)) -> 0 | F95: =IF('Growth (no penalty)'!E210>0,1,IF('Growth (no penalty)'!E313>0,4,0)) -> 0 | G95: =IF('Growth (no penalty)'!F210>0,1,IF('Growth (no penalty)'!F313>0,4,0)) -> 0 | H95: =IF('Growth (no penalty)'!G210>0,1,IF('Growth (no penalty)'!G313>0,4,0)) -> 0 | I95: =IF('Growth (no penalty)'!H210>0,1,IF('Growth (no penalty)'!H313>0,4,0)) -> 0 | J95: =IF('Growth (no penalty)'!I210>0,1,IF('Growth (no penalty)'!I313>0,4,0)) -> 0 | K95: =IF('Growth (no penalty)'!J210>0,1,IF('Growth (no penalty)'!J313>0,4,0)) -> 0 | ... BK95: =IF('Growth (no penalty)'!BJ210>0,1,IF('Growth (no penalty)'!BJ313>0,4,0)) -> 4
A96: ='Growth profile'!A75 -> project 107 | B96: Raw | C96: ='Raw profile'!I75 -> 2028 | D96: =IF('Raw profile'!C183>0,1,IF('Raw profile'!C286>0,2,0)) -> 0 | E96: =IF('Raw profile'!D183>0,1,IF('Raw profile'!D286>0,2,0)) -> 0 | F96: =IF('Raw profile'!E183>0,1,IF('Raw profile'!E286>0,2,0)) -> 1 | G96: =IF('Raw profile'!F183>0,1,IF('Raw profile'!F286>0,2,0)) -> 0 | H96: =IF('Raw profile'!G183>0,1,IF('Raw profile'!G286>0,2,0)) -> 1 | I96: =IF('Raw profile'!H183>0,1,IF('Raw profile'!H286>0,2,0)) -> 1 | J96: =IF('Raw profile'!I183>0,1,IF('Raw profile'!I286>0,2,0)) -> 1 | K96: =IF('Raw profile'!J183>0,1,IF('Raw profile'!J286>0,2,0)) -> 1 | ... BK96: =IF('Raw profile'!BJ183>0,1,IF('Raw profile'!BJ286>0,2,0)) -> 0
B97: Growth | C97: ='Growth profile'!I75 -> 2033 | D97: =IF('Growth profile'!C183>0,1,IF('Growth profile'!C286>0,3,0)) -> 0 | E97: =IF('Growth profile'!D183>0,1,IF('Growth profile'!D286>0,3,0)) -> 0 | F97: =IF('Growth profile'!E183>0,1,IF('Growth profile'!E286>0,3,0)) -> 0 | G97: =IF('Growth profile'!F183>0,1,IF('Growth profile'!F286>0,3,0)) -> 0 | H97: =IF('Growth profile'!G183>0,1,IF('Growth profile'!G286>0,3,0)) -> 0 | I97: =IF('Growth profile'!H183>0,1,IF('Growth profile'!H286>0,3,0)) -> 0 | J97: =IF('Growth profile'!I183>0,1,IF('Growth profile'!I286>0,3,0)) -> 0 | K97: =IF('Growth profile'!J183>0,1,IF('Growth profile'!J286>0,3,0)) -> 1 | ... BK97: =IF('Growth profile'!BJ183>0,1,IF('Growth profile'!BJ286>0,3,0)) -> 0
B98: No penalty | C98: ='Growth (no penalty)'!I75 -> 2037 | D98: =IF('Growth (no penalty)'!C183>0,1,IF('Growth (no penalty)'!C286>0,4,0)) -> 0 | E98: =IF('Growth (no penalty)'!D183>0,1,IF('Growth (no penalty)'!D286>0,4,0)) -> 0 | F98: =IF('Growth (no penalty)'!E183>0,1,IF('Growth (no penalty)'!E286>0,4,0)) -> 0 | G98: =IF('Growth (no penalty)'!F183>0,1,IF('Growth (no penalty)'!F286>0,4,0)) -> 0 | H98: =IF('Growth (no penalty)'!G183>0,1,IF('Growth (no penalty)'!G286>0,4,0)) -> 0 | I98: =IF('Growth (no penalty)'!H183>0,1,IF('Growth (no penalty)'!H286>0,4,0)) -> 0 | J98: =IF('Growth (no penalty)'!I183>0,1,IF('Growth (no penalty)'!I286>0,4,0)) -> 0 | K98: =IF('Growth (no penalty)'!J183>0,1,IF('Growth (no penalty)'!J286>0,4,0)) -> 0 | ... BK98: =IF('Growth (no penalty)'!BJ183>0,1,IF('Growth (no penalty)'!BJ286>0,4,0)) -> 4
A99: ='Growth profile'!A61 -> project 75 | B99: Raw | C99: ='Raw profile'!I61 -> 2029 | D99: =IF('Raw profile'!C169>0,1,IF('Raw profile'!C272>0,2,0)) -> 0 | E99: =IF('Raw profile'!D169>0,1,IF('Raw profile'!D272>0,2,0)) -> 0 | F99: =IF('Raw profile'!E169>0,1,IF('Raw profile'!E272>0,2,0)) -> 0 | G99: =IF('Raw profile'!F169>0,1,IF('Raw profile'!F272>0,2,0)) -> 1 | H99: =IF('Raw profile'!G169>0,1,IF('Raw profile'!G272>0,2,0)) -> 1 | I99: =IF('Raw profile'!H169>0,1,IF('Raw profile'!H272>0,2,0)) -> 1 | J99: =IF('Raw profile'!I169>0,1,IF('Raw profile'!I272>0,2,0)) -> 1 | K99: =IF('Raw profile'!J169>0,1,IF('Raw profile'!J272>0,2,0)) -> 1 | ... BK99: =IF('Raw profile'!BJ169>0,1,IF('Raw profile'!BJ272>0,2,0)) -> 0
B100: Growth | C100: ='Growth profile'!I61 -> 2026 | D100: =IF('Growth profile'!C169>0,1,IF('Growth profile'!C272>0,3,0)) -> 1 | E100: =IF('Growth profile'!D169>0,1,IF('Growth profile'!D272>0,3,0)) -> 1 | F100: =IF('Growth profile'!E169>0,1,IF('Growth profile'!E272>0,3,0)) -> 1 | G100: =IF('Growth profile'!F169>0,1,IF('Growth profile'!F272>0,3,0)) -> 1 | H100: =IF('Growth profile'!G169>0,1,IF('Growth profile'!G272>0,3,0)) -> 1 | I100: =IF('Growth profile'!H169>0,1,IF('Growth profile'!H272>0,3,0)) -> 1 | J100: =IF('Growth profile'!I169>0,1,IF('Growth profile'!I272>0,3,0)) -> 1 | K100: =IF('Growth profile'!J169>0,1,IF('Growth profile'!J272>0,3,0)) -> 1 | ... BK100: =IF('Growth profile'!BJ169>0,1,IF('Growth profile'!BJ272>0,3,0)) -> 0
B101: No penalty | C101: ='Growth (no penalty)'!I61 -> 2026 | D101: =IF('Growth (no penalty)'!C169>0,1,IF('Growth (no penalty)'!C272>0,4,0)) -> 1 | E101: =IF('Growth (no penalty)'!D169>0,1,IF('Growth (no penalty)'!D272>0,4,0)) -> 1 | F101: =IF('Growth (no penalty)'!E169>0,1,IF('Growth (no penalty)'!E272>0,4,0)) -> 1 | G101: =IF('Growth (no penalty)'!F169>0,1,IF('Growth (no penalty)'!F272>0,4,0)) -> 1 | H101: =IF('Growth (no penalty)'!G169>0,1,IF('Growth (no penalty)'!G272>0,4,0)) -> 1 | I101: =IF('Growth (no penalty)'!H169>0,1,IF('Growth (no penalty)'!H272>0,4,0)) -> 1 | J101: =IF('Growth (no penalty)'!I169>0,1,IF('Growth (no penalty)'!I272>0,4,0)) -> 1 | K101: =IF('Growth (no penalty)'!J169>0,1,IF('Growth (no penalty)'!J272>0,4,0)) -> 1 | ... BK101: =IF('Growth (no penalty)'!BJ169>0,1,IF('Growth (no penalty)'!BJ272>0,4,0)) -> 0
...

Sheet Comparison
A1: Project schedule comparison - raw vs growth (production objective), plus growth with no cash penalty
A2: Sorted by shift (largest deferral first). All values link to the profile sheets.
A4: Project | B4: Role | C4: Cost band | D4: Base BCR | E4: Cost ($M) | F4: Growth p.a. | G4: Start (raw) | H4: Start (growth) | I4: Shift (yrs) | J4: PV raw ($M) | K4: PV growth ($M) | L4: Benefits end (growth) | M4: Benefit yrs truncated (growth) | N4: Growth band | O4: Read-out | P4: Start (growth, no cash penalty) | Q4: Shift vs raw (no cash penalty)
A5: ='Growth profile'!A41 -> project 33 | B5: ='Growth profile'!B41 -> random growth | C5: ='Growth profile'!C41 -> 3 | D5: ='Growth profile'!D41 -> 3.38 | E5: ='Growth profile'!E41 -> 8.973675 | F5: ='Growth profile'!H41 -> 0.03 | G5: ='Raw profile'!I41 -> 2026 | H5: ='Growth profile'!I41 -> 2043 | I5: =H5-G5 -> 17 | J5: ='Raw profile'!O41 -> 30.236451 | K5: ='Growth profile'!O41 -> 69.481946 | L5: =MIN('Growth profile'!L41,2085) -> 2084 | M5: ='Growth profile'!N41 -> 0 | N5: =IF(F5<0,"shrinking",IF(F5<0.015,"under 1.5%",IF(F5<0.018,"1.5% to 1.8%","1.8% and over"))) -> 1.8% and over | O5: =IF(I5>0,IF(L5=2085,"Deferred - pinned to horizon end","Deferred"),IF(I5<0,"Accelerated","Unchanged")) -> Deferred | P5: ='Growth (no penalty)'!I41 -> 2044 | Q5: =P5-G5 -> 18
A6: ='Growth profile'!A51 -> project 48 | B6: ='Growth profile'!B51 -> random growth | C6: ='Growth profile'!C51 -> 1 | D6: ='Growth profile'!D51 -> 7 | E6: ='Growth profile'!E51 -> 1.006 | F6: ='Growth profile'!H51 -> 0.0299 | G6: ='Raw profile'!I51 -> 2026 | H6: ='Growth profile'!I51 -> 2043 | I6: =H6-G6 -> 17 | J6: ='Raw profile'!O51 -> 6.9459216 | K6: ='Growth profile'!O51 -> 15.899036 | L6: =MIN('Growth profile'!L51,2085) -> 2084 | M6: ='Growth profile'!N51 -> 0 | N6: =IF(F6<0,"shrinking",IF(F6<0.015,"under 1.5%",IF(F6<0.018,"1.5% to 1.8%","1.8% and over"))) -> 1.8% and over | O6: =IF(I6>0,IF(L6=2085,"Deferred - pinned to horizon end","Deferred"),IF(I6<0,"Accelerated","Unchanged")) -> Deferred | P6: ='Growth (no penalty)'!I51 -> 2044 | Q6: =P6-G6 -> 18
A7: ='Growth profile'!A83 -> project 125 | B7: ='Growth profile'!B83 -> random growth | C7: ='Growth profile'!C83 -> 5 | D7: ='Growth profile'!D83 -> 3.05 | E7: ='Growth profile'!E83 -> 94.762111 | F7: ='Growth profile'!H83 -> 0.0276 | G7: ='Raw profile'!I83 -> 2026 | H7: ='Growth profile'!I83 -> 2042 | I7: =H7-G7 -> 16 | J7: ='Raw profile'!O83 -> 284.79522 | K7: ='Growth profile'!O83 -> 589.3316 | L7: =MIN('Growth profile'!L83,2085) -> 2083 | M7: ='Growth profile'!N83 -> 0 | N7: =IF(F7<0,"shrinking",IF(F7<0.015,"under 1.5%",IF(F7<0.018,"1.5% to 1.8%","1.8% and over"))) -> 1.8% and over | O7: =IF(I7>0,IF(L7=2085,"Deferred - pinned to horizon end","Deferred"),IF(I7<0,"Accelerated","Unchanged")) -> Deferred | P7: ='Growth (no penalty)'!I83 -> 2044 | Q7: =P7-G7 -> 18
A8: ='Growth profile'!A56 -> project 56 | B8: ='Growth profile'!B56 -> random growth | C8: ='Growth profile'!C56 -> 1 | D8: ='Growth profile'!D56 -> 5.43 | E8: ='Growth profile'!E56 -> 0.05325 | F8: ='Growth profile'!H56 -> 0.0244 | G8: ='Raw profile'!I56 -> 2026 | H8: ='Growth profile'!I56 -> 2042 | I8: =H8-G8 -> 16 | J8: ='Raw profile'!O56 -> 0.2891475 | K8: ='Growth profile'!O56 -> 0.51625003 | L8: =MIN('Growth profile'!L56,2085) -> 2082 | M8: ='Growth profile'!N56 -> 0 | N8: =IF(F8<0,"shrinking",IF(F8<0.015,"under 1.5%",IF(F8<0.018,"1.5% to 1.8%","1.8% and over"))) -> 1.8% and over | O8: =IF(I8>0,IF(L8=2085,"Deferred - pinned to horizon end","Deferred"),IF(I8<0,"Accelerated","Unchanged")) -> Deferred | P8: ='Growth (no penalty)'!I56 -> 2045 | Q8: =P8-G8 -> 19
A9: ='Growth profile'!A64 -> project 84 | B9: ='Growth profile'!B64 -> random growth | C9: ='Growth profile'!C64 -> 1 | D9: ='Growth profile'!D64 -> 1.87 | E9: ='Growth profile'!E64 -> 1.1495637 | F9: ='Growth profile'!H64 -> 0.0291 | G9: ='Raw profile'!I64 -> 2026 | H9: ='Growth profile'!I64 -> 2042 | I9: =H9-G9 -> 16 | J9: ='Raw profile'!O64 -> 2.1496842 | K9: ='Growth profile'!O64 -> 4.5645555 | L9: =MIN('Growth profile'!L64,2085) -> 2082 | M9: ='Growth profile'!N64 -> 0 | N9: =IF(F9<0,"shrinking",IF(F9<0.015,"under 1.5%",IF(F9<0.018,"1.5% to 1.8%","1.8% and over"))) -> 1.8% and over | O9: =IF(I9>0,IF(L9=2085,"Deferred - pinned to horizon end","Deferred"),IF(I9<0,"Accelerated","Unchanged")) -> Deferred | P9: ='Growth (no penalty)'!I64 -> 2045 | Q9: =P9-G9 -> 19
A10: ='Growth profile'!A84 -> project 126 | B10: ='Growth profile'!B84 -> random growth | C10: ='Growth profile'!C84 -> 5 | D10: ='Growth profile'!D84 -> 2.92 | E10: ='Growth profile'!E84 -> 104.79906 | F10: ='Growth profile'!H84 -> 0.0266 | G10: ='Raw profile'!I84 -> 2026 | H10: ='Growth profile'!I84 -> 2041 | I10: =H10-G10 -> 15 | J10: ='Raw profile'!O84 -> 295.1268 | K10: ='Growth profile'!O84 -> 616.50866 | L10: =MIN('Growth profile'!L84,2085) -> 2084 | M10: ='Growth profile'!N84 -> 0 | N10: =IF(F10<0,"shrinking",IF(F10<0.015,"under 1.5%",IF(F10<0.018,"1.5% to 1.8%","1.8% and over"))) -> 1.8% and over | O10: =IF(I10>0,IF(L10=2085,"Deferred - pinned to horizon end","Deferred"),IF(I10<0,"Accelerated","Unchanged")) -> Deferred | P10: ='Growth (no penalty)'!I84 -> 2042 | Q10: =P10-G10 -> 16
A11: ='Growth profile'!A98 -> project 156 | B11: ='Growth profile'!B98 -> random growth | C11: ='Growth profile'!C98 -> 4 | D11: ='Growth profile'!D98 -> 3.2 | E11: ='Growth profile'!E98 -> 16.213995 | F11: ='Growth profile'!H98 -> 0.0274 | G11: ='Raw profile'!I98 -> 2026 | H11: ='Growth profile'!I98 -> 2040 | I11: =H11-G11 -> 14 | J11: ='Raw profile'!O98 -> 49.696442 | K11: ='Growth profile'!O98 -> 105.93552 | L11: =MIN('Growth profile'!L98,2085) -> 2083 | M11: ='Growth profile'!N98 -> 0 | N11: =IF(F11<0,"shrinking",IF(F11<0.015,"under 1.5%",IF(F11<0.018,"1.5% to 1.8%","1.8% and over"))) -> 1.8% and over | O11: =IF(I11>0,IF(L11=2085,"Deferred - pinned to horizon end","Deferred"),IF(I11<0,"Accelerated","Unchanged")) -> Deferred | P11: ='Growth (no penalty)'!I98 -> 2042 | Q11: =P11-G11 -> 16
A12: ='Growth profile'!A102 -> project 162 | B12: ='Growth profile'!B102 -> random growth | C12: ='Growth profile'!C102 -> 3 | D12: ='Growth profile'!D102 -> 2.94 | E12: ='Growth profile'!E102 -> 11.061426 | F12: ='Growth profile'!H102 -> 0.0246 | G12: ='Raw profile'!I102 -> 2027 | H12: ='Growth profile'!I102 -> 2041 | I12: =H12-G12 -> 14 | J12: ='Raw profile'!O102 -> 31.299626 | K12: ='Growth profile'!O102 -> 60.017609 | L12: =MIN('Growth profile'!L102,2085) -> 2083 | M12: ='Growth profile'!N102 -> 0 | N12: =IF(F12<0,"shrinking",IF(F12<0.015,"under 1.5%",IF(F12<0.018,"1.5% to 1.8%","1.8% and over"))) -> 1.8% and over | O12: =IF(I12>0,IF(L12=2085,"Deferred - pinned to horizon end","Deferred"),IF(I12<0,"Accelerated","Unchanged")) -> Deferred | P12: ='Growth (no penalty)'!I102 -> 2043 | Q12: =P12-G12 -> 16
A13: ='Growth profile'!A24 -> project 1 | B13: ='Growth profile'!B24 -> anchor: top BCR 7, +3% | C13: ='Growth profile'!C24 -> 4 | D13: ='Growth profile'!D24 -> 7 | E13: ='Growth profile'!E24 -> 36.329552 | F13: ='Growth profile'!H24 -> 0.03 | G13: ='Raw profile'!I24 -> 2026 | H13: ='Growth profile'!I24 -> 2039 | I13: =H13-G13 -> 13 | J13: ='Raw profile'!O24 -> 240.28604 | K13: ='Growth profile'!O24 -> 594.63487 | L13: =MIN('Growth profile'!L24,2085) -> 2084 | M13: ='Growth profile'!N24 -> 0 | N13: =IF(F13<0,"shrinking",IF(F13<0.015,"under 1.5%",IF(F13<0.018,"1.5% to 1.8%","1.8% and over"))) -> 1.8% and over | O13: =IF(I13>0,IF(L13=2085,"Deferred - pinned to horizon end","Deferred"),IF(I13<0,"Accelerated","Unchanged")) -> Deferred | P13: ='Growth (no penalty)'!I24 -> 2040 | Q13: =P13-G13 -> 14
A14: ='Growth profile'!A119 -> project 200 | B14: ='Growth profile'!B119 -> random growth | C14: ='Growth profile'!C119 -> 1 | D14: ='Growth profile'!D119 -> 1.97 | E14: ='Growth profile'!E119 -> 0.79345245 | F14: ='Growth profile'!H119 -> 0.0272 | G14: ='Raw profile'!I119 -> 2026 | H14: ='Growth profile'!I119 -> 2039 | I14: =H14-G14 -> 13 | J14: ='Raw profile'!O119 -> 1.5612809 | K14: ='Growth profile'!O119 -> 3.0838958 | L14: =MIN('Growth profile'!L119,2085) -> 2080 | M14: ='Growth profile'!N119 -> 0 | N14: =IF(F14<0,"shrinking",IF(F14<0.015,"under 1.5%",IF(F14<0.018,"1.5% to 1.8%","1.8% and over"))) -> 1.8% and over | O14: =IF(I14>0,IF(L14=2085,"Deferred - pinned to horizon end","Deferred"),IF(I14<0,"Accelerated","Unchanged")) -> Deferred | P14: ='Growth (no penalty)'!I119 -> 2044 | Q14: =P14-G14 -> 18
A15: ='Growth profile'!A70 -> project 100 | B15: ='Growth profile'!B70 -> random growth | C15: ='Growth profile'!C70 -> 4 | D15: ='Growth profile'!D70 -> 2.21 | E15: ='Growth profile'!E70 -> 17.984314 | F15: ='Growth profile'!H70 -> 0.0274 | G15: ='Raw profile'!I70 -> 2026 | H15: ='Growth profile'!I70 -> 2038 | I15: =H15-G15 -> 12 | J15: ='Raw profile'!O70 -> 39.386346 | K15: ='Growth profile'!O70 -> 77.531166 | L15: =MIN('Growth profile'!L70,2085) -> 2079 | M15: ='Growth profile'!N70 -> 0 | N15: =IF(F15<0,"shrinking",IF(F15<0.015,"under 1.5%",IF(F15<0.018,"1.5% to 1.8%","1.8% and over"))) -> 1.8% and over | O15: =IF(I15>0,IF(L15=2085,"Deferred - pinned to horizon end","Deferred"),IF(I15<0,"Accelerated","Unchanged")) -> Deferred | P15: ='Growth (no penalty)'!I70 -> 2044 | Q15: =P15-G15 -> 18
A16: ='Growth profile'!A29 -> project 12 | B16: ='Growth profile'!B29 -> random growth | C16: ='Growth profile'!C29 -> 2 | D16: ='Growth profile'!D29 -> 2.07 | E16: ='Growth profile'!E29 -> 2.9836078 | F16: ='Growth profile'!H29 -> 0.0231 | G16: ='Raw profile'!I29 -> 2026 | H16: ='Growth profile'!I29 -> 2037 | I16: =H16-G16 -> 11 | J16: ='Raw profile'!O29 -> 6.1478753 | K16: ='Growth profile'!O29 -> 10.404345 | L16: =MIN('Growth profile'!L29,2085) -> 2078 | M16: ='Growth profile'!N29 -> 0 | N16: =IF(F16<0,"shrinking",IF(F16<0.015,"under 1.5%",IF(F16<0.018,"1.5% to 1.8%","1.8% and over"))) -> 1.8% and over | O16: =IF(I16>0,IF(L16=2085,"Deferred - pinned to horizon end","Deferred"),IF(I16<0,"Accelerated","Unchanged")) -> Deferred | P16: ='Growth (no penalty)'!I29 -> 2044 | Q16: =P16-G16 -> 18
A17: ='Growth profile'!A112 -> project 184 | B17: ='Growth profile'!B112 -> random growth | C17: ='Growth profile'!C112 -> 2 | D17: ='Growth profile'!D112 -> 2.65 | E17: ='Growth profile'!E112 -> 2.823373 | F17: ='Growth profile'!H112 -> 0.0218 | G17: ='Raw profile'!I112 -> 2026 | H17: ='Growth profile'!I112 -> 2037 | I17: =H17-G17 -> 11 | J17: ='Raw profile'!O112 -> 7.4819384 | K17: ='Growth profile'!O112 -> 11.858082 | L17: =MIN('Growth profile'!L112,2085) -> 2077 | M17: ='Growth profile'!N112 -> 0 | N17: =IF(F17<0,"shrinking",IF(F17<0.015,"under 1.5%",IF(F17<0.018,"1.5% to 1.8%","1.8% and over"))) -> 1.8% and over | O17: =IF(I17>0,IF(L17=2085,"Deferred - pinned to horizon end","Deferred"),IF(I17<0,"Accelerated","Unchanged")) -> Deferred | P17: ='Growth (no penalty)'!I112 -> 2045 | Q17: =P17-G17 -> 19
A18: ='Growth profile'!A118 -> project 195 | B18: ='Growth profile'!B118 -> random growth | C18: ='Growth profile'!C118 -> 1 | D18: ='Growth profile'!D118 -> 1.96 | E18: ='Growth profile'!E118 -> 0.84528292 | F18: ='Growth profile'!H118 -> 0.0281 | G18: ='Raw profile'!I118 -> 2032 | H18: ='Growth profile'!I118 -> 2042 | I18: =H18-G18 -> 10 | J18: ='Raw profile'!O118 -> 1.4739021 | K18: ='Growth profile'!O118 -> 3.4715308 | L18: =MIN('Growth profile'!L118,2085) -> 2083 | M18: ='Growth profile'!N118 -> 0 | N18: =IF(F18<0,"shrinking",IF(F18<0.015,"under 1.5%",IF(F18<0.018,"1.5% to 1.8%","1.8% and over"))) -> 1.8% and over | O18: =IF(I18>0,IF(L18=2085,"Deferred - pinned to horizon end","Deferred"),IF(I18<0,"Accelerated","Unchanged")) -> Deferred | P18: ='Growth (no penalty)'!I118 -> 2044 | Q18: =P18-G18 -> 12
A19: ='Growth profile'!A32 -> project 20 | B19: ='Growth profile'!B32 -> random growth | C19: ='Growth profile'!C32 -> 2 | D19: ='Growth profile'!D32 -> 1.69 | E19: ='Growth profile'!E32 -> 1.8170941 | F19: ='Growth profile'!H32 -> 0.0192 | G19: ='Raw profile'!I32 -> 2026 | H19: ='Growth profile'!I32 -> 2035 | I19: =H19-G19 -> 9 | J19: ='Raw profile'!O32 -> 3.0655774 | K19: ='Growth profile'!O32 -> 4.5555424 | L19: =MIN('Growth profile'!L32,2085) -> 2076 | M19: ='Growth profile'!N32 -> 0 | N19: =IF(F19<0,"shrinking",IF(F19<0.015,"under 1.5%",IF(F19<0.018,"1.5% to 1.8%","1.8% and over"))) -> 1.8% and over | O19: =IF(I19>0,IF(L19=2085,"Deferred - pinned to horizon end","Deferred"),IF(I19<0,"Accelerated","Unchanged")) -> Deferred | P19: ='Growth (no penalty)'!I32 -> 2044 | Q19: =P19-G19 -> 18
A20: ='Growth profile'!A48 -> project 43 | B20: ='Growth profile'!B48 -> random growth | C20: ='Growth profile'!C48 -> 1 | D20: ='Growth profile'!D48 -> 1.52 | E20: ='Growth profile'!E48 -> 0.03815 | F20: ='Growth profile'!H48 -> 0.0184 | G20: ='Raw profile'!I48 -> 2026 | H20: ='Growth profile'!I48 -> 2035 | I20: =H20-G20 -> 9 | J20: ='Raw profile'!O48 -> 0.057988 | K20: ='Growth profile'!O48 -> 0.082479423 | L20: =MIN('Growth profile'!L48,2085) -> 2075 | M20: ='Growth profile'!N48 -> 0 | N20: =IF(F20<0,"shrinking",IF(F20<0.015,"under 1.5%",IF(F20<0.018,"1.5% to 1.8%","1.8% and over"))) -> 1.8% and over | O20: =IF(I20>0,IF(L20=2085,"Deferred - pinned to horizon end","Deferred"),IF(I20<0,"Accelerated","Unchanged")) -> Deferred | P20: ='Growth (no penalty)'!I48 -> 2045 | Q20: =P20-G20 -> 19
A21: ='Growth profile'!A96 -> project 150 | B21: ='Growth profile'!B96 -> random growth | C21: ='Growth profile'!C96 -> 4 | D21: ='Growth profile'!D96 -> 2.56 | E21: ='Growth profile'!E96 -> 18.792151 | F21: ='Growth profile'!H96 -> 0.021 | G21: ='Raw profile'!I96 -> 2026 | H21: ='Growth profile'!I96 -> 2034 | I21: =H21-G21 -> 8 | J21: ='Raw profile'!O96 -> 47.64093 | K21: ='Growth profile'!O96 -> 74.494623 | L21: =MIN('Growth profile'!L96,2085) -> 2075 | M21: ='Growth profile'!N96 -> 0 | N21: =IF(F21<0,"shrinking",IF(F21<0.015,"under 1.5%",IF(F21<0.018,"1.5% to 1.8%","1.8% and over"))) -> 1.8% and over | O21: =IF(I21>0,IF(L21=2085,"Deferred - pinned to horizon end","Deferred"),IF(I21<0,"Accelerated","Unchanged")) -> Deferred | P21: ='Growth (no penalty)'!I96 -> 2044 | Q21: =P21-G21 -> 18
A22: ='Growth profile'!A53 -> project 51 | B22: ='Growth profile'!B53 -> random growth | C22: ='Growth profile'!C53 -> 5 | D22: ='Growth profile'!D53 -> 2.18 | E22: ='Growth profile'!E53 -> 52.075215 | F22: ='Growth profile'!H53 -> 0.0294 | G22: ='Raw profile'!I53 -> 2032 | H22: ='Growth profile'!I53 -> 2040 | I22: =H22-G22 -> 8 | J22: ='Raw profile'!O53 -> 98.414598 | K22: ='Growth profile'!O53 -> 260.31302 | L22: =MIN('Growth profile'!L53,2085) -> 2084 | M22: ='Growth profile'!N53 -> 0 | N22: =IF(F22<0,"shrinking",IF(F22<0.015,"under 1.5%",IF(F22<0.018,"1.5% to 1.8%","1.8% and over"))) -> 1.8% and over | O22: =IF(I22>0,IF(L22=2085,"Deferred - pinned to horizon end","Deferred"),IF(I22<0,"Accelerated","Unchanged")) -> Deferred | P22: ='Growth (no penalty)'!I53 -> 2041 | Q22: =P22-G22 -> 9
A23: ='Growth profile'!A37 -> project 27 | B23: ='Growth profile'!B37 -> random growth | C23: ='Growth profile'!C37 -> 1 | D23: ='Growth profile'!D37 -> 4.41 | E23: ='Growth profile'!E37 -> 0.32379412 | F23: ='Growth profile'!H37 -> 0.0217 | G23: ='Raw profile'!I37 -> 2031 | H23: ='Growth profile'!I37 -> 2038 | I23: =H23-G23 -> 7 | J23: ='Raw profile'!O37 -> 1.2893364 | K23: ='Growth profile'!O37 -> 2.2972544 | L23: =MIN('Growth profile'!L37,2085) -> 2079 | M23: ='Growth profile'!N37 -> 0 | N23: =IF(F23<0,"shrinking",IF(F23<0.015,"under 1.5%",IF(F23<0.018,"1.5% to 1.8%","1.8% and over"))) -> 1.8% and over | O23: =IF(I23>0,IF(L23=2085,"Deferred - pinned to horizon end","Deferred"),IF(I23<0,"Accelerated","Unchanged")) -> Deferred | P23: ='Growth (no penalty)'!I37 -> 2044 | Q23: =P23-G23 -> 13
A24: ='Growth profile'!A65 -> project 87 | B24: ='Growth profile'!B65 -> random growth | C24: ='Growth profile'!C65 -> 4 | D24: ='Growth profile'!D65 -> 2.16 | E24: ='Growth profile'!E65 -> 35.82378 | F24: ='Growth profile'!H65 -> 0.0275 | G24: ='Raw profile'!I65 -> 2030 | H24: ='Growth profile'!I65 -> 2037 | I24: =H24-G24 -> 7 | J24: ='Raw profile'!O65 -> 69.702892 | K24: ='Growth profile'!O65 -> 150.9946 | L24: =MIN('Growth profile'!L65,2085) -> 2079 | M24: ='Growth profile'!N65 -> 0 | N24: =IF(F24<0,"shrinking",IF(F24<0.015,"under 1.5%",IF(F24<0.018,"1.5% to 1.8%","1.8% and over"))) -> 1.8% and over | O24: =IF(I24>0,IF(L24=2085,"Deferred - pinned to horizon end","Deferred"),IF(I24<0,"Accelerated","Unchanged")) -> Deferred | P24: ='Growth (no penalty)'!I65 -> 2043 | Q24: =P24-G24 -> 13
A25: ='Growth profile'!A47 -> project 42 | B25: ='Growth profile'!B47 -> random growth | C25: ='Growth profile'!C47 -> 1 | D25: ='Growth profile'!D47 -> 1 | E25: ='Growth profile'!E47 -> 0.0545 | F25: ='Growth profile'!H47 -> 0.0258 | G25: ='Raw profile'!I47 -> 2031 | H25: ='Growth profile'!I47 -> 2037 | I25: =H25-G25 -> 6 | J25: ='Raw profile'!O47 -> 0.049665484 | K25: ='Growth profile'!O47 -> 0.098021152 | L25: =MIN('Growth profile'!L47,2085) -> 2077 | M25: ='Growth profile'!N47 -> 0 | N25: =IF(F25<0,"shrinking",IF(F25<0.015,"under 1.5%",IF(F25<0.018,"1.5% to 1.8%","1.8% and over"))) -> 1.8% and over | O25: =IF(I25>0,IF(L25=2085,"Deferred - pinned to horizon end","Deferred"),IF(I25<0,"Accelerated","Unchanged")) -> Deferred | P25: ='Growth (no penalty)'!I47 -> 2045 | Q25: =P25-G25 -> 14
A26: ='Growth profile'!A62 -> project 77 | B26: ='Growth profile'!B62 -> random growth | C26: ='Growth profile'!C62 -> 1 | D26: ='Growth profile'!D62 -> 1.89 | E26: ='Growth profile'!E62 -> 0.063222 | F26: ='Growth profile'!H62 -> 0.0187 | G26: ='Raw profile'!I62 -> 2031 | H26: ='Growth profile'!I62 -> 2037 | I26: =H26-G26 -> 6 | J26: ='Raw profile'!O62 -> 0.10889005 | K26: ='Growth profile'!O62 -> 0.17188332 | L26: =MIN('Growth profile'!L62,2085) -> 2077 | M26: ='Growth profile'!N62 -> 0 | N26: =IF(F26<0,"shrinking",IF(F26<0.015,"under 1.5%",IF(F26<0.018,"1.5% to 1.8%","1.8% and over"))) -> 1.8% and over | O26: =IF(I26>0,IF(L26=2085,"Deferred - pinned to horizon end","Deferred"),IF(I26<0,"Accelerated","Unchanged")) -> Deferred | P26: ='Growth (no penalty)'!I62 -> 2045 | Q26: =P26-G26 -> 14
A27: ='Growth profile'!A75 -> project 107 | B27: ='Growth profile'!B75 -> random growth | C27: ='Growth profile'!C75 -> 5 | D27: ='Growth profile'!D75 -> 2.08 | E27: ='Growth profile'!E75 -> 425.52254 | F27: ='Growth profile'!H75 -> 0.0253 | G27: ='Raw profile'!I75 -> 2028 | H27: ='Growth profile'!I75 -> 2033 | I27: =H27-G27 -> 5 | J27: ='Raw profile'!O75 -> 738.58928 | K27: ='Growth profile'!O75 -> 1622.6542 | L27: =MIN('Growth profile'!L75,2085) -> 2081 | M27: ='Growth profile'!N75 -> 0 | N27: =IF(F27<0,"shrinking",IF(F27<0.015,"under 1.5%",IF(F27<0.018,"1.5% to 1.8%","1.8% and over"))) -> 1.8% and over | O27: =IF(I27>0,IF(L27=2085,"Deferred - pinned to horizon end","Deferred"),IF(I27<0,"Accelerated","Unchanged")) -> Deferred | P27: ='Growth (no penalty)'!I75 -> 2037 | Q27: =P27-G27 -> 9
A28: ='Growth profile'!A82 -> project 121 | B28: ='Growth profile'!B82 -> random growth | C28: ='Growth profile'!C82 -> 5 | D28: ='Growth profile'!D82 -> 1.87 | E28: ='Growth profile'!E82 -> 128.03976 | F28: ='Growth profile'!H82 -> 0.0286 | G28: ='Raw profile'!I82 -> 2037 | H28: ='Growth profile'!I82 -> 2042 | I28: =H28-G28 -> 5 | J28: ='Raw profile'!O82 -> 192.64176 | K28: ='Growth profile'!O82 -> 520.52194 | L28: =MIN('Growth profile'!L82,2085) -> 2084 | M28: ='Growth profile'!N82 -> 0 | N28: =IF(F28<0,"shrinking",IF(F28<0.015,"under 1.5%",IF(F28<0.018,"1.5% to 1.8%","1.8% and over"))) -> 1.8% and over | O28: =IF(I28>0,IF(L28=2085,"Deferred - pinned to horizon end","Deferred"),IF(I28<0,"Accelerated","Unchanged")) -> Deferred | P28: ='Growth (no penalty)'!I82 -> 2043 | Q28: =P28-G28 -> 6
A29: ='Growth profile'!A31 -> project 19 | B29: ='Growth profile'!B31 -> random growth | C29: ='Growth profile'!C31 -> 2 | D29: ='Growth profile'!D31 -> 1.39 | E29: ='Growth profile'!E31 -> 2.071 | F29: ='Growth profile'!H31 -> 0.0283 | G29: ='Raw profile'!I31 -> 2037 | H29: ='Growth profile'!I31 -> 2042 | I29: =H29-G29 -> 5 | J29: ='Raw profile'!O31 -> 2.3554772 | K29: ='Growth profile'!O31 -> 5.9339431 | L29: =MIN('Growth profile'!L31,2085) -> 2082 | M29: ='Growth profile'!N31 -> 0 | N29: =IF(F29<0,"shrinking",IF(F29<0.015,"under 1.5%",IF(F29<0.018,"1.5% to 1.8%","1.8% and over"))) -> 1.8% and over | O29: =IF(I29>0,IF(L29=2085,"Deferred - pinned to horizon end","Deferred"),IF(I29<0,"Accelerated","Unchanged")) -> Deferred | P29: ='Growth (no penalty)'!I31 -> 2045 | Q29: =P29-G29 -> 8
A30: ='Growth profile'!A122 -> project 213 | B30: ='Growth profile'!B122 -> random growth | C30: ='Growth profile'!C122 -> 1 | D30: ='Growth profile'!D122 -> 2.1 | E30: ='Growth profile'!E122 -> 0.042979235 | F30: ='Growth profile'!H122 -> 0.0234 | G30: ='Raw profile'!I122 -> 2031 | H30: ='Growth profile'!I122 -> 2036 | I30: =H30-G30 -> 5 | J30: ='Raw profile'!O122 -> 0.081764087 | K30: ='Growth profile'!O122 -> 0.15230604 | L30: =MIN('Growth profile'!L122,2085) -> 2077 | M30: ='Growth profile'!N122 -> 0 | N30: =IF(F30<0,"shrinking",IF(F30<0.015,"under 1.5%",IF(F30<0.018,"1.5% to 1.8%","1.8% and over"))) -> 1.8% and over | O30: =IF(I30>0,IF(L30=2085,"Deferred - pinned to horizon end","Deferred"),IF(I30<0,"Accelerated","Unchanged")) -> Deferred | P30: ='Growth (no penalty)'!I122 -> 2044 | Q30: =P30-G30 -> 13
A31: ='Growth profile'!A46 -> project 41 | B31: ='Growth profile'!B46 -> random growth | C31: ='Growth profile'!C46 -> 2 | D31: ='Growth profile'!D46 -> 2.15 | E31: ='Growth profile'!E46 -> 1.404405 | F31: ='Growth profile'!H46 -> 0.0225 | G31: ='Raw profile'!I46 -> 2031 | H31: ='Growth profile'!I46 -> 2036 | I31: =H31-G31 -> 5 | J31: ='Raw profile'!O46 -> 2.7263997 | K31: ='Growth profile'!O46 -> 4.936495 | L31: =MIN('Growth profile'!L46,2085) -> 2077 | M31: ='Growth profile'!N46 -> 0 | N31: =IF(F31<0,"shrinking",IF(F31<0.015,"under 1.5%",IF(F31<0.018,"1.5% to 1.8%","1.8% and over"))) -> 1.8% and over | O31: =IF(I31>0,IF(L31=2085,"Deferred - pinned to horizon end","Deferred"),IF(I31<0,"Accelerated","Unchanged")) -> Deferred | P31: ='Growth (no penalty)'!I46 -> 2044 | Q31: =P31-G31 -> 13
A32: ='Growth profile'!A49 -> project 44 | B32: ='Growth profile'!B49 -> random growth | C32: ='Growth profile'!C49 -> 1 | D32: ='Growth profile'!D49 -> 1 | E32: ='Growth profile'!E49 -> 0.0327 | F32: ='Growth profile'!H49 -> 0.0113 | G32: ='Raw profile'!I49 -> 2026 | H32: ='Growth profile'!I49 -> 2031 | I32: =H32-G32 -> 5 | J32: ='Raw profile'!O49 -> 0.0327 | K32: ='Growth profile'!O49 -> 0.038944387 | L32: =MIN('Growth profile'!L49,2085) -> 2071 | M32: ='Growth profile'!N49 -> 0 | N32: =IF(F32<0,"shrinking",IF(F32<0.015,"under 1.5%",IF(F32<0.018,"1.5% to 1.8%","1.8% and over"))) -> under 1.5% | O32: =IF(I32>0,IF(L32=2085,"Deferred - pinned to horizon end","Deferred"),IF(I32<0,"Accelerated","Unchanged")) -> Deferred | P32: ='Growth (no penalty)'!I49 -> 2032 | Q32: =P32-G32 -> 6
A33: ='Growth profile'!A52 -> project 50 | B33: ='Growth profile'!B52 -> random growth | C33: ='Growth profile'!C52 -> 4 | D33: ='Growth profile'!D52 -> 3.32 | E33: ='Growth profile'!E52 -> 21.837139 | F33: ='Growth profile'!H52 -> 0.0206 | G33: ='Raw profile'!I52 -> 2027 | H33: ='Growth profile'!I52 -> 2032 | I33: =H33-G33 -> 5 | J33: ='Raw profile'!O52 -> 65.502527 | K33: ='Growth profile'!O52 -> 116.64332 | L33: =MIN('Growth profile'!L52,2085) -> 2079 | M33: ='Growth profile'!N52 -> 0 | N33: =IF(F33<0,"shrinking",IF(F33<0.015,"under 1.5%",IF(F33<0.018,"1.5% to 1.8%","1.8% and over"))) -> 1.8% and over | O33: =IF(I33>0,IF(L33=2085,"Deferred - pinned to horizon end","Deferred"),IF(I33<0,"Accelerated","Unchanged")) -> Deferred | P33: ='Growth (no penalty)'!I52 -> 2038 | Q33: =P33-G33 -> 11
A34: ='Growth profile'!A78 -> project 112 | B34: ='Growth profile'!B78 -> random growth | C34: ='Growth profile'!C78 -> 5 | D34: ='Growth profile'!D78 -> 2.4 | E34: ='Growth profile'!E78 -> 249.26957 | F34: ='Growth profile'!H78 -> 0.0206 | G34: ='Raw profile'!I78 -> 2032 | H34: ='Growth profile'!I78 -> 2035 | I34: =H34-G34 -> 3 | J34: ='Raw profile'!O78 -> 524.75095 | K34: ='Growth profile'!O78 -> 928.05274 | L34: =MIN('Growth profile'!L78,2085) -> 2077 | M34: ='Growth profile'!N78 -> 0 | N34: =IF(F34<0,"shrinking",IF(F34<0.015,"under 1.5%",IF(F34<0.018,"1.5% to 1.8%","1.8% and over"))) -> 1.8% and over | O34: =IF(I34>0,IF(L34=2085,"Deferred - pinned to horizon end","Deferred"),IF(I34<0,"Accelerated","Unchanged")) -> Deferred | P34: ='Growth (no penalty)'!I78 -> 2043 | Q34: =P34-G34 -> 11
A35: ='Growth profile'!A39 -> project 29 | B35: ='Growth profile'!B39 -> random growth | C35: ='Growth profile'!C39 -> 1 | D35: ='Growth profile'!D39 -> 2.08 | E35: ='Growth profile'!E39 -> 0.32379412 | F35: ='Growth profile'!H39 -> 0.018 | G35: ='Raw profile'!I39 -> 2032 | H35: ='Growth profile'!I39 -> 2034 | I35: =H35-G35 -> 2 | J35: ='Raw profile'!O39 -> 0.59719587 | K35: ='Growth profile'!O39 -> 0.95547177 | L35: =MIN('Growth profile'!L39,2085) -> 2075 | M35: ='Growth profile'!N39 -> 0 | N35: =IF(F35<0,"shrinking",IF(F35<0.015,"under 1.5%",IF(F35<0.018,"1.5% to 1.8%","1.8% and over"))) -> 1.8% and over | O35: =IF(I35>0,IF(L35=2085,"Deferred - pinned to horizon end","Deferred"),IF(I35<0,"Accelerated","Unchanged")) -> Deferred | P35: ='Growth (no penalty)'!I39 -> 2044 | Q35: =P35-G35 -> 12
A36: ='Growth profile'!A26 -> project 7 | B36: ='Growth profile'!B26 -> random growth | C36: ='Growth profile'!C26 -> 3 | D36: ='Growth profile'!D26 -> 1.46 | E36: ='Growth profile'!E26 -> 7.63 | F36: ='Growth profile'!H26 -> 0.0289 | G36: ='Raw profile'!I26 -> 2037 | H36: ='Growth profile'!I26 -> 2038 | I36: =H36-G36 -> 1 | J36: ='Raw profile'!O26 -> 9.1150993 | K36: ='Growth profile'!O26 -> 22.381748 | L36: =MIN('Growth profile'!L26,2085) -> 2078 | M36: ='Growth profile'!N26 -> 0 | N36: =IF(F36<0,"shrinking",IF(F36<0.015,"under 1.5%",IF(F36<0.018,"1.5% to 1.8%","1.8% and over"))) -> 1.8% and over | O36: =IF(I36>0,IF(L36=2085,"Deferred - pinned to horizon end","Deferred"),IF(I36<0,"Accelerated","Unchanged")) -> Deferred | P36: ='Growth (no penalty)'!I26 -> 2045 | Q36: =P36-G36 -> 8
A37: ='Growth profile'!A74 -> project 106 | B37: ='Growth profile'!B74 -> random growth | C37: ='Growth profile'!C74 -> 5 | D37: ='Growth profile'!D74 -> 2.79 | E37: ='Growth profile'!E74 -> 440.52707 | F37: ='Growth profile'!H74 -> 0.0131 | G37: ='Raw profile'!I74 -> 2026 | H37: ='Growth profile'!I74 -> 2026 | I37: =H37-G37 -> 0 | J37: ='Raw profile'!O74 -> 1145.5241 | K37: ='Growth profile'!O74 -> 1628.0284 | L37: =MIN('Growth profile'!L74,2085) -> 2074 | M37: ='Growth profile'!N74 -> 0 | N37: =IF(F37<0,"shrinking",IF(F37<0.015,"under 1.5%",IF(F37<0.018,"1.5% to 1.8%","1.8% and over"))) -> under 1.5% | O37: =IF(I37>0,IF(L37=2085,"Deferred - pinned to horizon end","Deferred"),IF(I37<0,"Accelerated","Unchanged")) -> Unchanged | P37: ='Growth (no penalty)'!I74 -> 2026 | Q37: =P37-G37 -> 0
A38: ='Growth profile'!A76 -> project 108 | B38: ='Growth profile'!B76 -> random growth | C38: ='Growth profile'!C76 -> 5 | D38: ='Growth profile'!D76 -> 2.19 | E38: ='Growth profile'!E76 -> 300.06953 | F38: ='Growth profile'!H76 -> 0.0208 | G38: ='Raw profile'!I76 -> 2029 | H38: ='Growth profile'!I76 -> 2029 | I38: =H38-G38 -> 0 | J38: ='Raw profile'!O76 -> 561.17208 | K38: ='Growth profile'!O76 -> 1220.7562 | L38: =MIN('Growth profile'!L76,2085) -> 2084 | M38: ='Growth profile'!N76 -> 0 | N38: =IF(F38<0,"shrinking",IF(F38<0.015,"under 1.5%",IF(F38<0.018,"1.5% to 1.8%","1.8% and over"))) -> 1.8% and over | O38: =IF(I38>0,IF(L38=2085,"Deferred - pinned to horizon end","Deferred"),IF(I38<0,"Accelerated","Unchanged")) -> Unchanged | P38: ='Growth (no penalty)'!I76 -> 2030 | Q38: =P38-G38 -> 1
A39: ='Growth profile'!A79 -> project 116 | B39: ='Growth profile'!B79 -> random growth | C39: ='Growth profile'!C79 -> 5 | D39: ='Growth profile'!D79 -> 2.66 | E39: ='Growth profile'!E79 -> 178.82623 | F39: ='Growth profile'!H79 -> 0.01 | G39: ='Raw profile'!I79 -> 2026 | H39: ='Growth profile'!I79 -> 2026 | I39: =H39-G39 -> 0 | J39: ='Raw profile'!O79 -> 457.7364 | K39: ='Growth profile'!O79 -> 573.80192 | L39: =MIN('Growth profile'!L79,2085) -> 2070 | M39: ='Growth profile'!N79 -> 0 | N39: =IF(F39<0,"shrinking",IF(F39<0.015,"under 1.5%",IF(F39<0.018,"1.5% to 1.8%","1.8% and over"))) -> under 1.5% | O39: =IF(I39>0,IF(L39=2085,"Deferred - pinned to horizon end","Deferred"),IF(I39<0,"Accelerated","Unchanged")) -> Unchanged | P39: ='Growth (no penalty)'!I79 -> 2026 | Q39: =P39-G39 -> 0
A40: ='Growth profile'!A81 -> project 120 | B40: ='Growth profile'!B81 -> random growth | C40: ='Growth profile'!C81 -> 5 | D40: ='Growth profile'!D81 -> 4.19 | E40: ='Growth profile'!E81 -> 147.05308 | F40: ='Growth profile'!H81 -> 0.0104 | G40: ='Raw profile'!I81 -> 2026 | H40: ='Growth profile'!I81 -> 2026 | I40: =H40-G40 -> 0 | J40: ='Raw profile'!O81 -> 578.16995 | K40: ='Growth profile'!O81 -> 739.29467 | L40: =MIN('Growth profile'!L81,2085) -> 2071 | M40: ='Growth profile'!N81 -> 0 | N40: =IF(F40<0,"shrinking",IF(F40<0.015,"under 1.5%",IF(F40<0.018,"1.5% to 1.8%","1.8% and over"))) -> under 1.5% | O40: =IF(I40>0,IF(L40=2085,"Deferred - pinned to horizon end","Deferred"),IF(I40<0,"Accelerated","Unchanged")) -> Unchanged | P40: ='Growth (no penalty)'!I81 -> 2026 | Q40: =P40-G40 -> 0
A41: ='Growth profile'!A97 -> project 153 | B41: ='Growth profile'!B97 -> random growth | C41: ='Growth profile'!C97 -> 3 | D41: ='Growth profile'!D97 -> 2.4 | E41: ='Growth profile'!E97 -> 13.063524 | F41: ='Growth profile'!H97 -> 0.0153 | G41: ='Raw profile'!I97 -> 2026 | H41: ='Growth profile'!I97 -> 2026 | I41: =H41-G41 -> 0 | J41: ='Raw profile'!O97 -> 31.159668 | K41: ='Growth profile'!O97 -> 42.216316 | L41: =MIN('Growth profile'!L97,2085) -> 2067 | M41: ='Growth profile'!N97 -> 0 | N41: =IF(F41<0,"shrinking",IF(F41<0.015,"under 1.5%",IF(F41<0.018,"1.5% to 1.8%","1.8% and over"))) -> 1.5% to 1.8% | O41: =IF(I41>0,IF(L41=2085,"Deferred - pinned to horizon end","Deferred"),IF(I41<0,"Accelerated","Unchanged")) -> Unchanged | P41: ='Growth (no penalty)'!I97 -> 2026 | Q41: =P41-G41 -> 0
A42: ='Growth profile'!A121 -> project 211 | B42: ='Growth profile'!B121 -> random growth | C42: ='Growth profile'!C121 -> 1 | D42: ='Growth profile'!D121 -> 4.76 | E42: ='Growth profile'!E121 -> 0.05 | F42: ='Growth profile'!H121 -> 0.0148 | G42: ='Raw profile'!I121 -> 2026 | H42: ='Growth profile'!I121 -> 2026 | I42: =H42-G42 -> 0 | J42: ='Raw profile'!O121 -> 0.238 | K42: ='Growth profile'!O121 -> 0.31439808 | L42: =MIN('Growth profile'!L121,2085) -> 2066 | M42: ='Growth profile'!N121 -> 0 | N42: =IF(F42<0,"shrinking",IF(F42<0.015,"under 1.5%",IF(F42<0.018,"1.5% to 1.8%","1.8% and over"))) -> under 1.5% | O42: =IF(I42>0,IF(L42=2085,"Deferred - pinned to horizon end","Deferred"),IF(I42<0,"Accelerated","Unchanged")) -> Unchanged | P42: ='Growth (no penalty)'!I121 -> 2026 | Q42: =P42-G42 -> 0
A43: ='Growth profile'!A33 -> project 22 | B43: ='Growth profile'!B33 -> random growth | C43: ='Growth profile'!C33 -> 2 | D43: ='Growth profile'!D33 -> 3.73 | E43: ='Growth profile'!E33 -> 1.3854571 | F43: ='Growth profile'!H33 -> 0.0153 | G43: ='Raw profile'!I33 -> 2026 | H43: ='Growth profile'!I33 -> 2026 | I43: =H43-G43 -> 0 | J43: ='Raw profile'!O33 -> 5.1560314 | K43: ='Growth profile'!O33 -> 6.9855895 | L43: =MIN('Growth profile'!L33,2085) -> 2067 | M43: ='Growth profile'!N33 -> 0 | N43: =IF(F43<0,"shrinking",IF(F43<0.015,"under 1.5%",IF(F43<0.018,"1.5% to 1.8%","1.8% and over"))) -> 1.5% to 1.8% | O43: =IF(I43>0,IF(L43=2085,"Deferred - pinned to horizon end","Deferred"),IF(I43<0,"Accelerated","Unchanged")) -> Unchanged | P43: ='Growth (no penalty)'!I33 -> 2026 | Q43: =P43-G43 -> 0
A44: ='Growth profile'!A36 -> project 26 | B44: ='Growth profile'!B36 -> random growth | C44: ='Growth profile'!C36 -> 1 | D44: ='Growth profile'!D36 -> 2.94 | E44: ='Growth profile'!E36 -> 0.32058824 | F44: ='Growth profile'!H36 -> 0.0153 | G44: ='Raw profile'!I36 -> 2026 | H44: ='Growth profile'!I36 -> 2026 | I44: =H44-G44 -> 0 | J44: ='Raw profile'!O36 -> 0.94252941 | K44: ='Growth profile'!O36 -> 1.2573838 | L44: =MIN('Growth profile'!L36,2085) -> 2066 | M44: ='Growth profile'!N36 -> 0 | N44: =IF(F44<0,"shrinking",IF(F44<0.015,"under 1.5%",IF(F44<0.018,"1.5% to 1.8%","1.8% and over"))) -> 1.5% to 1.8% | O44: =IF(I44>0,IF(L44=2085,"Deferred - pinned to horizon end","Deferred"),IF(I44<0,"Accelerated","Unchanged")) -> Unchanged | P44: ='Growth (no penalty)'!I36 -> 2026 | Q44: =P44-G44 -> 0
A45: ='Growth profile'!A38 -> project 28 | B45: ='Growth profile'!B38 -> shrinker: -2% | C45: ='Growth profile'!C38 -> 1 | D45: ='Growth profile'!D38 -> 7 | E45: ='Growth profile'!E38 -> 0.32379412 | F45: ='Growth profile'!H38 -> -0.02 | G45: ='Raw profile'!I38 -> 2026 | H45: ='Growth profile'!I38 -> 2026 | I45: =H45-G45 -> 0 | J45: ='Raw profile'!O38 -> 2.2445577 | K45: ='Growth profile'!O38 -> 1.5693718 | L45: =MIN('Growth profile'!L38,2085) -> 2067 | M45: ='Growth profile'!N38 -> 0 | N45: =IF(F45<0,"shrinking",IF(F45<0.015,"under 1.5%",IF(F45<0.018,"1.5% to 1.8%","1.8% and over"))) -> shrinking | O45: =IF(I45>0,IF(L45=2085,"Deferred - pinned to horizon end","Deferred"),IF(I45<0,"Accelerated","Unchanged")) -> Unchanged | P45: ='Growth (no penalty)'!I38 -> 2026 | Q45: =P45-G45 -> 0
A46: ='Growth profile'!A40 -> project 32 | B46: ='Growth profile'!B40 -> random growth | C46: ='Growth profile'!C40 -> 4 | D46: ='Growth profile'!D40 -> 3.3 | E46: ='Growth profile'!E40 -> 15.455842 | F46: ='Growth profile'!H40 -> 0.0144 | G46: ='Raw profile'!I40 -> 2026 | H46: ='Growth profile'!I40 -> 2026 | I46: =H46-G46 -> 0 | J46: ='Raw profile'!O40 -> 49.346088 | K46: ='Growth profile'!O40 -> 66.588523 | L46: =MIN('Growth profile'!L40,2085) -> 2068 | M46: ='Growth profile'!N40 -> 0 | N46: =IF(F46<0,"shrinking",IF(F46<0.015,"under 1.5%",IF(F46<0.018,"1.5% to 1.8%","1.8% and over"))) -> under 1.5% | O46: =IF(I46>0,IF(L46=2085,"Deferred - pinned to horizon end","Deferred"),IF(I46<0,"Accelerated","Unchanged")) -> Unchanged | P46: ='Growth (no penalty)'!I40 -> 2026 | Q46: =P46-G46 -> 0
A47: ='Growth profile'!A25 -> project 4 | B47: ='Growth profile'!B25 -> random growth | C47: ='Growth profile'!C25 -> 2 | D47: ='Growth profile'!D25 -> 4.49 | E47: ='Growth profile'!E25 -> 1.6835429 | F47: ='Growth profile'!H25 -> 0.0142 | G47: ='Raw profile'!I25 -> 2026 | H47: ='Growth profile'!I25 -> 2026 | I47: =H47-G47 -> 0 | J47: ='Raw profile'!O25 -> 7.5362348 | K47: ='Growth profile'!O25 -> 9.9812277 | L47: =MIN('Growth profile'!L25,2085) -> 2067 | M47: ='Growth profile'!N25 -> 0 | N47: =IF(F47<0,"shrinking",IF(F47<0.015,"under 1.5%",IF(F47<0.018,"1.5% to 1.8%","1.8% and over"))) -> under 1.5% | O47: =IF(I47>0,IF(L47=2085,"Deferred - pinned to horizon end","Deferred"),IF(I47<0,"Accelerated","Unchanged")) -> Unchanged | P47: ='Growth (no penalty)'!I25 -> 2026 | Q47: =P47-G47 -> 0
A48: ='Growth profile'!A59 -> project 64 | B48: ='Growth profile'!B59 -> random growth | C48: ='Growth profile'!C59 -> 3 | D48: ='Growth profile'!D59 -> 6.35 | E48: ='Growth profile'!E59 -> 5.685148 | F48: ='Growth profile'!H59 -> 0.0153 | G48: ='Raw profile'!I59 -> 2026 | H48: ='Growth profile'!I59 -> 2026 | I48: =H48-G48 -> 0 | J48: ='Raw profile'!O59 -> 35.63191 | K48: ='Growth profile'!O59 -> 48.275481 | L48: =MIN('Growth profile'!L59,2085) -> 2067 | M48: ='Growth profile'!N59 -> 0 | N48: =IF(F48<0,"shrinking",IF(F48<0.015,"under 1.5%",IF(F48<0.018,"1.5% to 1.8%","1.8% and over"))) -> 1.5% to 1.8% | O48: =IF(I48>0,IF(L48=2085,"Deferred - pinned to horizon end","Deferred"),IF(I48<0,"Accelerated","Unchanged")) -> Unchanged | P48: ='Growth (no penalty)'!I59 -> 2026 | Q48: =P48-G48 -> 0
A49: ='Growth profile'!A63 -> project 78 | B49: ='Growth profile'!B63 -> random growth | C49: ='Growth profile'!C63 -> 5 | D49: ='Growth profile'!D63 -> 1.91 | E49: ='Growth profile'!E63 -> 79.104192 | F49: ='Growth profile'!H63 -> 0.0191 | G49: ='Raw profile'!I63 -> 2032 | H49: ='Growth profile'!I63 -> 2032 | I49: =H49-G49 -> 0 | J49: ='Raw profile'!O63 -> 130.73436 | K49: ='Growth profile'!O63 -> 219.56531 | L49: =MIN('Growth profile'!L63,2085) -> 2074 | M49: ='Growth profile'!N63 -> 0 | N49: =IF(F49<0,"shrinking",IF(F49<0.015,"under 1.5%",IF(F49<0.018,"1.5% to 1.8%","1.8% and over"))) -> 1.8% and over | O49: =IF(I49>0,IF(L49=2085,"Deferred - pinned to horizon end","Deferred"),IF(I49<0,"Accelerated","Unchanged")) -> Unchanged | P49: ='Growth (no penalty)'!I63 -> 2043 | Q49: =P49-G49 -> 11
A50: ='Growth profile'!A77 -> project 110 | B50: ='Growth profile'!B77 -> random growth | C50: ='Growth profile'!C77 -> 5 | D50: ='Growth profile'!D77 -> 1.57 | E50: ='Growth profile'!E77 -> 330.73303 | F50: ='Growth profile'!H77 -> 0.0256 | G50: ='Raw profile'!I77 -> 2033 | H50: ='Growth profile'!I77 -> 2032 | I50: =H50-G50 -> -1 | J50: ='Raw profile'!O77 -> 410.0477 | K50: ='Growth profile'!O77 -> 959.61841 | L50: =MIN('Growth profile'!L77,2085) -> 2079 | M50: ='Growth profile'!N77 -> 0 | N50: =IF(F50<0,"shrinking",IF(F50<0.015,"under 1.5%",IF(F50<0.018,"1.5% to 1.8%","1.8% and over"))) -> 1.8% and over | O50: =IF(I50>0,IF(L50=2085,"Deferred - pinned to horizon end","Deferred"),IF(I50<0,"Accelerated","Unchanged")) -> Accelerated | P50: ='Growth (no penalty)'!I77 -> 2038 | Q50: =P50-G50 -> 5
A51: ='Growth profile'!A91 -> project 144 | B51: ='Growth profile'!B91 -> random growth | C51: ='Growth profile'!C91 -> 4 | D51: ='Growth profile'!D91 -> 2.53 | E51: ='Growth profile'!E91 -> 27.535001 | F51: ='Growth profile'!H91 -> 0.0114 | G51: ='Raw profile'!I91 -> 2027 | H51: ='Growth profile'!I91 -> 2026 | I51: =H51-G51 -> -1 | J51: ='Raw profile'!O91 -> 63.644686 | K51: ='Growth profile'!O91 -> 83.94586 | L51: =MIN('Growth profile'!L91,2085) -> 2070 | M51: ='Growth profile'!N91 -> 0 | N51: =IF(F51<0,"shrinking",IF(F51<0.015,"under 1.5%",IF(F51<0.018,"1.5% to 1.8%","1.8% and over"))) -> under 1.5% | O51: =IF(I51>0,IF(L51=2085,"Deferred - pinned to horizon end","Deferred"),IF(I51<0,"Accelerated","Unchanged")) -> Accelerated | P51: ='Growth (no penalty)'!I91 -> 2026 | Q51: =P51-G51 -> -1
A52: ='Growth profile'!A101 -> project 161 | B52: ='Growth profile'!B101 -> random growth | C52: ='Growth profile'!C101 -> 3 | D52: ='Growth profile'!D101 -> 1.67 | E52: ='Growth profile'!E101 -> 11.881 | F52: ='Growth profile'!H101 -> 0.0208 | G52: ='Raw profile'!I101 -> 2037 | H52: ='Growth profile'!I101 -> 2035 | I52: =H52-G52 -> -2 | J52: ='Raw profile'!O101 -> 16.235044 | K52: ='Growth profile'!O101 -> 30.269542 | L52: =MIN('Growth profile'!L101,2085) -> 2075 | M52: ='Growth profile'!N101 -> 0 | N52: =IF(F52<0,"shrinking",IF(F52<0.015,"under 1.5%",IF(F52<0.018,"1.5% to 1.8%","1.8% and over"))) -> 1.8% and over | O52: =IF(I52>0,IF(L52=2085,"Deferred - pinned to horizon end","Deferred"),IF(I52<0,"Accelerated","Unchanged")) -> Accelerated | P52: ='Growth (no penalty)'!I101 -> 2045 | Q52: =P52-G52 -> 8
A53: ='Growth profile'!A35 -> project 24 | B53: ='Growth profile'!B35 -> random growth | C53: ='Growth profile'!C35 -> 1 | D53: ='Growth profile'!D35 -> 1.4 | E53: ='Growth profile'!E35 -> 1.2198382 | F53: ='Growth profile'!H35 -> 0.0212 | G53: ='Raw profile'!I35 -> 2037 | H53: ='Growth profile'!I35 -> 2035 | I53: =H53-G53 -> -2 | J53: ='Raw profile'!O35 -> 1.3919475 | K53: ='Growth profile'!O35 -> 2.682235 | L53: =MIN('Growth profile'!L35,2085) -> 2076 | M53: ='Growth profile'!N35 -> 0 | N53: =IF(F53<0,"shrinking",IF(F53<0.015,"under 1.5%",IF(F53<0.018,"1.5% to 1.8%","1.8% and over"))) -> 1.8% and over | O53: =IF(I53>0,IF(L53=2085,"Deferred - pinned to horizon end","Deferred"),IF(I53<0,"Accelerated","Unchanged")) -> Accelerated | P53: ='Growth (no penalty)'!I35 -> 2044 | Q53: =P53-G53 -> 7
A54: ='Growth profile'!A89 -> project 137 | B54: ='Growth profile'!B89 -> random growth | C54: ='Growth profile'!C89 -> 5 | D54: ='Growth profile'!D89 -> 2.92 | E54: ='Growth profile'!E89 -> 46.943105 | F54: ='Growth profile'!H89 -> 0.0117 | G54: ='Raw profile'!I89 -> 2029 | H54: ='Growth profile'!I89 -> 2026 | I54: =H54-G54 -> -3 | J54: ='Raw profile'!O89 -> 126.33206 | K54: ='Growth profile'!O89 -> 170.0463 | L54: =MIN('Growth profile'!L89,2085) -> 2068 | M54: ='Growth profile'!N89 -> 0 | N54: =IF(F54<0,"shrinking",IF(F54<0.015,"under 1.5%",IF(F54<0.018,"1.5% to 1.8%","1.8% and over"))) -> under 1.5% | O54: =IF(I54>0,IF(L54=2085,"Deferred - pinned to horizon end","Deferred"),IF(I54<0,"Accelerated","Unchanged")) -> Accelerated | P54: ='Growth (no penalty)'!I89 -> 2026 | Q54: =P54-G54 -> -3
A55: ='Growth profile'!A95 -> project 149 | B55: ='Growth profile'!B95 -> random growth | C55: ='Growth profile'!C95 -> 4 | D55: ='Growth profile'!D95 -> 1.7 | E55: ='Growth profile'!E95 -> 21.708014 | F55: ='Growth profile'!H95 -> 0.0195 | G55: ='Raw profile'!I95 -> 2036 | H55: ='Growth profile'!I95 -> 2033 | I55: =H55-G55 -> -3 | J55: ='Raw profile'!O95 -> 29.93034 | K55: ='Growth profile'!O95 -> 54.671267 | L55: =MIN('Growth profile'!L95,2085) -> 2075 | M55: ='Growth profile'!N95 -> 0 | N55: =IF(F55<0,"shrinking",IF(F55<0.015,"under 1.5%",IF(F55<0.018,"1.5% to 1.8%","1.8% and over"))) -> 1.8% and over | O55: =IF(I55>0,IF(L55=2085,"Deferred - pinned to horizon end","Deferred"),IF(I55<0,"Accelerated","Unchanged")) -> Accelerated | P55: ='Growth (no penalty)'!I95 -> 2043 | Q55: =P55-G55 -> 7
A56: ='Growth profile'!A99 -> project 157 | B56: ='Growth profile'!B99 -> random growth | C56: ='Growth profile'!C99 -> 3 | D56: ='Growth profile'!D99 -> 1.63 | E56: ='Growth profile'!E99 -> 13.672991 | F56: ='Growth profile'!H99 -> 0.0185 | G56: ='Raw profile'!I99 -> 2036 | H56: ='Growth profile'!I99 -> 2033 | I56: =H56-G56 -> -3 | J56: ='Raw profile'!O99 -> 18.140393 | K56: ='Growth profile'!O99 -> 32.184132 | L56: =MIN('Growth profile'!L99,2085) -> 2075 | M56: ='Growth profile'!N99 -> 0 | N56: =IF(F56<0,"shrinking",IF(F56<0.015,"under 1.5%",IF(F56<0.018,"1.5% to 1.8%","1.8% and over"))) -> 1.8% and over | O56: =IF(I56>0,IF(L56=2085,"Deferred - pinned to horizon end","Deferred"),IF(I56<0,"Accelerated","Unchanged")) -> Accelerated | P56: ='Growth (no penalty)'!I99 -> 2043 | Q56: =P56-G56 -> 7
A57: ='Growth profile'!A103 -> project 166 | B57: ='Growth profile'!B103 -> random growth | C57: ='Growth profile'!C103 -> 3 | D57: ='Growth profile'!D103 -> 2.49 | E57: ='Growth profile'!E103 -> 9.6976119 | F57: ='Growth profile'!H103 -> 0.014 | G57: ='Raw profile'!I103 -> 2029 | H57: ='Growth profile'!I103 -> 2026 | I57: =H57-G57 -> -3 | J57: ='Raw profile'!O103 -> 21.583516 | K57: ='Growth profile'!O103 -> 30.945713 | L57: =MIN('Growth profile'!L103,2085) -> 2069 | M57: ='Growth profile'!N103 -> 0 | N57: =IF(F57<0,"shrinking",IF(F57<0.015,"under 1.5%",IF(F57<0.018,"1.5% to 1.8%","1.8% and over"))) -> under 1.5% | O57: =IF(I57>0,IF(L57=2085,"Deferred - pinned to horizon end","Deferred"),IF(I57<0,"Accelerated","Unchanged")) -> Accelerated | P57: ='Growth (no penalty)'!I103 -> 2026 | Q57: =P57-G57 -> -3
A58: ='Growth profile'!A42 -> project 37 | B58: ='Growth profile'!B42 -> random growth | C58: ='Growth profile'!C42 -> 3 | D58: ='Growth profile'!D42 -> 1.84 | E58: ='Growth profile'!E42 -> 8.6772549 | F58: ='Growth profile'!H42 -> 0.0202 | G58: ='Raw profile'!I42 -> 2037 | H58: ='Growth profile'!I42 -> 2034 | I58: =H58-G58 -> -3 | J58: ='Raw profile'!O42 -> 13.017693 | K58: ='Growth profile'!O42 -> 24.269694 | L58: =MIN('Growth profile'!L42,2085) -> 2075 | M58: ='Growth profile'!N42 -> 0 | N58: =IF(F58<0,"shrinking",IF(F58<0.015,"under 1.5%",IF(F58<0.018,"1.5% to 1.8%","1.8% and over"))) -> 1.8% and over | O58: =IF(I58>0,IF(L58=2085,"Deferred - pinned to horizon end","Deferred"),IF(I58<0,"Accelerated","Unchanged")) -> Accelerated | P58: ='Growth (no penalty)'!I42 -> 2044 | Q58: =P58-G58 -> 7
A59: ='Growth profile'!A54 -> project 53 | B59: ='Growth profile'!B54 -> random growth | C59: ='Growth profile'!C54 -> 2 | D59: ='Growth profile'!D54 -> 1.13 | E59: ='Growth profile'!E54 -> 3.056 | F59: ='Growth profile'!H54 -> 0.0272 | G59: ='Raw profile'!I54 -> 2041 | H59: ='Growth profile'!I54 -> 2038 | I59: =H59-G59 -> -3 | J59: ='Raw profile'!O54 -> 2.6032413 | K59: ='Growth profile'!O54 -> 6.6546728 | L59: =MIN('Growth profile'!L54,2085) -> 2079 | M59: ='Growth profile'!N54 -> 0 | N59: =IF(F59<0,"shrinking",IF(F59<0.015,"under 1.5%",IF(F59<0.018,"1.5% to 1.8%","1.8% and over"))) -> 1.8% and over | O59: =IF(I59>0,IF(L59=2085,"Deferred - pinned to horizon end","Deferred"),IF(I59<0,"Accelerated","Unchanged")) -> Accelerated | P59: ='Growth (no penalty)'!I54 -> 2044 | Q59: =P59-G59 -> 3
A60: ='Growth profile'!A61 -> project 75 | B60: ='Growth profile'!B61 -> random growth | C60: ='Growth profile'!C61 -> 4 | D60: ='Growth profile'!D61 -> 1 | E60: ='Growth profile'!E61 -> 18.90696 | F60: ='Growth profile'!H61 -> 0.0122 | G60: ='Raw profile'!I61 -> 2029 | H60: ='Growth profile'!I61 -> 2026 | I60: =H60-G60 -> -3 | J60: ='Raw profile'!O61 -> 15.688001 | K60: ='Growth profile'!O61 -> 24.957789 | L60: =MIN('Growth profile'!L61,2085) -> 2081 | M60: ='Growth profile'!N61 -> 0 | N60: =IF(F60<0,"shrinking",IF(F60<0.015,"under 1.5%",IF(F60<0.018,"1.5% to 1.8%","1.8% and over"))) -> under 1.5% | O60: =IF(I60>0,IF(L60=2085,"Deferred - pinned to horizon end","Deferred"),IF(I60<0,"Accelerated","Unchanged")) -> Accelerated | P60: ='Growth (no penalty)'!I61 -> 2026 | Q60: =P60-G60 -> -3
A61: ='Growth profile'!A67 -> project 91 | B61: ='Growth profile'!B67 -> random growth | C61: ='Growth profile'!C67 -> 3 | D61: ='Growth profile'!D67 -> 1.49 | E61: ='Growth profile'!E67 -> 10.200193 | F61: ='Growth profile'!H67 -> 0.02 | G61: ='Raw profile'!I67 -> 2035 | H61: ='Growth profile'!I67 -> 2032 | I61: =H61-G61 -> -3 | J61: ='Raw profile'!O67 -> 12.328013 | K61: ='Growth profile'!O67 -> 22.849843 | L61: =MIN('Growth profile'!L67,2085) -> 2075 | M61: ='Growth profile'!N67 -> 0 | N61: =IF(F61<0,"shrinking",IF(F61<0.015,"under 1.5%",IF(F61<0.018,"1.5% to 1.8%","1.8% and over"))) -> 1.8% and over | O61: =IF(I61>0,IF(L61=2085,"Deferred - pinned to horizon end","Deferred"),IF(I61<0,"Accelerated","Unchanged")) -> Accelerated | P61: ='Growth (no penalty)'!I67 -> 2042 | Q61: =P61-G61 -> 7
A62: ='Growth profile'!A69 -> project 98 | B62: ='Growth profile'!B69 -> random growth | C62: ='Growth profile'!C69 -> 4 | D62: ='Growth profile'!D69 -> 1.17 | E62: ='Growth profile'!E69 -> 32.593137 | F62: ='Growth profile'!H69 -> 0.0283 | G62: ='Raw profile'!I69 -> 2041 | H62: ='Growth profile'!I69 -> 2038 | I62: =H62-G62 -> -3 | J62: ='Raw profile'!O69 -> 29.113879 | K62: ='Growth profile'!O69 -> 75.112188 | L62: =MIN('Growth profile'!L69,2085) -> 2078 | M62: ='Growth profile'!N69 -> 0 | N62: =IF(F62<0,"shrinking",IF(F62<0.015,"under 1.5%",IF(F62<0.018,"1.5% to 1.8%","1.8% and over"))) -> 1.8% and over | O62: =IF(I62>0,IF(L62=2085,"Deferred - pinned to horizon end","Deferred"),IF(I62<0,"Accelerated","Unchanged")) -> Accelerated | P62: ='Growth (no penalty)'!I69 -> 2045 | Q62: =P62-G62 -> 4
A63: ='Growth profile'!A87 -> project 133 | B63: ='Growth profile'!B87 -> random growth | C63: ='Growth profile'!C87 -> 5 | D63: ='Growth profile'!D87 -> 1.16 | E63: ='Growth profile'!E87 -> 60.444938 | F63: ='Growth profile'!H87 -> 0.0276 | G63: ='Raw profile'!I87 -> 2037 | H63: ='Growth profile'!I87 -> 2033 | I63: =H63-G63 -> -4 | J63: ='Raw profile'!O87 -> 52.964489 | K63: ='Growth profile'!O87 -> 139.57763 | L63: =MIN('Growth profile'!L87,2085) -> 2079 | M63: ='Growth profile'!N87 -> 0 | N63: =IF(F63<0,"shrinking",IF(F63<0.015,"under 1.5%",IF(F63<0.018,"1.5% to 1.8%","1.8% and over"))) -> 1.8% and over | O63: =IF(I63>0,IF(L63=2085,"Deferred - pinned to horizon end","Deferred"),IF(I63<0,"Accelerated","Unchanged")) -> Accelerated | P63: ='Growth (no penalty)'!I87 -> 2039 | Q63: =P63-G63 -> 2
A64: ='Growth profile'!A50 -> project 47 | B64: ='Growth profile'!B50 -> random growth | C64: ='Growth profile'!C50 -> 2 | D64: ='Growth profile'!D50 -> 1.58 | E64: ='Growth profile'!E50 -> 2.8349571 | F64: ='Growth profile'!H50 -> 0.0176 | G64: ='Raw profile'!I50 -> 2037 | H64: ='Growth profile'!I50 -> 2033 | I64: =H64-G64 -> -4 | J64: ='Raw profile'!O50 -> 3.640694 | K64: ='Growth profile'!O50 -> 6.2927346 | L64: =MIN('Growth profile'!L50,2085) -> 2074 | M64: ='Growth profile'!N50 -> 0 | N64: =IF(F64<0,"shrinking",IF(F64<0.015,"under 1.5%",IF(F64<0.018,"1.5% to 1.8%","1.8% and over"))) -> 1.5% to 1.8% | O64: =IF(I64>0,IF(L64=2085,"Deferred - pinned to horizon end","Deferred"),IF(I64<0,"Accelerated","Unchanged")) -> Accelerated | P64: ='Growth (no penalty)'!I50 -> 2044 | Q64: =P64-G64 -> 7
A65: ='Growth profile'!A27 -> project 8 | B65: ='Growth profile'!B27 -> random growth | C65: ='Growth profile'!C27 -> 3 | D65: ='Growth profile'!D27 -> 1 | E65: ='Growth profile'!E27 -> 5.45 | F65: ='Growth profile'!H27 -> 0.0275 | G65: ='Raw profile'!I27 -> 2041 | H65: ='Growth profile'!I27 -> 2037 | I65: =H65-G65 -> -4 | J65: ='Raw profile'!O27 -> 4.1608738 | K65: ='Growth profile'!O27 -> 10.34822 | L65: =MIN('Growth profile'!L27,2085) -> 2077 | M65: ='Growth profile'!N27 -> 0 | N65: =IF(F65<0,"shrinking",IF(F65<0.015,"under 1.5%",IF(F65<0.018,"1.5% to 1.8%","1.8% and over"))) -> 1.8% and over | O65: =IF(I65>0,IF(L65=2085,"Deferred - pinned to horizon end","Deferred"),IF(I65<0,"Accelerated","Unchanged")) -> Accelerated | P65: ='Growth (no penalty)'!I27 -> 2045 | Q65: =P65-G65 -> 4
A66: ='Growth profile'!A66 -> project 90 | B66: ='Growth profile'!B66 -> random growth | C66: ='Growth profile'!C66 -> 4 | D66: ='Growth profile'!D66 -> 1.97 | E66: ='Growth profile'!E66 -> 16.347102 | F66: ='Growth profile'!H66 -> 0.0153 | G66: ='Raw profile'!I66 -> 2030 | H66: ='Growth profile'!I66 -> 2026 | I66: =H66-G66 -> -4 | J66: ='Raw profile'!O66 -> 29.209299 | K66: ='Growth profile'!O66 -> 43.263339 | L66: =MIN('Growth profile'!L66,2085) -> 2068 | M66: ='Growth profile'!N66 -> 0 | N66: =IF(F66<0,"shrinking",IF(F66<0.015,"under 1.5%",IF(F66<0.018,"1.5% to 1.8%","1.8% and over"))) -> 1.5% to 1.8% | O66: =IF(I66>0,IF(L66=2085,"Deferred - pinned to horizon end","Deferred"),IF(I66<0,"Accelerated","Unchanged")) -> Accelerated | P66: ='Growth (no penalty)'!I66 -> 2026 | Q66: =P66-G66 -> -4
A67: ='Growth profile'!A88 -> project 135 | B67: ='Growth profile'!B88 -> random growth | C67: ='Growth profile'!C88 -> 4 | D67: ='Growth profile'!D88 -> 1.18 | E67: ='Growth profile'!E88 -> 41.607442 | F67: ='Growth profile'!H88 -> 0.0289 | G67: ='Raw profile'!I88 -> 2039 | H67: ='Growth profile'!I88 -> 2034 | I67: =H67-G67 -> -5 | J67: ='Raw profile'!O88 -> 37.32793 | K67: ='Growth profile'!O88 -> 104.55393 | L67: =MIN('Growth profile'!L88,2085) -> 2079 | M67: ='Growth profile'!N88 -> 0 | N67: =IF(F67<0,"shrinking",IF(F67<0.015,"under 1.5%",IF(F67<0.018,"1.5% to 1.8%","1.8% and over"))) -> 1.8% and over | O67: =IF(I67>0,IF(L67=2085,"Deferred - pinned to horizon end","Deferred"),IF(I67<0,"Accelerated","Unchanged")) -> Accelerated | P67: ='Growth (no penalty)'!I88 -> 2040 | Q67: =P67-G67 -> 1
A68: ='Growth profile'!A105 -> project 168 | B68: ='Growth profile'!B105 -> random growth | C68: ='Growth profile'!C105 -> 3 | D68: ='Growth profile'!D105 -> 1.33 | E68: ='Growth profile'!E105 -> 8.2256237 | F68: ='Growth profile'!H105 -> 0.0299 | G68: ='Raw profile'!I105 -> 2040 | H68: ='Growth profile'!I105 -> 2035 | I68: =H68-G68 -> -5 | J68: ='Raw profile'!O105 -> 8.1646321 | K68: ='Growth profile'!O105 -> 23.663068 | L68: =MIN('Growth profile'!L105,2085) -> 2079 | M68: ='Growth profile'!N105 -> 0 | N68: =IF(F68<0,"shrinking",IF(F68<0.015,"under 1.5%",IF(F68<0.018,"1.5% to 1.8%","1.8% and over"))) -> 1.8% and over | O68: =IF(I68>0,IF(L68=2085,"Deferred - pinned to horizon end","Deferred"),IF(I68<0,"Accelerated","Unchanged")) -> Accelerated | P68: ='Growth (no penalty)'!I105 -> 2041 | Q68: =P68-G68 -> 1
A69: ='Growth profile'!A106 -> project 171 | B69: ='Growth profile'!B106 -> random growth | C69: ='Growth profile'!C106 -> 3 | D69: ='Growth profile'!D106 -> 1.43 | E69: ='Growth profile'!E106 -> 6.3080873 | F69: ='Growth profile'!H106 -> 0.023 | G69: ='Raw profile'!I106 -> 2039 | H69: ='Growth profile'!I106 -> 2033 | I69: =H69-G69 -> -6 | J69: ='Raw profile'!O106 -> 6.8955719 | K69: ='Growth profile'!O106 -> 14.700529 | L69: =MIN('Growth profile'!L106,2085) -> 2075 | M69: ='Growth profile'!N106 -> 0 | N69: =IF(F69<0,"shrinking",IF(F69<0.015,"under 1.5%",IF(F69<0.018,"1.5% to 1.8%","1.8% and over"))) -> 1.8% and over | O69: =IF(I69>0,IF(L69=2085,"Deferred - pinned to horizon end","Deferred"),IF(I69<0,"Accelerated","Unchanged")) -> Accelerated | P69: ='Growth (no penalty)'!I106 -> 2043 | Q69: =P69-G69 -> 4
A70: ='Growth profile'!A57 -> project 58 | B70: ='Growth profile'!B57 -> random growth | C70: ='Growth profile'!C57 -> 2 | D70: ='Growth profile'!D57 -> 1.19 | E70: ='Growth profile'!E57 -> 4.2647691 | F70: ='Growth profile'!H57 -> 0.0236 | G70: ='Raw profile'!I57 -> 2039 | H70: ='Growth profile'!I57 -> 2033 | I70: =H70-G70 -> -6 | J70: ='Raw profile'!O57 -> 3.8853769 | K70: ='Growth profile'!O57 -> 8.6286084 | L70: =MIN('Growth profile'!L57,2085) -> 2076 | M70: ='Growth profile'!N57 -> 0 | N70: =IF(F70<0,"shrinking",IF(F70<0.015,"under 1.5%",IF(F70<0.018,"1.5% to 1.8%","1.8% and over"))) -> 1.8% and over | O70: =IF(I70>0,IF(L70=2085,"Deferred - pinned to horizon end","Deferred"),IF(I70<0,"Accelerated","Unchanged")) -> Accelerated | P70: ='Growth (no penalty)'!I57 -> 2042 | Q70: =P70-G70 -> 3
A71: ='Growth profile'!A58 -> project 61 | B71: ='Growth profile'!B58 -> random growth | C71: ='Growth profile'!C58 -> 3 | D71: ='Growth profile'!D58 -> 1.03 | E71: ='Growth profile'!E58 -> 8.698992 | F71: ='Growth profile'!H58 -> 0.0207 | G71: ='Raw profile'!I58 -> 2041 | H71: ='Growth profile'!I58 -> 2035 | I71: =H71-G71 -> -6 | J71: ='Raw profile'!O58 -> 6.8406 | K71: ='Growth profile'!O58 -> 13.629177 | L71: =MIN('Growth profile'!L58,2085) -> 2075 | M71: ='Growth profile'!N58 -> 0 | N71: =IF(F71<0,"shrinking",IF(F71<0.015,"under 1.5%",IF(F71<0.018,"1.5% to 1.8%","1.8% and over"))) -> 1.8% and over | O71: =IF(I71>0,IF(L71=2085,"Deferred - pinned to horizon end","Deferred"),IF(I71<0,"Accelerated","Unchanged")) -> Accelerated | P71: ='Growth (no penalty)'!I58 -> 2045 | Q71: =P71-G71 -> 4
A72: ='Growth profile'!A93 -> project 146 | B72: ='Growth profile'!B93 -> random growth | C72: ='Growth profile'!C93 -> 4 | D72: ='Growth profile'!D93 -> 1 | E72: ='Growth profile'!E93 -> 30.370387 | F72: ='Growth profile'!H93 -> 0.0253 | G72: ='Raw profile'!I93 -> 2039 | H72: ='Growth profile'!I93 -> 2032 | I72: =H72-G72 -> -7 | J72: ='Raw profile'!O93 -> 22.562572 | K72: ='Growth profile'!O93 -> 55.027559 | L72: =MIN('Growth profile'!L93,2085) -> 2077 | M72: ='Growth profile'!N93 -> 0 | N72: =IF(F72<0,"shrinking",IF(F72<0.015,"under 1.5%",IF(F72<0.018,"1.5% to 1.8%","1.8% and over"))) -> 1.8% and over | O72: =IF(I72>0,IF(L72=2085,"Deferred - pinned to horizon end","Deferred"),IF(I72<0,"Accelerated","Unchanged")) -> Accelerated | P72: ='Growth (no penalty)'!I93 -> 2040 | Q72: =P72-G72 -> 1
A73: ='Growth profile'!A107 -> project 175 | B73: ='Growth profile'!B107 -> random growth | C73: ='Growth profile'!C107 -> 3 | D73: ='Growth profile'!D107 -> 1.48 | E73: ='Growth profile'!E107 -> 5.6237161 | F73: ='Growth profile'!H107 -> 0.0188 | G73: ='Raw profile'!I107 -> 2039 | H73: ='Growth profile'!I107 -> 2032 | I73: =H73-G73 -> -7 | J73: ='Raw profile'!O107 -> 6.3305221 | K73: ='Growth profile'!O107 -> 12.13647 | L73: =MIN('Growth profile'!L107,2085) -> 2075 | M73: ='Growth profile'!N107 -> 0 | N73: =IF(F73<0,"shrinking",IF(F73<0.015,"under 1.5%",IF(F73<0.018,"1.5% to 1.8%","1.8% and over"))) -> 1.8% and over | O73: =IF(I73>0,IF(L73=2085,"Deferred - pinned to horizon end","Deferred"),IF(I73<0,"Accelerated","Unchanged")) -> Accelerated | P73: ='Growth (no penalty)'!I107 -> 2042 | Q73: =P73-G73 -> 3
A74: ='Growth profile'!A116 -> project 192 | B74: ='Growth profile'!B116 -> random growth | C74: ='Growth profile'!C116 -> 2 | D74: ='Growth profile'!D116 -> 1 | E74: ='Growth profile'!E116 -> 1.2762487 | F74: ='Growth profile'!H116 -> 0.0226 | G74: ='Raw profile'!I116 -> 2042 | H74: ='Growth profile'!I116 -> 2035 | I74: =H74-G74 -> -7 | J74: ='Raw profile'!O116 -> 0.95890634 | K74: ='Growth profile'!O116 -> 2.1005709 | L74: =MIN('Growth profile'!L116,2085) -> 2076 | M74: ='Growth profile'!N116 -> 0 | N74: =IF(F74<0,"shrinking",IF(F74<0.015,"under 1.5%",IF(F74<0.018,"1.5% to 1.8%","1.8% and over"))) -> 1.8% and over | O74: =IF(I74>0,IF(L74=2085,"Deferred - pinned to horizon end","Deferred"),IF(I74<0,"Accelerated","Unchanged")) -> Accelerated | P74: ='Growth (no penalty)'!I116 -> 2044 | Q74: =P74-G74 -> 2
A75: ='Growth profile'!A60 -> project 74 | B75: ='Growth profile'!B60 -> random growth | C75: ='Growth profile'!C60 -> 5 | D75: ='Growth profile'!D60 -> 1.01 | E75: ='Growth profile'!E60 -> 52.287063 | F75: ='Growth profile'!H60 -> 0.0228 | G75: ='Raw profile'!I60 -> 2040 | H75: ='Growth profile'!I60 -> 2033 | I75: =H75-G75 -> -7 | J75: ='Raw profile'!O60 -> 39.877044 | K75: ='Growth profile'!O60 -> 89.858909 | L75: =MIN('Growth profile'!L60,2085) -> 2077 | M75: ='Growth profile'!N60 -> 0 | N75: =IF(F75<0,"shrinking",IF(F75<0.015,"under 1.5%",IF(F75<0.018,"1.5% to 1.8%","1.8% and over"))) -> 1.8% and over | O75: =IF(I75>0,IF(L75=2085,"Deferred - pinned to horizon end","Deferred"),IF(I75<0,"Accelerated","Unchanged")) -> Accelerated | P75: ='Growth (no penalty)'!I60 -> 2041 | Q75: =P75-G75 -> 1
A76: ='Growth profile'!A72 -> project 103 | B76: ='Growth profile'!B72 -> random growth | C76: ='Growth profile'!C72 -> 2 | D76: ='Growth profile'!D72 -> 1 | E76: ='Growth profile'!E72 -> 4.0982569 | F76: ='Growth profile'!H72 -> 0.0228 | G76: ='Raw profile'!I72 -> 2041 | H76: ='Growth profile'!I72 -> 2033 | I76: =H76-G76 -> -8 | J76: ='Raw profile'!O72 -> 3.0369222 | K76: ='Growth profile'!O72 -> 6.6578065 | L76: =MIN('Growth profile'!L72,2085) -> 2075 | M76: ='Growth profile'!N72 -> 0 | N76: =IF(F76<0,"shrinking",IF(F76<0.015,"under 1.5%",IF(F76<0.018,"1.5% to 1.8%","1.8% and over"))) -> 1.8% and over | O76: =IF(I76>0,IF(L76=2085,"Deferred - pinned to horizon end","Deferred"),IF(I76<0,"Accelerated","Unchanged")) -> Accelerated | P76: ='Growth (no penalty)'!I72 -> 2043 | Q76: =P76-G76 -> 2
A77: ='Growth profile'!A73 -> project 104 | B77: ='Growth profile'!B73 -> random growth | C77: ='Growth profile'!C73 -> 2 | D77: ='Growth profile'!D73 -> 1 | E77: ='Growth profile'!E73 -> 1.4307451 | F77: ='Growth profile'!H73 -> 0.0222 | G77: ='Raw profile'!I73 -> 2042 | H77: ='Growth profile'!I73 -> 2034 | I77: =H77-G77 -> -8 | J77: ='Raw profile'!O73 -> 1.0577576 | K77: ='Growth profile'!O73 -> 2.3276201 | L77: =MIN('Growth profile'!L73,2085) -> 2076 | M77: ='Growth profile'!N73 -> 0 | N77: =IF(F77<0,"shrinking",IF(F77<0.015,"under 1.5%",IF(F77<0.018,"1.5% to 1.8%","1.8% and over"))) -> 1.8% and over | O77: =IF(I77>0,IF(L77=2085,"Deferred - pinned to horizon end","Deferred"),IF(I77<0,"Accelerated","Unchanged")) -> Accelerated | P77: ='Growth (no penalty)'!I73 -> 2043 | Q77: =P77-G77 -> 1
A78: ='Growth profile'!A80 -> project 119 | B78: ='Growth profile'!B80 -> random growth | C78: ='Growth profile'!C80 -> 5 | D78: ='Growth profile'!D80 -> 1.72 | E78: ='Growth profile'!E80 -> 136.4087 | F78: ='Growth profile'!H80 -> 0.0165 | G78: ='Raw profile'!I80 -> 2037 | H78: ='Growth profile'!I80 -> 2029 | I78: =H78-G78 -> -8 | J78: ='Raw profile'!O80 -> 181.83362 | K78: ='Growth profile'!O80 -> 326.47839 | L78: =MIN('Growth profile'!L80,2085) -> 2074 | M78: ='Growth profile'!N80 -> 0 | N78: =IF(F78<0,"shrinking",IF(F78<0.015,"under 1.5%",IF(F78<0.018,"1.5% to 1.8%","1.8% and over"))) -> 1.5% to 1.8% | O78: =IF(I78>0,IF(L78=2085,"Deferred - pinned to horizon end","Deferred"),IF(I78<0,"Accelerated","Unchanged")) -> Accelerated | P78: ='Growth (no penalty)'!I80 -> 2028 | Q78: =P78-G78 -> -9
A79: ='Growth profile'!A90 -> project 142 | B79: ='Growth profile'!B90 -> random growth | C79: ='Growth profile'!C90 -> 4 | D79: ='Growth profile'!D90 -> 1 | E79: ='Growth profile'!E90 -> 37.825933 | F79: ='Growth profile'!H90 -> 0.0197 | G79: ='Raw profile'!I90 -> 2041 | H79: ='Growth profile'!I90 -> 2033 | I79: =H79-G79 -> -8 | J79: ='Raw profile'!O90 -> 28.177893 | K79: ='Growth profile'!O90 -> 56.399891 | L79: =MIN('Growth profile'!L90,2085) -> 2075 | M79: ='Growth profile'!N90 -> 0 | N79: =IF(F79<0,"shrinking",IF(F79<0.015,"under 1.5%",IF(F79<0.018,"1.5% to 1.8%","1.8% and over"))) -> 1.8% and over | O79: =IF(I79>0,IF(L79=2085,"Deferred - pinned to horizon end","Deferred"),IF(I79<0,"Accelerated","Unchanged")) -> Accelerated | P79: ='Growth (no penalty)'!I90 -> 2043 | Q79: =P79-G79 -> 2
A80: ='Growth profile'!A92 -> project 145 | B80: ='Growth profile'!B92 -> random growth | C80: ='Growth profile'!C92 -> 4 | D80: ='Growth profile'!D92 -> 1 | E80: ='Growth profile'!E92 -> 27.535001 | F80: ='Growth profile'!H92 -> 0.0252 | G80: ='Raw profile'!I92 -> 2039 | H80: ='Growth profile'!I92 -> 2031 | I80: =H80-G80 -> -8 | J80: ='Raw profile'!O92 -> 20.373805 | K80: ='Growth profile'!O92 -> 47.957673 | L80: =MIN('Growth profile'!L92,2085) -> 2075 | M80: ='Growth profile'!N92 -> 0 | N80: =IF(F80<0,"shrinking",IF(F80<0.015,"under 1.5%",IF(F80<0.018,"1.5% to 1.8%","1.8% and over"))) -> 1.8% and over | O80: =IF(I80>0,IF(L80=2085,"Deferred - pinned to horizon end","Deferred"),IF(I80<0,"Accelerated","Unchanged")) -> Accelerated | P80: ='Growth (no penalty)'!I92 -> 2041 | Q80: =P80-G80 -> 2
A81: ='Growth profile'!A120 -> project 204 | B81: ='Growth profile'!B120 -> random growth | C81: ='Growth profile'!C120 -> 1 | D81: ='Growth profile'!D120 -> 1 | E81: ='Growth profile'!E120 -> 0.35637154 | F81: ='Growth profile'!H120 -> 0.0114 | G81: ='Raw profile'!I120 -> 2040 | H81: ='Growth profile'!I120 -> 2032 | I81: =H81-G81 -> -8 | J81: ='Raw profile'!O120 -> 0.27039977 | K81: ='Growth profile'!O120 -> 0.42173568 | L81: =MIN('Growth profile'!L120,2085) -> 2074 | M81: ='Growth profile'!N120 -> 0 | N81: =IF(F81<0,"shrinking",IF(F81<0.015,"under 1.5%",IF(F81<0.018,"1.5% to 1.8%","1.8% and over"))) -> under 1.5% | O81: =IF(I81>0,IF(L81=2085,"Deferred - pinned to horizon end","Deferred"),IF(I81<0,"Accelerated","Unchanged")) -> Accelerated | P81: ='Growth (no penalty)'!I120 -> 2027 | Q81: =P81-G81 -> -13
A82: ='Growth profile'!A86 -> project 130 | B82: ='Growth profile'!B86 -> random growth | C82: ='Growth profile'!C86 -> 5 | D82: ='Growth profile'!D86 -> 1.53 | E82: ='Growth profile'!E86 -> 70.521534 | F82: ='Growth profile'!H86 -> 0.0112 | G82: ='Raw profile'!I86 -> 2035 | H82: ='Growth profile'!I86 -> 2026 | I82: =H82-G82 -> -9 | J82: ='Raw profile'!O86 -> 83.027609 | K82: ='Growth profile'!O86 -> 129.64438 | L82: =MIN('Growth profile'!L86,2085) -> 2073 | M82: ='Growth profile'!N86 -> 0 | N82: =IF(F82<0,"shrinking",IF(F82<0.015,"under 1.5%",IF(F82<0.018,"1.5% to 1.8%","1.8% and over"))) -> under 1.5% | O82: =IF(I82>0,IF(L82=2085,"Deferred - pinned to horizon end","Deferred"),IF(I82<0,"Accelerated","Unchanged")) -> Accelerated | P82: ='Growth (no penalty)'!I86 -> 2026 | Q82: =P82-G82 -> -9
A83: ='Growth profile'!A108 -> project 176 | B83: ='Growth profile'!B108 -> random growth | C83: ='Growth profile'!C108 -> 3 | D83: ='Growth profile'!D108 -> 1 | E83: ='Growth profile'!E108 -> 5.254902 | F83: ='Growth profile'!H108 -> 0.0204 | G83: ='Raw profile'!I108 -> 2043 | H83: ='Growth profile'!I108 -> 2034 | I83: =H83-G83 -> -9 | J83: ='Raw profile'!O108 -> 3.8537686 | K83: ='Growth profile'!O108 -> 8.0057794 | L83: =MIN('Growth profile'!L108,2085) -> 2075 | M83: ='Growth profile'!N108 -> 0 | N83: =IF(F83<0,"shrinking",IF(F83<0.015,"under 1.5%",IF(F83<0.018,"1.5% to 1.8%","1.8% and over"))) -> 1.8% and over | O83: =IF(I83>0,IF(L83=2085,"Deferred - pinned to horizon end","Deferred"),IF(I83<0,"Accelerated","Unchanged")) -> Accelerated | P83: ='Growth (no penalty)'!I108 -> 2044 | Q83: =P83-G83 -> 1
A84: ='Growth profile'!A111 -> project 182 | B84: ='Growth profile'!B111 -> random growth | C84: ='Growth profile'!C111 -> 2 | D84: ='Growth profile'!D111 -> 1 | E84: ='Growth profile'!E111 -> 3.3626563 | F84: ='Growth profile'!H111 -> 0.0168 | G84: ='Raw profile'!I111 -> 2039 | H84: ='Growth profile'!I111 -> 2030 | I84: =H84-G84 -> -9 | J84: ='Raw profile'!O111 -> 2.5311313 | K84: ='Growth profile'!O111 -> 4.7353029 | L84: =MIN('Growth profile'!L111,2085) -> 2075 | M84: ='Growth profile'!N111 -> 0 | N84: =IF(F84<0,"shrinking",IF(F84<0.015,"under 1.5%",IF(F84<0.018,"1.5% to 1.8%","1.8% and over"))) -> 1.5% to 1.8% | O84: =IF(I84>0,IF(L84=2085,"Deferred - pinned to horizon end","Deferred"),IF(I84<0,"Accelerated","Unchanged")) -> Accelerated | P84: ='Growth (no penalty)'!I111 -> 2031 | Q84: =P84-G84 -> -8
A85: ='Growth profile'!A85 -> project 128 | B85: ='Growth profile'!B85 -> random growth | C85: ='Growth profile'!C85 -> 5 | D85: ='Growth profile'!D85 -> 1 | E85: ='Growth profile'!E85 -> 74.022864 | F85: ='Growth profile'!H85 -> 0.0162 | G85: ='Raw profile'!I85 -> 2039 | H85: ='Growth profile'!I85 -> 2029 | I85: =H85-G85 -> -10 | J85: ='Raw profile'!O85 -> 54.99382 | K85: ='Growth profile'!O85 -> 99.738214 | L85: =MIN('Growth profile'!L85,2085) -> 2073 | M85: ='Growth profile'!N85 -> 0 | N85: =IF(F85<0,"shrinking",IF(F85<0.015,"under 1.5%",IF(F85<0.018,"1.5% to 1.8%","1.8% and over"))) -> 1.5% to 1.8% | O85: =IF(I85>0,IF(L85=2085,"Deferred - pinned to horizon end","Deferred"),IF(I85<0,"Accelerated","Unchanged")) -> Accelerated | P85: ='Growth (no penalty)'!I85 -> 2028 | Q85: =P85-G85 -> -11
A86: ='Growth profile'!A43 -> project 38 | B86: ='Growth profile'!B43 -> random growth | C86: ='Growth profile'!C43 -> 5 | D86: ='Growth profile'!D43 -> 1.95 | E86: ='Growth profile'!E43 -> 81.978949 | F86: ='Growth profile'!H43 -> 0.0118 | G86: ='Raw profile'!I43 -> 2036 | H86: ='Growth profile'!I43 -> 2026 | I86: =H86-G86 -> -10 | J86: ='Raw profile'!O43 -> 129.14717 | K86: ='Growth profile'!O43 -> 199.58505 | L86: =MIN('Growth profile'!L43,2085) -> 2069 | M86: ='Growth profile'!N43 -> 0 | N86: =IF(F86<0,"shrinking",IF(F86<0.015,"under 1.5%",IF(F86<0.018,"1.5% to 1.8%","1.8% and over"))) -> under 1.5% | O86: =IF(I86>0,IF(L86=2085,"Deferred - pinned to horizon end","Deferred"),IF(I86<0,"Accelerated","Unchanged")) -> Accelerated | P86: ='Growth (no penalty)'!I43 -> 2026 | Q86: =P86-G86 -> -10
A87: ='Growth profile'!A71 -> project 101 | B87: ='Growth profile'!B71 -> random growth | C87: ='Growth profile'!C71 -> 4 | D87: ='Growth profile'!D71 -> 1 | E87: ='Growth profile'!E71 -> 14.980998 | F87: ='Growth profile'!H71 -> 0.016 | G87: ='Raw profile'!I71 -> 2041 | H87: ='Growth profile'!I71 -> 2030 | I87: =H87-G87 -> -11 | J87: ='Raw profile'!O71 -> 11.186167 | K87: ='Growth profile'!O71 -> 20.217064 | L87: =MIN('Growth profile'!L71,2085) -> 2072 | M87: ='Growth profile'!N71 -> 0 | N87: =IF(F87<0,"shrinking",IF(F87<0.015,"under 1.5%",IF(F87<0.018,"1.5% to 1.8%","1.8% and over"))) -> 1.5% to 1.8% | O87: =IF(I87>0,IF(L87=2085,"Deferred - pinned to horizon end","Deferred"),IF(I87<0,"Accelerated","Unchanged")) -> Accelerated | P87: ='Growth (no penalty)'!I71 -> 2028 | Q87: =P87-G87 -> -13
A88: ='Growth profile'!A30 -> project 16 | B88: ='Growth profile'!B30 -> random growth | C88: ='Growth profile'!C30 -> 2 | D88: ='Growth profile'!D30 -> 1.49 | E88: ='Growth profile'!E30 -> 2.4198 | F88: ='Growth profile'!H30 -> 0.0179 | G88: ='Raw profile'!I30 -> 2037 | H88: ='Growth profile'!I30 -> 2026 | I88: =H88-G88 -> -11 | J88: ='Raw profile'!O30 -> 2.9501884 | K88: ='Growth profile'!O30 -> 5.0644933 | L88: =MIN('Growth profile'!L30,2085) -> 2066 | M88: ='Growth profile'!N30 -> 0 | N88: =IF(F88<0,"shrinking",IF(F88<0.015,"under 1.5%",IF(F88<0.018,"1.5% to 1.8%","1.8% and over"))) -> 1.5% to 1.8% | O88: =IF(I88>0,IF(L88=2085,"Deferred - pinned to horizon end","Deferred"),IF(I88<0,"Accelerated","Unchanged")) -> Accelerated | P88: ='Growth (no penalty)'!I30 -> 2045 | Q88: =P88-G88 -> 8
A89: ='Growth profile'!A104 -> project 167 | B89: ='Growth profile'!B104 -> random growth | C89: ='Growth profile'!C104 -> 3 | D89: ='Growth profile'!D104 -> 1 | E89: ='Growth profile'!E104 -> 12.409649 | F89: ='Growth profile'!H104 -> 0.0162 | G89: ='Raw profile'!I104 -> 2041 | H89: ='Growth profile'!I104 -> 2030 | I89: =H89-G89 -> -11 | J89: ='Raw profile'!O104 -> 9.1762163 | K89: ='Growth profile'!O104 -> 16.922738 | L89: =MIN('Growth profile'!L104,2085) -> 2073 | M89: ='Growth profile'!N104 -> 0 | N89: =IF(F89<0,"shrinking",IF(F89<0.015,"under 1.5%",IF(F89<0.018,"1.5% to 1.8%","1.8% and over"))) -> 1.5% to 1.8% | O89: =IF(I89>0,IF(L89=2085,"Deferred - pinned to horizon end","Deferred"),IF(I89<0,"Accelerated","Unchanged")) -> Accelerated | P89: ='Growth (no penalty)'!I104 -> 2031 | Q89: =P89-G89 -> -10
A90: ='Growth profile'!A113 -> project 186 | B90: ='Growth profile'!B113 -> random growth | C90: ='Growth profile'!C113 -> 2 | D90: ='Growth profile'!D113 -> 1 | E90: ='Growth profile'!E113 -> 1.7251179 | F90: ='Growth profile'!H113 -> 0.0146 | G90: ='Raw profile'!I113 -> 2042 | H90: ='Growth profile'!I113 -> 2031 | I90: =H90-G90 -> -11 | J90: ='Raw profile'!O113 -> 1.2747097 | K90: ='Growth profile'!O113 -> 2.252328 | L90: =MIN('Growth profile'!L113,2085) -> 2073 | M90: ='Growth profile'!N113 -> 0 | N90: =IF(F90<0,"shrinking",IF(F90<0.015,"under 1.5%",IF(F90<0.018,"1.5% to 1.8%","1.8% and over"))) -> under 1.5% | O90: =IF(I90>0,IF(L90=2085,"Deferred - pinned to horizon end","Deferred"),IF(I90<0,"Accelerated","Unchanged")) -> Accelerated | P90: ='Growth (no penalty)'!I113 -> 2031 | Q90: =P90-G90 -> -11
A91: ='Growth profile'!A115 -> project 190 | B91: ='Growth profile'!B115 -> random growth | C91: ='Growth profile'!C115 -> 1 | D91: ='Growth profile'!D115 -> 1.32 | E91: ='Growth profile'!E115 -> 1.204376 | F91: ='Growth profile'!H115 -> 0.0114 | G91: ='Raw profile'!I115 -> 2037 | H91: ='Growth profile'!I115 -> 2026 | I91: =H91-G91 -> -11 | J91: ='Raw profile'!O115 -> 1.3008285 | K91: ='Growth profile'!O115 -> 1.9657242 | L91: =MIN('Growth profile'!L115,2085) -> 2066 | M91: ='Growth profile'!N115 -> 0 | N91: =IF(F91<0,"shrinking",IF(F91<0.015,"under 1.5%",IF(F91<0.018,"1.5% to 1.8%","1.8% and over"))) -> under 1.5% | O91: =IF(I91>0,IF(L91=2085,"Deferred - pinned to horizon end","Deferred"),IF(I91<0,"Accelerated","Unchanged")) -> Accelerated | P91: ='Growth (no penalty)'!I115 -> 2026 | Q91: =P91-G91 -> -11
A92: ='Growth profile'!A117 -> project 193 | B92: ='Growth profile'!B117 -> random growth | C92: ='Growth profile'!C117 -> 1 | D92: ='Growth profile'!D117 -> 1.47 | E92: ='Growth profile'!E117 -> 1.0588235 | F92: ='Growth profile'!H117 -> 0.0146 | G92: ='Raw profile'!I117 -> 2037 | H92: ='Growth profile'!I117 -> 2026 | I92: =H92-G92 -> -11 | J92: ='Raw profile'!O117 -> 1.2735762 | K92: ='Growth profile'!O117 -> 2.0480437 | L92: =MIN('Growth profile'!L117,2085) -> 2066 | M92: ='Growth profile'!N117 -> 0 | N92: =IF(F92<0,"shrinking",IF(F92<0.015,"under 1.5%",IF(F92<0.018,"1.5% to 1.8%","1.8% and over"))) -> under 1.5% | O92: =IF(I92>0,IF(L92=2085,"Deferred - pinned to horizon end","Deferred"),IF(I92<0,"Accelerated","Unchanged")) -> Accelerated | P92: ='Growth (no penalty)'!I117 -> 2026 | Q92: =P92-G92 -> -11
A93: ='Growth profile'!A34 -> project 23 | B93: ='Growth profile'!B34 -> random growth | C93: ='Growth profile'!C34 -> 1 | D93: ='Growth profile'!D34 -> 1.67 | E93: ='Growth profile'!E34 -> 0.654 | F93: ='Growth profile'!H34 -> 0.0149 | G93: ='Raw profile'!I34 -> 2037 | H93: ='Growth profile'!I34 -> 2026 | I93: =H93-G93 -> -11 | J93: ='Raw profile'!O34 -> 0.89367216 | K93: ='Growth profile'!O34 -> 1.4456068 | L93: =MIN('Growth profile'!L34,2085) -> 2066 | M93: ='Growth profile'!N34 -> 0 | N93: =IF(F93<0,"shrinking",IF(F93<0.015,"under 1.5%",IF(F93<0.018,"1.5% to 1.8%","1.8% and over"))) -> under 1.5% | O93: =IF(I93>0,IF(L93=2085,"Deferred - pinned to horizon end","Deferred"),IF(I93<0,"Accelerated","Unchanged")) -> Accelerated | P93: ='Growth (no penalty)'!I34 -> 2026 | Q93: =P93-G93 -> -11
A94: ='Growth profile'!A55 -> project 55 | B94: ='Growth profile'!B55 -> random growth | C94: ='Growth profile'!C55 -> 4 | D94: ='Growth profile'!D55 -> 1.85 | E94: ='Growth profile'!E55 -> 25.841057 | F94: ='Growth profile'!H55 -> 0.0102 | G94: ='Raw profile'!I55 -> 2037 | H94: ='Growth profile'!I55 -> 2026 | I94: =H94-G94 -> -11 | J94: ='Raw profile'!O55 -> 38.811127 | K94: ='Growth profile'!O55 -> 57.83501 | L94: =MIN('Growth profile'!L55,2085) -> 2067 | M94: ='Growth profile'!N55 -> 0 | N94: =IF(F94<0,"shrinking",IF(F94<0.015,"under 1.5%",IF(F94<0.018,"1.5% to 1.8%","1.8% and over"))) -> under 1.5% | O94: =IF(I94>0,IF(L94=2085,"Deferred - pinned to horizon end","Deferred"),IF(I94<0,"Accelerated","Unchanged")) -> Accelerated | P94: ='Growth (no penalty)'!I55 -> 2026 | Q94: =P94-G94 -> -11
A95: ='Growth profile'!A123 -> project 218 | B95: ='Growth profile'!B123 -> random growth | C95: ='Growth profile'!C123 -> 3 | D95: ='Growth profile'!D123 -> 1 | E95: ='Growth profile'!E123 -> 9.0115146 | F95: ='Growth profile'!H123 -> 0.0143 | G95: ='Raw profile'!I123 -> 2041 | H95: ='Growth profile'!I123 -> 2029 | I95: =H95-G95 -> -12 | J95: ='Raw profile'!O123 -> 6.7123903 | K95: ='Growth profile'!O123 -> 11.655937 | L95: =MIN('Growth profile'!L123,2085) -> 2071 | M95: ='Growth profile'!N123 -> 0 | N95: =IF(F95<0,"shrinking",IF(F95<0.015,"under 1.5%",IF(F95<0.018,"1.5% to 1.8%","1.8% and over"))) -> under 1.5% | O95: =IF(I95>0,IF(L95=2085,"Deferred - pinned to horizon end","Deferred"),IF(I95<0,"Accelerated","Unchanged")) -> Accelerated | P95: ='Growth (no penalty)'!I123 -> 2028 | Q95: =P95-G95 -> -13
A96: ='Growth profile'!A68 -> project 92 | B96: ='Growth profile'!B68 -> random growth | C96: ='Growth profile'!C68 -> 3 | D96: ='Growth profile'!D68 -> 1.31 | E96: ='Growth profile'!E68 -> 13.727193 | F96: ='Growth profile'!H68 -> 0.0136 | G96: ='Raw profile'!I68 -> 2038 | H96: ='Growth profile'!I68 -> 2026 | I96: =H96-G96 -> -12 | J96: ='Raw profile'!O68 -> 13.745982 | K96: ='Growth profile'!O68 -> 23.175653 | L96: =MIN('Growth profile'!L68,2085) -> 2070 | M96: ='Growth profile'!N68 -> 0 | N96: =IF(F96<0,"shrinking",IF(F96<0.015,"under 1.5%",IF(F96<0.018,"1.5% to 1.8%","1.8% and over"))) -> under 1.5% | O96: =IF(I96>0,IF(L96=2085,"Deferred - pinned to horizon end","Deferred"),IF(I96<0,"Accelerated","Unchanged")) -> Accelerated | P96: ='Growth (no penalty)'!I68 -> 2026 | Q96: =P96-G96 -> -12
A97: ='Growth profile'!A109 -> project 180 | B97: ='Growth profile'!B109 -> random growth | C97: ='Growth profile'!C109 -> 2 | D97: ='Growth profile'!D109 -> 1.5 | E97: ='Growth profile'!E109 -> 3.5977124 | F97: ='Growth profile'!H109 -> 0.0124 | G97: ='Raw profile'!I109 -> 2040 | H97: ='Growth profile'!I109 -> 2026 | I97: =H97-G97 -> -14 | J97: ='Raw profile'!O109 -> 4.157485 | K97: ='Growth profile'!O109 -> 6.8218887 | L97: =MIN('Growth profile'!L109,2085) -> 2067 | M97: ='Growth profile'!N109 -> 0 | N97: =IF(F97<0,"shrinking",IF(F97<0.015,"under 1.5%",IF(F97<0.018,"1.5% to 1.8%","1.8% and over"))) -> under 1.5% | O97: =IF(I97>0,IF(L97=2085,"Deferred - pinned to horizon end","Deferred"),IF(I97<0,"Accelerated","Unchanged")) -> Accelerated | P97: ='Growth (no penalty)'!I109 -> 2026 | Q97: =P97-G97 -> -14
A98: ='Growth profile'!A94 -> project 148 | B98: ='Growth profile'!B94 -> random growth | C98: ='Growth profile'!C94 -> 4 | D98: ='Growth profile'!D94 -> 1 | E98: ='Growth profile'!E94 -> 22.667925 | F98: ='Growth profile'!H94 -> 0.0126 | G98: ='Raw profile'!I94 -> 2041 | H98: ='Growth profile'!I94 -> 2026 | I98: =H98-G98 -> -15 | J98: ='Raw profile'!O94 -> 17.021257 | K98: ='Growth profile'!O94 -> 29.154125 | L98: =MIN('Growth profile'!L94,2085) -> 2069 | M98: ='Growth profile'!N94 -> 0 | N98: =IF(F98<0,"shrinking",IF(F98<0.015,"under 1.5%",IF(F98<0.018,"1.5% to 1.8%","1.8% and over"))) -> under 1.5% | O98: =IF(I98>0,IF(L98=2085,"Deferred - pinned to horizon end","Deferred"),IF(I98<0,"Accelerated","Unchanged")) -> Accelerated | P98: ='Growth (no penalty)'!I94 -> 2026 | Q98: =P98-G98 -> -15
A99: ='Growth profile'!A114 -> project 188 | B99: ='Growth profile'!B114 -> random growth | C99: ='Growth profile'!C114 -> 2 | D99: ='Growth profile'!D114 -> 1.36 | E99: ='Growth profile'!E114 -> 1.3199078 | F99: ='Growth profile'!H114 -> 0.0144 | G99: ='Raw profile'!I114 -> 2041 | H99: ='Growth profile'!I114 -> 2026 | I99: =H99-G99 -> -15 | J99: ='Raw profile'!O114 -> 1.3436046 | K99: ='Growth profile'!O114 -> 2.3662061 | L99: =MIN('Growth profile'!L114,2085) -> 2068 | M99: ='Growth profile'!N114 -> 0 | N99: =IF(F99<0,"shrinking",IF(F99<0.015,"under 1.5%",IF(F99<0.018,"1.5% to 1.8%","1.8% and over"))) -> under 1.5% | O99: =IF(I99>0,IF(L99=2085,"Deferred - pinned to horizon end","Deferred"),IF(I99<0,"Accelerated","Unchanged")) -> Accelerated | P99: ='Growth (no penalty)'!I114 -> 2028 | Q99: =P99-G99 -> -13
A100: ='Growth profile'!A100 -> project 158 | B100: ='Growth profile'!B100 -> random growth | C100: ='Growth profile'!C100 -> 3 | D100: ='Growth profile'!D100 -> 1 | E100: ='Growth profile'!E100 -> 13.672991 | F100: ='Growth profile'!H100 -> 0.0142 | G100: ='Raw profile'!I100 -> 2042 | H100: ='Growth profile'!I100 -> 2026 | I100: =H100-G100 -> -16 | J100: ='Raw profile'!O100 -> 10.046465 | K100: ='Growth profile'!O100 -> 17.913409 | L100: =MIN('Growth profile'!L100,2085) -> 2068 | M100: ='Growth profile'!N100 -> 0 | N100: =IF(F100<0,"shrinking",IF(F100<0.015,"under 1.5%",IF(F100<0.018,"1.5% to 1.8%","1.8% and over"))) -> under 1.5% | O100: =IF(I100>0,IF(L100=2085,"Deferred - pinned to horizon end","Deferred"),IF(I100<0,"Accelerated","Unchanged")) -> Accelerated | P100: ='Growth (no penalty)'!I100 -> 2026 | Q100: =P100-G100 -> -16
A101: ='Growth profile'!A110 -> project 181 | B101: ='Growth profile'!B110 -> random growth | C101: ='Growth profile'!C110 -> 2 | D101: ='Growth profile'!D110 -> 1 | E101: ='Growth profile'!E110 -> 3.597 | F101: ='Growth profile'!H110 -> 0.0145 | G101: ='Raw profile'!I110 -> 2042 | H101: ='Growth profile'!I110 -> 2026 | I101: =H101-G101 -> -16 | J101: ='Raw profile'!O110 -> 2.699908 | K101: ='Growth profile'!O110 -> 4.7237526 | L101: =MIN('Growth profile'!L110,2085) -> 2066 | M101: ='Growth profile'!N110 -> 0 | N101: =IF(F101<0,"shrinking",IF(F101<0.015,"under 1.5%",IF(F101<0.018,"1.5% to 1.8%","1.8% and over"))) -> under 1.5% | O101: =IF(I101>0,IF(L101=2085,"Deferred - pinned to horizon end","Deferred"),IF(I101<0,"Accelerated","Unchanged")) -> Accelerated | P101: ='Growth (no penalty)'!I110 -> 2026 | Q101: =P101-G101 -> -16
...

Sheet Raw profile
A1: Raw profile - MindOpt production objective (OPTIMAL, gap 0.0000%, 329s)
A2: Blue = inputs (start years pre-filled with the MindOpt solution; edit to test a schedule). Black = formulas. $M real. Objective units follow the optimiser's scaling.
D3: Schedule & objective checks | L3: Holding-cash penalty bands (balance carried into a year that is still building)
A4: Funding envelope ($M p.a.) | B4: 210 | D4: Min closing balance ($M) - >= 0 within $0.5M solver rounding (no debt) | J4: =MIN(C344:BJ344) -> -0.025858743 | L4: Band | M4: From ($M) | N4: From (% env) | O4: Weight / $0.01M-yr
A5: Base year (growth & discount t=0) | B5: 2026 | D5: Peak balance carried into a construction year ($M) | J5: =MAX(C346:BJ346) -> 47.2655 | L5: Band 1 | M5: 35.445 | N5: =M5/$B$4 -> 0.16878571 | O5: 1000
A6: Discount rate, years 1-30 | B6: 0.02 | D6: Average balance carried while building ($M) | J6: =IFERROR(SUM(C346:BJ346)/SUM(C345:BJ345),0) -> 5.2065596 | L6: Band 2 | M6: 47.26 | N6: =M6/$B$4 -> 0.22504762 | O6: 10000
A7: Discount switch year (t) | B7: 30 | D7: Years holding cash above the penalty-free cap | J7: =COUNTIF(C348:BJ348,">0.005") -> 1 | L7: Band 3 | M7: 59.0751 | N7: =M7/$B$4 -> 0.28131 | O7: 100000
A8: Discount rate, after switch | B8: 0.015 | D8: Max annual spend / envelope | J8: =MAX(C341:BJ341)/$B$4 -> 1.2079536 | L8: Band 4 (and above) | M8: 70.8901 | N8: =M8/$B$4 -> 0.3375719 | O8: 1000000
A9: Benefit life (years) | B9: 40 | D9: Years with spend above the envelope | J9: =SUMPRODUCT(--(C341:BJ341>C338:BJ338+0.005)) -> 12 | L9: Below band 1: free (backlog weight only). Final construction year: released, never penalised.
A10: Backlog weight (per $0.01M held) | B10: 1 | D10: Funded years with zero spend (idle) | J10: =COUNTIFS(C339:BJ339,1,C341:BJ341,0) -> 0
A11: PV weight | B11: 0.0001 | D11: Objective: backlog units | J11: =SUM(C346:BJ346)*$B$12*$B$10 -> 9371.8072
A12: Spend scale (units per $M) | B12: 100 | D12: Objective: holding-cash tier units | J12: =SUM(C353:BJ353) -> 1187000.2
A13: PV scale | B13: 10000 | D13: Objective: PV units (PV x 1e6 x PV weight x PV scale) | J13: =O124*1000000*$B$11*$B$13 -> 7.4101203e+09
A14: Last construction year (surplus released here, not penalised) | B14: =MAX(J24:J123) -> 2044 | D14: Objective (Excel) = backlog + tiers - PV | J14: =J11+J12-J13 -> -7.4089239e+09
D15: Objective (MindOpt) | J15: -7.4089294e+09
D16: Check: Excel / MindOpt - 1 | J16: =IFERROR(J14/J15-1,0) -> -7.3886603e-07
D17: Total PV of benefits ($M) | J17: =O124 -> 7410.1203
A23: Project | B23: Role | C23: Cost band (1=small) | D23: Base BCR (test, no growth) | E23: Cost ($M) | F23: Duration (yrs) | G23: Annual benefit ($M, 2026 terms) | H23: Real growth p.a. | I23: Start year | J23: Build end | K23: Benefit start | L23: Benefit end (uncapped) | M23: Benefit yrs in horizon | N23: Benefit yrs truncated | O23: PV benefits ($M) | P23: MindOpt PV ($M) | Q23: Check: Excel - MindOpt | R23: PV cost ($M) | S23: PV BCR | T23: Spend yr 1 | U23: Spend yr 2 | V23: Spend yr 3 | W23: Spend yr 4 | X23: Spend yr 5 | Y23: Spend yr 6 | Z23: Spend yr 7 | AA23: Spend yr 8 | AB23: Spend yr 9 | AC23: Spend yr 10 | AD23: Spend yr 11 | AE23: Spend yr 12 | AF23: Spend yr 13 | AG23: Spend yr 14 | AH23: Spend yr 15 | AI23: Spend yr 16
A24: project 1 | B24: no growth (raw) | C24: 4 | D24: 7 | E24: 36.329552 | F24: 6 | G24: 9.5924845 | H24: 0 | I24: 2026 | J24: =I24+F24-1 -> 2031 | K24: =I24+F24 -> 2032 | L24: =K24+$B$9-1 -> 2071 | M24: =MAX(0,MIN(L24,2085)-K24+1) -> 40 | N24: =$B$9-M24 -> 0 | O24: =SUMPRODUCT(C235:BJ235,$C$129:$BJ$129) -> 240.28604 | P24: 240.28604 | Q24: =O24-P24 -> 0 | R24: =SUMPRODUCT(C132:BJ132,$C$129:$BJ$129) -> 34.326578 | S24: =IF(R24=0,0,O24/R24) -> 7 | T24: 0.650261 | U24: 2.3382451 | V24: 9.131088 | W24: 13.552779 | X24: 10.145459 | Y24: 0.5117207 | Z24: 0 | AA24: 0 | AB24: 0 | AC24: 0 | AD24: 0 | AE24: 0 | AF24: 0 | AG24: 0 | AH24: 0 | AI24: 0
A25: project 4 | B25: no growth (raw) | C25: 2 | D25: 4.49 | E25: 1.6835429 | F25: 2 | G25: 0.27936778 | H25: 0 | I25: 2026 | J25: =I25+F25-1 -> 2027 | K25: =I25+F25 -> 2028 | L25: =K25+$B$9-1 -> 2067 | M25: =MAX(0,MIN(L25,2085)-K25+1) -> 40 | N25: =$B$9-M25 -> 0 | O25: =SUMPRODUCT(C236:BJ236,$C$129:$BJ$129) -> 7.5362348 | P25: 7.5362348 | Q25: =O25-P25 -> 0 | R25: =SUMPRODUCT(C133:BJ133,$C$129:$BJ$129) -> 1.6784487 | S25: =IF(R25=0,0,O25/R25) -> 4.49 | T25: 1.423739 | U25: 0.25980392 | V25: 0 | W25: 0 | X25: 0 | Y25: 0 | Z25: 0 | AA25: 0 | AB25: 0 | AC25: 0 | AD25: 0 | AE25: 0 | AF25: 0 | AG25: 0 | AH25: 0 | AI25: 0
A26: project 7 | B26: no growth (raw) | C26: 3 | D26: 1.46 | E26: 7.63 | F26: 1 | G26: 0.40526409 | H26: 0 | I26: 2037 | J26: =I26+F26-1 -> 2037 | K26: =I26+F26 -> 2038 | L26: =K26+$B$9-1 -> 2077 | M26: =MAX(0,MIN(L26,2085)-K26+1) -> 40 | N26: =$B$9-M26 -> 0 | O26: =SUMPRODUCT(C237:BJ237,$C$129:$BJ$129) -> 9.1150993 | P26: 9.1150993 | Q26: =O26-P26 -> 0 | R26: =SUMPRODUCT(C134:BJ134,$C$129:$BJ$129) -> 6.136527 | S26: =IF(R26=0,0,O26/R26) -> 1.485384 | T26: 7.63 | U26: 0 | V26: 0 | W26: 0 | X26: 0 | Y26: 0 | Z26: 0 | AA26: 0 | AB26: 0 | AC26: 0 | AD26: 0 | AE26: 0 | AF26: 0 | AG26: 0 | AH26: 0 | AI26: 0
A27: project 8 | B27: no growth (raw) | C27: 3 | D27: 1 | E27: 5.45 | F27: 1 | G27: 0.1982701 | H27: 0 | I27: 2041 | J27: =I27+F27-1 -> 2041 | K27: =I27+F27 -> 2042 | L27: =K27+$B$9-1 -> 2081 | M27: =MAX(0,MIN(L27,2085)-K27+1) -> 40 | N27: =$B$9-M27 -> 0 | O27: =SUMPRODUCT(C238:BJ238,$C$129:$BJ$129) -> 4.1608738 | P27: 4.1608738 | Q27: =O27-P27 -> 0 | R27: =SUMPRODUCT(C135:BJ135,$C$129:$BJ$129) -> 4.0494303 | S27: =IF(R27=0,0,O27/R27) -> 1.0275208 | T27: 5.45 | U27: 0 | V27: 0 | W27: 0 | X27: 0 | Y27: 0 | Z27: 0 | AA27: 0 | AB27: 0 | AC27: 0 | AD27: 0 | AE27: 0 | AF27: 0 | AG27: 0 | AH27: 0 | AI27: 0
A28: project 9 | B28: no growth (raw) | C28: 2 | D28: 1 | E28: 4.36 | F28: 1 | G28: 0.15861608 | H28: 0 | I28: 2043 | J28: =I28+F28-1 -> 2043 | K28: =I28+F28 -> 2044 | L28: =K28+$B$9-1 -> 2083 | M28: =MAX(0,MIN(L28,2085)-K28+1) -> 40 | N28: =$B$9-M28 -> 0 | O28: =SUMPRODUCT(C239:BJ239,$C$129:$BJ$129) -> 3.2179194 | P28: 3.2179194 | Q28: =O28-P28 -> 0 | R28: =SUMPRODUCT(C136:BJ136,$C$129:$BJ$129) -> 3.1137488 | S28: =IF(R28=0,0,O28/R28) -> 1.0334551 | T28: 4.36 | U28: 0 | V28: 0 | W28: 0 | X28: 0 | Y28: 0 | Z28: 0 | AA28: 0 | AB28: 0 | AC28: 0 | AD28: 0 | AE28: 0 | AF28: 0 | AG28: 0 | AH28: 0 | AI28: 0
A29: project 12 | B29: no growth (raw) | C29: 2 | D29: 2.07 | E29: 2.9836078 | F29: 2 | G29: 0.22790138 | H29: 0 | I29: 2026 | J29: =I29+F29-1 -> 2027 | K29: =I29+F29 -> 2028 | L29: =K29+$B$9-1 -> 2067 | M29: =MAX(0,MIN(L29,2085)-K29+1) -> 40 | N29: =$B$9-M29 -> 0 | O29: =SUMPRODUCT(C240:BJ240,$C$129:$BJ$129) -> 6.1478753 | P29: 6.1478753 | Q29: =O29-P29 -> 0 | R29: =SUMPRODUCT(C137:BJ137,$C$129:$BJ$129) -> 2.9699881 | S29: =IF(R29=0,0,O29/R29) -> 2.07 | T29: 2.289 | U29: 0.69460784 | V29: 0 | W29: 0 | X29: 0 | Y29: 0 | Z29: 0 | AA29: 0 | AB29: 0 | AC29: 0 | AD29: 0 | AE29: 0 | AF29: 0 | AG29: 0 | AH29: 0 | AI29: 0
A30: project 16 | B30: no growth (raw) | C30: 2 | D30: 1.49 | E30: 2.4198 | F30: 1 | G30: 0.13116757 | H30: 0 | I30: 2037 | J30: =I30+F30-1 -> 2037 | K30: =I30+F30 -> 2038 | L30: =K30+$B$9-1 -> 2077 | M30: =MAX(0,MIN(L30,2085)-K30+1) -> 40 | N30: =$B$9-M30 -> 0 | O30: =SUMPRODUCT(C241:BJ241,$C$129:$BJ$129) -> 2.9501884 | P30: 2.9501884 | Q30: =O30-P30 -> 0 | R30: =SUMPRODUCT(C138:BJ138,$C$129:$BJ$129) -> 1.9461557 | S30: =IF(R30=0,0,O30/R30) -> 1.5159056 | T30: 2.4198 | U30: 0 | V30: 0 | W30: 0 | X30: 0 | Y30: 0 | Z30: 0 | AA30: 0 | AB30: 0 | AC30: 0 | AD30: 0 | AE30: 0 | AF30: 0 | AG30: 0 | AH30: 0 | AI30: 0
A31: project 19 | B31: no growth (raw) | C31: 2 | D31: 1.39 | E31: 2.071 | F31: 1 | G31: 0.10472627 | H31: 0 | I31: 2037 | J31: =I31+F31-1 -> 2037 | K31: =I31+F31 -> 2038 | L31: =K31+$B$9-1 -> 2077 | M31: =MAX(0,MIN(L31,2085)-K31+1) -> 40 | N31: =$B$9-M31 -> 0 | O31: =SUMPRODUCT(C242:BJ242,$C$129:$BJ$129) -> 2.3554772 | P31: 2.3554772 | Q31: =O31-P31 -> 0 | R31: =SUMPRODUCT(C139:BJ139,$C$129:$BJ$129) -> 1.6656288 | S31: =IF(R31=0,0,O31/R31) -> 1.414167 | T31: 2.071 | U31: 0 | V31: 0 | W31: 0 | X31: 0 | Y31: 0 | Z31: 0 | AA31: 0 | AB31: 0 | AC31: 0 | AD31: 0 | AE31: 0 | AF31: 0 | AG31: 0 | AH31: 0 | AI31: 0
A32: project 20 | B32: no growth (raw) | C32: 2 | D32: 1.69 | E32: 1.8170941 | F32: 2 | G32: 0.11364077 | H32: 0 | I32: 2026 | J32: =I32+F32-1 -> 2027 | K32: =I32+F32 -> 2028 | L32: =K32+$B$9-1 -> 2067 | M32: =MAX(0,MIN(L32,2085)-K32+1) -> 40 | N32: =$B$9-M32 -> 0 | O32: =SUMPRODUCT(C243:BJ243,$C$129:$BJ$129) -> 3.0655774 | P32: 3.0655774 | Q32: =O32-P32 -> 0 | R32: =SUMPRODUCT(C140:BJ140,$C$129:$BJ$129) -> 1.8139511 | S32: =IF(R32=0,0,O32/R32) -> 1.69 | T32: 1.6568 | U32: 0.16029412 | V32: 0 | W32: 0 | X32: 0 | Y32: 0 | Z32: 0 | AA32: 0 | AB32: 0 | AC32: 0 | AD32: 0 | AE32: 0 | AF32: 0 | AG32: 0 | AH32: 0 | AI32: 0
A33: project 22 | B33: no growth (raw) | C33: 2 | D33: 3.73 | E33: 1.3854571 | F33: 2 | G33: 0.19113378 | H33: 0 | I33: 2026 | J33: =I33+F33-1 -> 2027 | K33: =I33+F33 -> 2028 | L33: =K33+$B$9-1 -> 2067 | M33: =MAX(0,MIN(L33,2085)-K33+1) -> 40 | N33: =$B$9-M33 -> 0 | O33: =SUMPRODUCT(C244:BJ244,$C$129:$BJ$129) -> 5.1560314 | P33: 5.1560314 | Q33: =O33-P33 -> 0 | R33: =SUMPRODUCT(C141:BJ141,$C$129:$BJ$129) -> 1.3823141 | S33: =IF(R33=0,0,O33/R33) -> 3.73 | T33: 1.225162 | U33: 0.1602951 | V33: 0 | W33: 0 | X33: 0 | Y33: 0 | Z33: 0 | AA33: 0 | AB33: 0 | AC33: 0 | AD33: 0 | AE33: 0 | AF33: 0 | AG33: 0 | AH33: 0 | AI33: 0
A34: project 23 | B34: no growth (raw) | C34: 1 | D34: 1.67 | E34: 0.654 | F34: 1 | G34: 0.039733328 | H34: 0 | I34: 2037 | J34: =I34+F34-1 -> 2037 | K34: =I34+F34 -> 2038 | L34: =K34+$B$9-1 -> 2077 | M34: =MAX(0,MIN(L34,2085)-K34+1) -> 40 | N34: =$B$9-M34 -> 0 | O34: =SUMPRODUCT(C245:BJ245,$C$129:$BJ$129) -> 0.89367216 | P34: 0.89367216 | Q34: =O34-P34 -> 0 | R34: =SUMPRODUCT(C142:BJ142,$C$129:$BJ$129) -> 0.52598803 | S34: =IF(R34=0,0,O34/R34) -> 1.6990352 | T34: 0.654 | U34: 0 | V34: 0 | W34: 0 | X34: 0 | Y34: 0 | Z34: 0 | AA34: 0 | AB34: 0 | AC34: 0 | AD34: 0 | AE34: 0 | AF34: 0 | AG34: 0 | AH34: 0 | AI34: 0
A35: project 24 | B35: no growth (raw) | C35: 1 | D35: 1.4 | E35: 1.2198382 | F35: 2 | G35: 0.062980831 | H35: 0 | I35: 2037 | J35: =I35+F35-1 -> 2038 | K35: =I35+F35 -> 2039 | L35: =K35+$B$9-1 -> 2078 | M35: =MAX(0,MIN(L35,2085)-K35+1) -> 40 | N35: =$B$9-M35 -> 0 | O35: =SUMPRODUCT(C246:BJ246,$C$129:$BJ$129) -> 1.3919475 | P35: 1.3919475 | Q35: =O35-P35 -> 0 | R35: =SUMPRODUCT(C143:BJ143,$C$129:$BJ$129) -> 0.97601517 | S35: =IF(R35=0,0,O35/R35) -> 1.4261535 | T35: 0.89925 | U35: 0.32058824 | V35: 0 | W35: 0 | X35: 0 | Y35: 0 | Z35: 0 | AA35: 0 | AB35: 0 | AC35: 0 | AD35: 0 | AE35: 0 | AF35: 0 | AG35: 0 | AH35: 0 | AI35: 0
... A123: project 218 | B123: no growth (raw) | C123: 3 | D123: 1 | E123: 9.0115146 | F123: 3 | G123: 0.3308638 | H123: 0 | I123: 2041 | J123: =I123+F123-1 -> 2043 | K123: =I123+F123 -> 2044 | L123: =K123+$B$9-1 -> 2083 | M123: =MAX(0,MIN(L123,2085)-K123+1) -> 40 | N123: =$B$9-M123 -> 0 | O123: =SUMPRODUCT(C334:BJ334,$C$129:$BJ$129) -> 6.7123903 | P123: 6.7123903 | Q123: =O123-P123 -> 0 | R123: =SUMPRODUCT(C231:BJ231,$C$129:$BJ$129) -> 6.508922 | S123: =IF(R123=0,0,O123/R123) -> 1.0312599 | T123: 0.5603614 | U123: 3.9954467 | V123: 4.4557065 | W123: 0 | X123: 0 | Y123: 0 | Z123: 0 | AA123: 0 | AB123: 0 | AC123: 0 | AD123: 0 | AE123: 0 | AF123: 0 | AG123: 0 | AH123: 0 | AI123: 0
A124: Total | E124: =SUM(E24:E123) -> 3829.6469 | O124: =SUM(O24:O123) -> 7410.1203 | P124: =SUM(P24:P123) -> 7410.1203 | Q124: =SUM(Q24:Q123) -> 0 | R124: =SUM(R24:R123) -> 3244.3484 | S124: =IF(R124=0,0,O124/R124) -> 2.2840088
A127: Year | C127: 2026 | D127: 2027 | E127: 2028 | F127: 2029 | G127: 2030 | H127: 2031 | I127: 2032 | J127: 2033 | K127: 2034 | L127: 2035 | M127: 2036 | N127: 2037 | O127: 2038 | P127: 2039 | Q127: 2040 | R127: 2041 | S127: 2042 | T127: 2043 | U127: 2044 | V127: 2045 | W127: 2046 | X127: 2047 | Y127: 2048 | Z127: 2049 | AA127: 2050 | AB127: 2051 | AC127: 2052 | AD127: 2053 | AE127: 2054 | AF127: 2055 | AG127: 2056 | AH127: 2057 | AI127: 2058 | AJ127: 2059 | AK127: 2060 | AL127: 2061 | AM127: 2062 | AN127: 2063 | AO127: 2064 | AP127: 2065 | AQ127: 2066 | AR127: 2067 | AS127: 2068 | AT127: 2069 | AU127: 2070 | AV127: 2071 | AW127: 2072 | AX127: 2073 | AY127: 2074 | AZ127: 2075 | BA127: 2076 | BB127: 2077 | BC127: 2078 | BD127: 2079 | BE127: 2080 | BF127: 2081 | BG127: 2082 | BH127: 2083 | BI127: 2084 | BJ127: 2085
A128: t (years from base) | C128: =C127-$B$5 -> 0 | D128: =D127-$B$5 -> 1 | E128: =E127-$B$5 -> 2 | F128: =F127-$B$5 -> 3 | G128: =G127-$B$5 -> 4 | H128: =H127-$B$5 -> 5 | I128: =I127-$B$5 -> 6 | J128: =J127-$B$5 -> 7 | ... BJ128: =BJ127-$B$5 -> 59
A129: Discount factor | C129: 1 | D129: =C129/(1+IF(D128<=$B$7,$B$6,$B$8)) -> 0.98039216 | E129: =D129/(1+IF(E128<=$B$7,$B$6,$B$8)) -> 0.96116878 | F129: =E129/(1+IF(F128<=$B$7,$B$6,$B$8)) -> 0.94232233 | G129: =F129/(1+IF(G128<=$B$7,$B$6,$B$8)) -> 0.92384543 | H129: =G129/(1+IF(H128<=$B$7,$B$6,$B$8)) -> 0.90573081 | I129: =H129/(1+IF(I128<=$B$7,$B$6,$B$8)) -> 0.88797138 | J129: =I129/(1+IF(J128<=$B$7,$B$6,$B$8)) -> 0.87056018 | K129: =J129/(1+IF(K128<=$B$7,$B$6,$B$8)) -> 0.85349037 | ... BJ129: =BI129/(1+IF(BJ128<=$B$7,$B$6,$B$8)) -> 0.35849213
A131: Capital spend by project ($M)
A132: =A24 -> project 1 | C132: =IF(AND(C$127>=$I24,C$127<$I24+$F24),INDEX($T24:$AI24,C$127-$I24+1),0) -> 0.650261 | D132: =IF(AND(D$127>=$I24,D$127<$I24+$F24),INDEX($T24:$AI24,D$127-$I24+1),0) -> 2.3382451 | E132: =IF(AND(E$127>=$I24,E$127<$I24+$F24),INDEX($T24:$AI24,E$127-$I24+1),0) -> 9.131088 | F132: =IF(AND(F$127>=$I24,F$127<$I24+$F24),INDEX($T24:$AI24,F$127-$I24+1),0) -> 13.552779 | G132: =IF(AND(G$127>=$I24,G$127<$I24+$F24),INDEX($T24:$AI24,G$127-$I24+1),0) -> 10.145459 | H132: =IF(AND(H$127>=$I24,H$127<$I24+$F24),INDEX($T24:$AI24,H$127-$I24+1),0) -> 0.5117207 | I132: =IF(AND(I$127>=$I24,I$127<$I24+$F24),INDEX($T24:$AI24,I$127-$I24+1),0) -> 0 | J132: =IF(AND(J$127>=$I24,J$127<$I24+$F24),INDEX($T24:$AI24,J$127-$I24+1),0) -> 0 | ... BJ132: =IF(AND(BJ$127>=$I24,BJ$127<$I24+$F24),INDEX($T24:$AI24,BJ$127-$I24+1),0) -> 0
A133: =A25 -> project 4 | C133: =IF(AND(C$127>=$I25,C$127<$I25+$F25),INDEX($T25:$AI25,C$127-$I25+1),0) -> 1.423739 | D133: =IF(AND(D$127>=$I25,D$127<$I25+$F25),INDEX($T25:$AI25,D$127-$I25+1),0) -> 0.25980392 | E133: =IF(AND(E$127>=$I25,E$127<$I25+$F25),INDEX($T25:$AI25,E$127-$I25+1),0) -> 0 | F133: =IF(AND(F$127>=$I25,F$127<$I25+$F25),INDEX($T25:$AI25,F$127-$I25+1),0) -> 0 | G133: =IF(AND(G$127>=$I25,G$127<$I25+$F25),INDEX($T25:$AI25,G$127-$I25+1),0) -> 0 | H133: =IF(AND(H$127>=$I25,H$127<$I25+$F25),INDEX($T25:$AI25,H$127-$I25+1),0) -> 0 | I133: =IF(AND(I$127>=$I25,I$127<$I25+$F25),INDEX($T25:$AI25,I$127-$I25+1),0) -> 0 | J133: =IF(AND(J$127>=$I25,J$127<$I25+$F25),INDEX($T25:$AI25,J$127-$I25+1),0) -> 0 | ... BJ133: =IF(AND(BJ$127>=$I25,BJ$127<$I25+$F25),INDEX($T25:$AI25,BJ$127-$I25+1),0) -> 0
A134: =A26 -> project 7 | C134: =IF(AND(C$127>=$I26,C$127<$I26+$F26),INDEX($T26:$AI26,C$127-$I26+1),0) -> 0 | D134: =IF(AND(D$127>=$I26,D$127<$I26+$F26),INDEX($T26:$AI26,D$127-$I26+1),0) -> 0 | E134: =IF(AND(E$127>=$I26,E$127<$I26+$F26),INDEX($T26:$AI26,E$127-$I26+1),0) -> 0 | F134: =IF(AND(F$127>=$I26,F$127<$I26+$F26),INDEX($T26:$AI26,F$127-$I26+1),0) -> 0 | G134: =IF(AND(G$127>=$I26,G$127<$I26+$F26),INDEX($T26:$AI26,G$127-$I26+1),0) -> 0 | H134: =IF(AND(H$127>=$I26,H$127<$I26+$F26),INDEX($T26:$AI26,H$127-$I26+1),0) -> 0 | I134: =IF(AND(I$127>=$I26,I$127<$I26+$F26),INDEX($T26:$AI26,I$127-$I26+1),0) -> 0 | J134: =IF(AND(J$127>=$I26,J$127<$I26+$F26),INDEX($T26:$AI26,J$127-$I26+1),0) -> 0 | ... BJ134: =IF(AND(BJ$127>=$I26,BJ$127<$I26+$F26),INDEX($T26:$AI26,BJ$127-$I26+1),0) -> 0
A135: =A27 -> project 8 | C135: =IF(AND(C$127>=$I27,C$127<$I27+$F27),INDEX($T27:$AI27,C$127-$I27+1),0) -> 0 | D135: =IF(AND(D$127>=$I27,D$127<$I27+$F27),INDEX($T27:$AI27,D$127-$I27+1),0) -> 0 | E135: =IF(AND(E$127>=$I27,E$127<$I27+$F27),INDEX($T27:$AI27,E$127-$I27+1),0) -> 0 | F135: =IF(AND(F$127>=$I27,F$127<$I27+$F27),INDEX($T27:$AI27,F$127-$I27+1),0) -> 0 | G135: =IF(AND(G$127>=$I27,G$127<$I27+$F27),INDEX($T27:$AI27,G$127-$I27+1),0) -> 0 | H135: =IF(AND(H$127>=$I27,H$127<$I27+$F27),INDEX($T27:$AI27,H$127-$I27+1),0) -> 0 | I135: =IF(AND(I$127>=$I27,I$127<$I27+$F27),INDEX($T27:$AI27,I$127-$I27+1),0) -> 0 | J135: =IF(AND(J$127>=$I27,J$127<$I27+$F27),INDEX($T27:$AI27,J$127-$I27+1),0) -> 0 | ... BJ135: =IF(AND(BJ$127>=$I27,BJ$127<$I27+$F27),INDEX($T27:$AI27,BJ$127-$I27+1),0) -> 0
A136: =A28 -> project 9 | C136: =IF(AND(C$127>=$I28,C$127<$I28+$F28),INDEX($T28:$AI28,C$127-$I28+1),0) -> 0 | D136: =IF(AND(D$127>=$I28,D$127<$I28+$F28),INDEX($T28:$AI28,D$127-$I28+1),0) -> 0 | E136: =IF(AND(E$127>=$I28,E$127<$I28+$F28),INDEX($T28:$AI28,E$127-$I28+1),0) -> 0 | F136: =IF(AND(F$127>=$I28,F$127<$I28+$F28),INDEX($T28:$AI28,F$127-$I28+1),0) -> 0 | G136: =IF(AND(G$127>=$I28,G$127<$I28+$F28),INDEX($T28:$AI28,G$127-$I28+1),0) -> 0 | H136: =IF(AND(H$127>=$I28,H$127<$I28+$F28),INDEX($T28:$AI28,H$127-$I28+1),0) -> 0 | I136: =IF(AND(I$127>=$I28,I$127<$I28+$F28),INDEX($T28:$AI28,I$127-$I28+1),0) -> 0 | J136: =IF(AND(J$127>=$I28,J$127<$I28+$F28),INDEX($T28:$AI28,J$127-$I28+1),0) -> 0 | ... BJ136: =IF(AND(BJ$127>=$I28,BJ$127<$I28+$F28),INDEX($T28:$AI28,BJ$127-$I28+1),0) -> 0
A137: =A29 -> project 12 | C137: =IF(AND(C$127>=$I29,C$127<$I29+$F29),INDEX($T29:$AI29,C$127-$I29+1),0) -> 2.289 | D137: =IF(AND(D$127>=$I29,D$127<$I29+$F29),INDEX($T29:$AI29,D$127-$I29+1),0) -> 0.69460784 | E137: =IF(AND(E$127>=$I29,E$127<$I29+$F29),INDEX($T29:$AI29,E$127-$I29+1),0) -> 0 | F137: =IF(AND(F$127>=$I29,F$127<$I29+$F29),INDEX($T29:$AI29,F$127-$I29+1),0) -> 0 | G137: =IF(AND(G$127>=$I29,G$127<$I29+$F29),INDEX($T29:$AI29,G$127-$I29+1),0) -> 0 | H137: =IF(AND(H$127>=$I29,H$127<$I29+$F29),INDEX($T29:$AI29,H$127-$I29+1),0) -> 0 | I137: =IF(AND(I$127>=$I29,I$127<$I29+$F29),INDEX($T29:$AI29,I$127-$I29+1),0) -> 0 | J137: =IF(AND(J$127>=$I29,J$127<$I29+$F29),INDEX($T29:$AI29,J$127-$I29+1),0) -> 0 | ... BJ137: =IF(AND(BJ$127>=$I29,BJ$127<$I29+$F29),INDEX($T29:$AI29,BJ$127-$I29+1),0) -> 0
A138: =A30 -> project 16 | C138: =IF(AND(C$127>=$I30,C$127<$I30+$F30),INDEX($T30:$AI30,C$127-$I30+1),0) -> 0 | D138: =IF(AND(D$127>=$I30,D$127<$I30+$F30),INDEX($T30:$AI30,D$127-$I30+1),0) -> 0 | E138: =IF(AND(E$127>=$I30,E$127<$I30+$F30),INDEX($T30:$AI30,E$127-$I30+1),0) -> 0 | F138: =IF(AND(F$127>=$I30,F$127<$I30+$F30),INDEX($T30:$AI30,F$127-$I30+1),0) -> 0 | G138: =IF(AND(G$127>=$I30,G$127<$I30+$F30),INDEX($T30:$AI30,G$127-$I30+1),0) -> 0 | H138: =IF(AND(H$127>=$I30,H$127<$I30+$F30),INDEX($T30:$AI30,H$127-$I30+1),0) -> 0 | I138: =IF(AND(I$127>=$I30,I$127<$I30+$F30),INDEX($T30:$AI30,I$127-$I30+1),0) -> 0 | J138: =IF(AND(J$127>=$I30,J$127<$I30+$F30),INDEX($T30:$AI30,J$127-$I30+1),0) -> 0 | ... BJ138: =IF(AND(BJ$127>=$I30,BJ$127<$I30+$F30),INDEX($T30:$AI30,BJ$127-$I30+1),0) -> 0
A139: =A31 -> project 19 | C139: =IF(AND(C$127>=$I31,C$127<$I31+$F31),INDEX($T31:$AI31,C$127-$I31+1),0) -> 0 | D139: =IF(AND(D$127>=$I31,D$127<$I31+$F31),INDEX($T31:$AI31,D$127-$I31+1),0) -> 0 | E139: =IF(AND(E$127>=$I31,E$127<$I31+$F31),INDEX($T31:$AI31,E$127-$I31+1),0) -> 0 | F139: =IF(AND(F$127>=$I31,F$127<$I31+$F31),INDEX($T31:$AI31,F$127-$I31+1),0) -> 0 | G139: =IF(AND(G$127>=$I31,G$127<$I31+$F31),INDEX($T31:$AI31,G$127-$I31+1),0) -> 0 | H139: =IF(AND(H$127>=$I31,H$127<$I31+$F31),INDEX($T31:$AI31,H$127-$I31+1),0) -> 0 | I139: =IF(AND(I$127>=$I31,I$127<$I31+$F31),INDEX($T31:$AI31,I$127-$I31+1),0) -> 0 | J139: =IF(AND(J$127>=$I31,J$127<$I31+$F31),INDEX($T31:$AI31,J$127-$I31+1),0) -> 0 | ... BJ139: =IF(AND(BJ$127>=$I31,BJ$127<$I31+$F31),INDEX($T31:$AI31,BJ$127-$I31+1),0) -> 0
A140: =A32 -> project 20 | C140: =IF(AND(C$127>=$I32,C$127<$I32+$F32),INDEX($T32:$AI32,C$127-$I32+1),0) -> 1.6568 | D140: =IF(AND(D$127>=$I32,D$127<$I32+$F32),INDEX($T32:$AI32,D$127-$I32+1),0) -> 0.16029412 | E140: =IF(AND(E$127>=$I32,E$127<$I32+$F32),INDEX($T32:$AI32,E$127-$I32+1),0) -> 0 | F140: =IF(AND(F$127>=$I32,F$127<$I32+$F32),INDEX($T32:$AI32,F$127-$I32+1),0) -> 0 | G140: =IF(AND(G$127>=$I32,G$127<$I32+$F32),INDEX($T32:$AI32,G$127-$I32+1),0) -> 0 | H140: =IF(AND(H$127>=$I32,H$127<$I32+$F32),INDEX($T32:$AI32,H$127-$I32+1),0) -> 0 | I140: =IF(AND(I$127>=$I32,I$127<$I32+$F32),INDEX($T32:$AI32,I$127-$I32+1),0) -> 0 | J140: =IF(AND(J$127>=$I32,J$127<$I32+$F32),INDEX($T32:$AI32,J$127-$I32+1),0) -> 0 | ... BJ140: =IF(AND(BJ$127>=$I32,BJ$127<$I32+$F32),INDEX($T32:$AI32,BJ$127-$I32+1),0) -> 0
A141: =A33 -> project 22 | C141: =IF(AND(C$127>=$I33,C$127<$I33+$F33),INDEX($T33:$AI33,C$127-$I33+1),0) -> 1.225162 | D141: =IF(AND(D$127>=$I33,D$127<$I33+$F33),INDEX($T33:$AI33,D$127-$I33+1),0) -> 0.1602951 | E141: =IF(AND(E$127>=$I33,E$127<$I33+$F33),INDEX($T33:$AI33,E$127-$I33+1),0) -> 0 | F141: =IF(AND(F$127>=$I33,F$127<$I33+$F33),INDEX($T33:$AI33,F$127-$I33+1),0) -> 0 | G141: =IF(AND(G$127>=$I33,G$127<$I33+$F33),INDEX($T33:$AI33,G$127-$I33+1),0) -> 0 | H141: =IF(AND(H$127>=$I33,H$127<$I33+$F33),INDEX($T33:$AI33,H$127-$I33+1),0) -> 0 | I141: =IF(AND(I$127>=$I33,I$127<$I33+$F33),INDEX($T33:$AI33,I$127-$I33+1),0) -> 0 | J141: =IF(AND(J$127>=$I33,J$127<$I33+$F33),INDEX($T33:$AI33,J$127-$I33+1),0) -> 0 | ... BJ141: =IF(AND(BJ$127>=$I33,BJ$127<$I33+$F33),INDEX($T33:$AI33,BJ$127-$I33+1),0) -> 0
A142: =A34 -> project 23 | C142: =IF(AND(C$127>=$I34,C$127<$I34+$F34),INDEX($T34:$AI34,C$127-$I34+1),0) -> 0 | D142: =IF(AND(D$127>=$I34,D$127<$I34+$F34),INDEX($T34:$AI34,D$127-$I34+1),0) -> 0 | E142: =IF(AND(E$127>=$I34,E$127<$I34+$F34),INDEX($T34:$AI34,E$127-$I34+1),0) -> 0 | F142: =IF(AND(F$127>=$I34,F$127<$I34+$F34),INDEX($T34:$AI34,F$127-$I34+1),0) -> 0 | G142: =IF(AND(G$127>=$I34,G$127<$I34+$F34),INDEX($T34:$AI34,G$127-$I34+1),0) -> 0 | H142: =IF(AND(H$127>=$I34,H$127<$I34+$F34),INDEX($T34:$AI34,H$127-$I34+1),0) -> 0 | I142: =IF(AND(I$127>=$I34,I$127<$I34+$F34),INDEX($T34:$AI34,I$127-$I34+1),0) -> 0 | J142: =IF(AND(J$127>=$I34,J$127<$I34+$F34),INDEX($T34:$AI34,J$127-$I34+1),0) -> 0 | ... BJ142: =IF(AND(BJ$127>=$I34,BJ$127<$I34+$F34),INDEX($T34:$AI34,BJ$127-$I34+1),0) -> 0
A143: =A35 -> project 24 | C143: =IF(AND(C$127>=$I35,C$127<$I35+$F35),INDEX($T35:$AI35,C$127-$I35+1),0) -> 0 | D143: =IF(AND(D$127>=$I35,D$127<$I35+$F35),INDEX($T35:$AI35,D$127-$I35+1),0) -> 0 | E143: =IF(AND(E$127>=$I35,E$127<$I35+$F35),INDEX($T35:$AI35,E$127-$I35+1),0) -> 0 | F143: =IF(AND(F$127>=$I35,F$127<$I35+$F35),INDEX($T35:$AI35,F$127-$I35+1),0) -> 0 | G143: =IF(AND(G$127>=$I35,G$127<$I35+$F35),INDEX($T35:$AI35,G$127-$I35+1),0) -> 0 | H143: =IF(AND(H$127>=$I35,H$127<$I35+$F35),INDEX($T35:$AI35,H$127-$I35+1),0) -> 0 | I143: =IF(AND(I$127>=$I35,I$127<$I35+$F35),INDEX($T35:$AI35,I$127-$I35+1),0) -> 0 | J143: =IF(AND(J$127>=$I35,J$127<$I35+$F35),INDEX($T35:$AI35,J$127-$I35+1),0) -> 0 | ... BJ143: =IF(AND(BJ$127>=$I35,BJ$127<$I35+$F35),INDEX($T35:$AI35,BJ$127-$I35+1),0) -> 0
... A231: =A123 -> project 218 | C231: =IF(AND(C$127>=$I123,C$127<$I123+$F123),INDEX($T123:$AI123,C$127-$I123+1),0) -> 0 | D231: =IF(AND(D$127>=$I123,D$127<$I123+$F123),INDEX($T123:$AI123,D$127-$I123+1),0) -> 0 | E231: =IF(AND(E$127>=$I123,E$127<$I123+$F123),INDEX($T123:$AI123,E$127-$I123+1),0) -> 0 | F231: =IF(AND(F$127>=$I123,F$127<$I123+$F123),INDEX($T123:$AI123,F$127-$I123+1),0) -> 0 | G231: =IF(AND(G$127>=$I123,G$127<$I123+$F123),INDEX($T123:$AI123,G$127-$I123+1),0) -> 0 | H231: =IF(AND(H$127>=$I123,H$127<$I123+$F123),INDEX($T123:$AI123,H$127-$I123+1),0) -> 0 | I231: =IF(AND(I$127>=$I123,I$127<$I123+$F123),INDEX($T123:$AI123,I$127-$I123+1),0) -> 0 | J231: =IF(AND(J$127>=$I123,J$127<$I123+$F123),INDEX($T123:$AI123,J$127-$I123+1),0) -> 0 | ... BJ231: =IF(AND(BJ$127>=$I123,BJ$127<$I123+$F123),INDEX($T123:$AI123,BJ$127-$I123+1),0) -> 0
A232: Total spend | C232: =SUM(C132:C231) -> 162.7345 | D232: =SUM(D132:D231) -> 253.67025 | E232: =SUM(E132:E231) -> 212.90894 | F232: =SUM(F132:F231) -> 210.24458 | G232: =SUM(G132:G231) -> 210.44428 | H232: =SUM(H132:H231) -> 210.02331 | I232: =SUM(I132:I231) -> 205.03903 | J232: =SUM(J132:J231) -> 212.73966 | ... BJ232: =SUM(BJ132:BJ231) -> 0
A234: Benefits by project ($M real, incl. growth)
A235: =A24 -> project 1 | C235: =IF(AND(C$127>=$K24,C$127<=$L24),$G24*(1+$H24)^(C$127-$B$5),0) -> 0 | D235: =IF(AND(D$127>=$K24,D$127<=$L24),$G24*(1+$H24)^(D$127-$B$5),0) -> 0 | E235: =IF(AND(E$127>=$K24,E$127<=$L24),$G24*(1+$H24)^(E$127-$B$5),0) -> 0 | F235: =IF(AND(F$127>=$K24,F$127<=$L24),$G24*(1+$H24)^(F$127-$B$5),0) -> 0 | G235: =IF(AND(G$127>=$K24,G$127<=$L24),$G24*(1+$H24)^(G$127-$B$5),0) -> 0 | H235: =IF(AND(H$127>=$K24,H$127<=$L24),$G24*(1+$H24)^(H$127-$B$5),0) -> 0 | I235: =IF(AND(I$127>=$K24,I$127<=$L24),$G24*(1+$H24)^(I$127-$B$5),0) -> 9.5924845 | J235: =IF(AND(J$127>=$K24,J$127<=$L24),$G24*(1+$H24)^(J$127-$B$5),0) -> 9.5924845 | ... BJ235: =IF(AND(BJ$127>=$K24,BJ$127<=$L24),$G24*(1+$H24)^(BJ$127-$B$5),0) -> 0
A236: =A25 -> project 4 | C236: =IF(AND(C$127>=$K25,C$127<=$L25),$G25*(1+$H25)^(C$127-$B$5),0) -> 0 | D236: =IF(AND(D$127>=$K25,D$127<=$L25),$G25*(1+$H25)^(D$127-$B$5),0) -> 0 | E236: =IF(AND(E$127>=$K25,E$127<=$L25),$G25*(1+$H25)^(E$127-$B$5),0) -> 0.27936778 | F236: =IF(AND(F$127>=$K25,F$127<=$L25),$G25*(1+$H25)^(F$127-$B$5),0) -> 0.27936778 | G236: =IF(AND(G$127>=$K25,G$127<=$L25),$G25*(1+$H25)^(G$127-$B$5),0) -> 0.27936778 | H236: =IF(AND(H$127>=$K25,H$127<=$L25),$G25*(1+$H25)^(H$127-$B$5),0) -> 0.27936778 | I236: =IF(AND(I$127>=$K25,I$127<=$L25),$G25*(1+$H25)^(I$127-$B$5),0) -> 0.27936778 | J236: =IF(AND(J$127>=$K25,J$127<=$L25),$G25*(1+$H25)^(J$127-$B$5),0) -> 0.27936778 | ... BJ236: =IF(AND(BJ$127>=$K25,BJ$127<=$L25),$G25*(1+$H25)^(BJ$127-$B$5),0) -> 0
A237: =A26 -> project 7 | C237: =IF(AND(C$127>=$K26,C$127<=$L26),$G26*(1+$H26)^(C$127-$B$5),0) -> 0 | D237: =IF(AND(D$127>=$K26,D$127<=$L26),$G26*(1+$H26)^(D$127-$B$5),0) -> 0 | E237: =IF(AND(E$127>=$K26,E$127<=$L26),$G26*(1+$H26)^(E$127-$B$5),0) -> 0 | F237: =IF(AND(F$127>=$K26,F$127<=$L26),$G26*(1+$H26)^(F$127-$B$5),0) -> 0 | G237: =IF(AND(G$127>=$K26,G$127<=$L26),$G26*(1+$H26)^(G$127-$B$5),0) -> 0 | H237: =IF(AND(H$127>=$K26,H$127<=$L26),$G26*(1+$H26)^(H$127-$B$5),0) -> 0 | I237: =IF(AND(I$127>=$K26,I$127<=$L26),$G26*(1+$H26)^(I$127-$B$5),0) -> 0 | J237: =IF(AND(J$127>=$K26,J$127<=$L26),$G26*(1+$H26)^(J$127-$B$5),0) -> 0 | ... BJ237: =IF(AND(BJ$127>=$K26,BJ$127<=$L26),$G26*(1+$H26)^(BJ$127-$B$5),0) -> 0
A238: =A27 -> project 8 | C238: =IF(AND(C$127>=$K27,C$127<=$L27),$G27*(1+$H27)^(C$127-$B$5),0) -> 0 | D238: =IF(AND(D$127>=$K27,D$127<=$L27),$G27*(1+$H27)^(D$127-$B$5),0) -> 0 | E238: =IF(AND(E$127>=$K27,E$127<=$L27),$G27*(1+$H27)^(E$127-$B$5),0) -> 0 | F238: =IF(AND(F$127>=$K27,F$127<=$L27),$G27*(1+$H27)^(F$127-$B$5),0) -> 0 | G238: =IF(AND(G$127>=$K27,G$127<=$L27),$G27*(1+$H27)^(G$127-$B$5),0) -> 0 | H238: =IF(AND(H$127>=$K27,H$127<=$L27),$G27*(1+$H27)^(H$127-$B$5),0) -> 0 | I238: =IF(AND(I$127>=$K27,I$127<=$L27),$G27*(1+$H27)^(I$127-$B$5),0) -> 0 | J238: =IF(AND(J$127>=$K27,J$127<=$L27),$G27*(1+$H27)^(J$127-$B$5),0) -> 0 | ... BJ238: =IF(AND(BJ$127>=$K27,BJ$127<=$L27),$G27*(1+$H27)^(BJ$127-$B$5),0) -> 0
A239: =A28 -> project 9 | C239: =IF(AND(C$127>=$K28,C$127<=$L28),$G28*(1+$H28)^(C$127-$B$5),0) -> 0 | D239: =IF(AND(D$127>=$K28,D$127<=$L28),$G28*(1+$H28)^(D$127-$B$5),0) -> 0 | E239: =IF(AND(E$127>=$K28,E$127<=$L28),$G28*(1+$H28)^(E$127-$B$5),0) -> 0 | F239: =IF(AND(F$127>=$K28,F$127<=$L28),$G28*(1+$H28)^(F$127-$B$5),0) -> 0 | G239: =IF(AND(G$127>=$K28,G$127<=$L28),$G28*(1+$H28)^(G$127-$B$5),0) -> 0 | H239: =IF(AND(H$127>=$K28,H$127<=$L28),$G28*(1+$H28)^(H$127-$B$5),0) -> 0 | I239: =IF(AND(I$127>=$K28,I$127<=$L28),$G28*(1+$H28)^(I$127-$B$5),0) -> 0 | J239: =IF(AND(J$127>=$K28,J$127<=$L28),$G28*(1+$H28)^(J$127-$B$5),0) -> 0 | ... BJ239: =IF(AND(BJ$127>=$K28,BJ$127<=$L28),$G28*(1+$H28)^(BJ$127-$B$5),0) -> 0
A240: =A29 -> project 12 | C240: =IF(AND(C$127>=$K29,C$127<=$L29),$G29*(1+$H29)^(C$127-$B$5),0) -> 0 | D240: =IF(AND(D$127>=$K29,D$127<=$L29),$G29*(1+$H29)^(D$127-$B$5),0) -> 0 | E240: =IF(AND(E$127>=$K29,E$127<=$L29),$G29*(1+$H29)^(E$127-$B$5),0) -> 0.22790138 | F240: =IF(AND(F$127>=$K29,F$127<=$L29),$G29*(1+$H29)^(F$127-$B$5),0) -> 0.22790138 | G240: =IF(AND(G$127>=$K29,G$127<=$L29),$G29*(1+$H29)^(G$127-$B$5),0) -> 0.22790138 | H240: =IF(AND(H$127>=$K29,H$127<=$L29),$G29*(1+$H29)^(H$127-$B$5),0) -> 0.22790138 | I240: =IF(AND(I$127>=$K29,I$127<=$L29),$G29*(1+$H29)^(I$127-$B$5),0) -> 0.22790138 | J240: =IF(AND(J$127>=$K29,J$127<=$L29),$G29*(1+$H29)^(J$127-$B$5),0) -> 0.22790138 | ... BJ240: =IF(AND(BJ$127>=$K29,BJ$127<=$L29),$G29*(1+$H29)^(BJ$127-$B$5),0) -> 0
A241: =A30 -> project 16 | C241: =IF(AND(C$127>=$K30,C$127<=$L30),$G30*(1+$H30)^(C$127-$B$5),0) -> 0 | D241: =IF(AND(D$127>=$K30,D$127<=$L30),$G30*(1+$H30)^(D$127-$B$5),0) -> 0 | E241: =IF(AND(E$127>=$K30,E$127<=$L30),$G30*(1+$H30)^(E$127-$B$5),0) -> 0 | F241: =IF(AND(F$127>=$K30,F$127<=$L30),$G30*(1+$H30)^(F$127-$B$5),0) -> 0 | G241: =IF(AND(G$127>=$K30,G$127<=$L30),$G30*(1+$H30)^(G$127-$B$5),0) -> 0 | H241: =IF(AND(H$127>=$K30,H$127<=$L30),$G30*(1+$H30)^(H$127-$B$5),0) -> 0 | I241: =IF(AND(I$127>=$K30,I$127<=$L30),$G30*(1+$H30)^(I$127-$B$5),0) -> 0 | J241: =IF(AND(J$127>=$K30,J$127<=$L30),$G30*(1+$H30)^(J$127-$B$5),0) -> 0 | ... BJ241: =IF(AND(BJ$127>=$K30,BJ$127<=$L30),$G30*(1+$H30)^(BJ$127-$B$5),0) -> 0
